{
  "items": [
    {
      "id": "ac_0_vita_5_mana_100_level_0_path_peasant_crafts_alchemy_max_held_in_1_slot_1_uses_50_effect_restores_100_mana_takes_5_vita_merchant_suggested_price_minimum_0_maximum_0_other_uses_crafts_how_to_obtain_potion_shops_comments_none_shop_prices_npc_sells_150_npc_buys_75",
      "name": "AC : 0 Vita : -5 Mana : 100 Level: 0 Path: Peasant Crafts: Alchemy Max. Held in 1 Slot: 1 Uses: 50 Effect: Restores 100 mana, takes 5 vita Merchant suggested price: Minimum: 0 Maximum: 0 Other Uses: Crafts How to Obtain: Potion Shops Comments: None Shop prices: NPC Sells: 150 NPC Buys: 75",
      "category": "item",
      "path": [
        "Peasant"
      ],
      "level_tier": "",
      "stats": {
        "Vita": -5,
        "Mana": 100
      },
      "stack_size": 1,
      "crafts": [
        "Alchemy"
      ],
      "other_uses": [
        "Crafts"
      ],
      "effect": "Restores 100 mana, takes 5 vita",
      "obtain": [
        "Potion Shops"
      ],
      "npc_buys": 75
    },
    {
      "id": "ac_0_vita_5_mana_80_level_0_path_peasant_crafts_alchemy_max_held_in_1_slot_1_uses_50_effect_none_merchant_suggested_price_minimum_0_maximum_0_other_uses_crafts_how_to_obtain_potion_shops_comments_none_shop_prices_npc_sells_100_npc_buys_50",
      "name": "AC : 0 Vita : -5 Mana : 80 Level: 0 Path: Peasant Crafts: Alchemy Max. Held in 1 Slot: 1 Uses: 50 Effect: None Merchant suggested price: Minimum: 0 Maximum: 0 Other Uses: Crafts How to Obtain: Potion Shops Comments: None Shop prices: NPC Sells: 100 NPC Buys: 50",
      "category": "item",
      "path": [
        "Peasant"
      ],
      "level_tier": "",
      "stats": {
        "Vita": -5,
        "Mana": 80
      },
      "stack_size": 1,
      "crafts": [
        "Alchemy"
      ],
      "other_uses": [
        "Crafts"
      ],
      "obtain": [
        "Potion Shops"
      ],
      "npc_buys": 50
    },
    {
      "id": "ac_0_vita_0_mana_0_level_0_path_peasant_crafts_alchemy_max_held_in_1_slot_3_uses_1_effect_creates_dart_poison_merchant_suggested_price_minimum_0_maximum_0_other_uses_crafts_how_to_obtain_created_by_alchemists_comments_none_shop_prices_npc_sells_0_npc_buys_0",
      "name": "AC : 0 Vita : 0 Mana : 0 Level: 0 Path: Peasant Crafts: Alchemy Max. Held in 1 Slot: 3 Uses: 1 Effect: Creates dart poison Merchant suggested price: Minimum: 0 Maximum: 0 Other Uses: Crafts How to Obtain: Created by Alchemists Comments: None Shop prices: NPC Sells: 0 NPC Buys: 0",
      "category": "item",
      "path": [
        "Peasant"
      ],
      "level_tier": "",
      "stats": {
        "Vita": 0,
        "Mana": 0
      },
      "stack_size": 3,
      "crafts": [
        "Alchemy"
      ],
      "other_uses": [
        "Crafts"
      ],
      "effect": "Creates dart poison",
      "obtain": [
        "Created by Alchemists"
      ],
      "npc_buys": 0
    },
    {
      "id": "ac_0_vita_0_mana_0_level_0_path_peasant_crafts_farming_max_held_in_1_slot_1_uses_1_effect_used_for_cutting_wood_merchant_suggested_price_minimum_200_maximum_100_other_uses_crafts_how_to_obtain_shops_comments_used_for_cutting_wood_shop_prices_npc_sells_200_npc_buys_100",
      "name": "AC : 0 Vita : 0 Mana : 0 Level: 0 Path: Peasant Crafts: Farming Max. Held in 1 Slot: 1 Uses: 1 Effect: Used for cutting wood Merchant suggested price: Minimum: 200 Maximum: 100 Other Uses: Crafts How to Obtain: Shops Comments: Used for cutting wood Shop prices: NPC Sells: 200 NPC Buys: 100",
      "category": "item",
      "path": [
        "Peasant"
      ],
      "level_tier": "",
      "stats": {
        "Vita": 0,
        "Mana": 0
      },
      "stack_size": 1,
      "crafts": [
        "Farming"
      ],
      "other_uses": [
        "Crafts"
      ],
      "effect": "Used for cutting wood",
      "obtain": [
        "Shops"
      ],
      "comments": "Used for cutting wood",
      "npc_buys": 100
    },
    {
      "id": "ac_0_vita_0_mana_0_level_0_path_peasant_crafts_farming_max_held_in_1_slot_1_uses_1_effect_used_for_gathering_coconuts_merchant_suggested_price_minimum_200_maximum_100_other_uses_crafts_how_to_obtain_shops_comments_shop_prices_npc_sells_200_npc_buys_100",
      "name": "AC : 0 Vita : 0 Mana : 0 Level: 0 Path: Peasant Crafts: Farming Max. Held in 1 Slot: 1 Uses: 1 Effect: Used for gathering coconuts Merchant suggested price: Minimum: 200 Maximum: 100 Other Uses: Crafts How to Obtain: Shops Comments: Shop prices: NPC Sells: 200 NPC Buys: 100",
      "category": "item",
      "path": [
        "Peasant"
      ],
      "level_tier": "",
      "stats": {
        "Vita": 0,
        "Mana": 0
      },
      "stack_size": 1,
      "crafts": [
        "Farming"
      ],
      "other_uses": [
        "Crafts"
      ],
      "effect": "Used for gathering coconuts",
      "obtain": [
        "Shops"
      ],
      "comments": "Shop prices:",
      "npc_buys": 100
    },
    {
      "id": "ac_0_vita_0_mana_0_level_0_path_peasant_crafts_fishing_max_held_in_1_slot_1_uses_1_effect_vita_restoration_merchant_suggested_price_minimum_0_maximum_0_other_uses_how_to_obtain_fishing_comments_none_shop_prices_npc_sells_0_npc_buys_0",
      "name": "AC : 0 Vita : 0 Mana : 0 Level: 0 Path: Peasant Crafts: Fishing Max. Held in 1 Slot: 1 Uses: 1 Effect: Vita restoration Merchant suggested price: Minimum: 0 Maximum: 0 Other Uses: How to Obtain: Fishing Comments: None Shop prices: NPC Sells: 0 NPC Buys: 0",
      "category": "item",
      "path": [
        "Peasant"
      ],
      "level_tier": "",
      "stats": {
        "Vita": 0,
        "Mana": 0
      },
      "stack_size": 1,
      "crafts": [
        "Fishing"
      ],
      "other_uses": [
        "How to Obtain:"
      ],
      "effect": "Vita restoration",
      "obtain": [
        "Fishing"
      ],
      "npc_buys": 0
    },
    {
      "id": "ac_0_vita_0_mana_0_level_0_path_peasant_crafts_gemcutting_max_held_in_1_slot_100_uses_1_effect_none_merchant_suggested_price_minimum_0_maximum_0_other_uses_crafts_how_to_obtain_dropped_by_many_creatures_comments_none_shop_prices_npc_sells_0_npc_buys_0",
      "name": "AC : 0 Vita : 0 Mana : 0 Level: 0 Path: Peasant Crafts: Gemcutting Max. Held in 1 Slot: 100 Uses: 1 Effect: None Merchant suggested price: Minimum: 0 Maximum: 0 Other Uses: Crafts How to Obtain: Dropped by many creatures Comments: None Shop prices: NPC Sells: 0 NPC Buys: 0",
      "category": "item",
      "level_tier": "",
      "stats": {
        "Vita": 0,
        "Mana": 0
      },
      "stack_size": 100,
      "crafts": [
        "Gemcutting"
      ],
      "other_uses": [
        "Crafts"
      ],
      "effect": null,
      "obtain": [
        "Dropped by many creatures"
      ],
      "comments": null,
      "npc_buys": 0,
      "path": [
        "Peasant"
      ]
    },
    {
      "id": "ac_0_vita_0_mana_0_level_0_path_peasant_crafts_gemcutting_max_held_in_1_slot_20_uses_1_effect_none_merchant_suggested_price_minimum_0_maximum_0_other_uses_crafts_how_to_obtain_dropped_by_many_creatures_comments_none_shop_prices_npc_sells_0_npc_buys_0",
      "name": "AC : 0 Vita : 0 Mana : 0 Level: 0 Path: Peasant Crafts: Gemcutting Max. Held in 1 Slot: 20 Uses: 1 Effect: None Merchant suggested price: Minimum: 0 Maximum: 0 Other Uses: Crafts How to Obtain: Dropped by many creatures Comments: None Shop prices: NPC Sells: 0 NPC Buys: 0",
      "category": "item",
      "level_tier": "",
      "stats": {
        "Vita": 0,
        "Mana": 0
      },
      "stack_size": 20,
      "crafts": [
        "Gemcutting"
      ],
      "other_uses": [
        "Crafts"
      ],
      "effect": null,
      "obtain": [
        "Dropped by many creatures"
      ],
      "comments": null,
      "npc_buys": 0,
      "path": [
        "Peasant"
      ]
    },
    {
      "id": "ac_0_vita_0_mana_0_level_0_path_peasant_crafts_mining_max_held_in_1_slot_1_uses_1_effect_used_for_mining_merchant_suggested_price_minimum_20_maximum_40_other_uses_crafts_how_to_obtain_shops_comments_shop_prices_npc_sells_40_npc_buys_20",
      "name": "AC : 0 Vita : 0 Mana : 0 Level: 0 Path: Peasant Crafts: Mining Max. Held in 1 Slot: 1 Uses: 1 Effect: Used for mining Merchant suggested price: Minimum: 20 Maximum: 40 Other Uses: Crafts How to Obtain: Shops Comments: Shop prices: NPC Sells: 40 NPC Buys: 20",
      "category": "item",
      "path": [
        "Peasant"
      ],
      "level_tier": "",
      "stats": {
        "Vita": 0,
        "Mana": 0
      },
      "stack_size": 1,
      "crafts": [
        "Mining"
      ],
      "other_uses": [
        "Crafts"
      ],
      "effect": "Used for mining",
      "obtain": [
        "Shops"
      ],
      "comments": "Shop prices:",
      "npc_buys": 20
    },
    {
      "id": "ac_0_vita_0_mana_0_level_0_path_peasant_crafts_scribe_max_held_in_1_slot_1_uses_1_effect_needed_for_spells_and_the_scribe_craft_merchant_suggested_price_minimum_0_maximum_0_other_uses_needed_to_make_most_scrolls_how_to_obtain_buy_in_messenger_shops_comments_none_shop_prices_npc_sells_100_npc_buys_50",
      "name": "AC : 0 Vita : 0 Mana : 0 Level: 0 Path: Peasant Crafts: Scribe Max. Held in 1 Slot: 1 Uses: 1 Effect: Needed for spells and the Scribe craft Merchant suggested price: Minimum: 0 Maximum: 0 Other Uses: Needed to make most Scrolls How to Obtain: Buy in Messenger shops Comments: None Shop prices: NPC Sells: 100 NPC Buys: 50",
      "category": "item",
      "path": [
        "Peasant"
      ],
      "level_tier": "",
      "stats": {
        "Vita": 0,
        "Mana": 0
      },
      "stack_size": 1,
      "crafts": [
        "Scribe"
      ],
      "other_uses": [
        "Needed to make most Scrolls"
      ],
      "effect": "Needed for spells and the Scribe craft",
      "obtain": [
        "Buy in Messenger shops"
      ],
      "npc_buys": 50
    },
    {
      "id": "ac_0_vita_0_mana_0_level_0_path_peasant_crafts_scribe_max_held_in_1_slot_1_uses_1_effect_none_merchant_suggested_price_minimum_0_maximum_0_other_uses_needed_to_make_most_scrolls_how_to_obtain_buy_in_messenger_shops_comments_none_shop_prices_npc_sells_100_npc_buys_50",
      "name": "AC : 0 Vita : 0 Mana : 0 Level: 0 Path: Peasant Crafts: Scribe Max. Held in 1 Slot: 1 Uses: 1 Effect: None Merchant suggested price: Minimum: 0 Maximum: 0 Other Uses: Needed to make most Scrolls How to Obtain: Buy in Messenger shops Comments: None Shop prices: NPC Sells: 100 NPC Buys: 50",
      "category": "item",
      "path": [
        "Peasant"
      ],
      "level_tier": "",
      "stats": {
        "Vita": 0,
        "Mana": 0
      },
      "stack_size": 1,
      "crafts": [
        "Scribe"
      ],
      "other_uses": [
        "Needed to make most Scrolls"
      ],
      "obtain": [
        "Buy in Messenger shops"
      ],
      "npc_buys": 50
    },
    {
      "id": "ac_0_vita_0_mana_0_level_0_path_peasant_crafts_scribe_max_held_in_1_slot_1_uses_1_effect_none_merchant_suggested_price_minimum_0_maximum_0_other_uses_needed_to_make_scroll_of_defense_how_to_obtain_buy_in_kugnae_baek_s_shop_comments_none_shop_prices_npc_sells_5_000_npc_buys_2_500",
      "name": "AC : 0 Vita : 0 Mana : 0 Level: 0 Path: Peasant Crafts: Scribe Max. Held in 1 Slot: 1 Uses: 1 Effect: None Merchant suggested price: Minimum: 0 Maximum: 0 Other Uses: Needed to make Scroll of defense How to Obtain: Buy in Kugnae, Baek's shop Comments: None Shop prices: NPC Sells: 5,000 NPC Buys: 2,500",
      "category": "item",
      "path": [
        "Peasant"
      ],
      "level_tier": "",
      "stats": {
        "Vita": 0,
        "Mana": 0
      },
      "stack_size": 1,
      "crafts": [
        "Scribe"
      ],
      "other_uses": [
        "Needed to make Scroll of defense"
      ],
      "obtain": [
        "Buy in Kugnae, Baek's shop"
      ],
      "npc_buys": 2
    },
    {
      "id": "ac_0_vita_0_mana_0_level_0_path_peasant_crafts_scribe_max_held_in_1_slot_100_uses_1_effect_none_merchant_suggested_price_minimum_0_maximum_0_other_uses_crafts_how_to_obtain_dropped_by_many_creatures_comments_none_shop_prices_npc_sells_0_npc_buys_0",
      "name": "AC : 0 Vita : 0 Mana : 0 Level: 0 Path: Peasant Crafts: Scribe Max. Held in 1 Slot: 100 Uses: 1 Effect: None Merchant suggested price: Minimum: 0 Maximum: 0 Other Uses: Crafts How to Obtain: Dropped by many creatures Comments: None Shop prices: NPC Sells: 0 NPC Buys: 0",
      "category": "item",
      "level_tier": "",
      "stats": {
        "Vita": 0,
        "Mana": 0
      },
      "stack_size": 100,
      "crafts": [
        "Scribe"
      ],
      "other_uses": [
        "Crafts"
      ],
      "effect": null,
      "obtain": [
        "Dropped by many creatures"
      ],
      "comments": null,
      "npc_buys": 0,
      "path": [
        "Peasant"
      ]
    },
    {
      "id": "ac_0_vita_0_mana_0_level_0_path_peasant_crafts_woodcutting_max_held_in_1_slot_1_uses_1_effect_used_for_cutting_wood_merchant_suggested_price_minimum_50_maximum_50_other_uses_crafts_how_to_obtain_shops_comments_used_for_cutting_wood_shop_prices_npc_sells_50_npc_buys_25",
      "name": "AC : 0 Vita : 0 Mana : 0 Level: 0 Path: Peasant Crafts: Woodcutting Max. Held in 1 Slot: 1 Uses: 1 Effect: Used for cutting wood Merchant suggested price: Minimum: 50 Maximum: 50 Other Uses: Crafts How to Obtain: Shops Comments: Used for cutting wood Shop prices: NPC Sells: 50 NPC Buys: 25",
      "category": "item",
      "path": [
        "Peasant"
      ],
      "level_tier": "",
      "stats": {
        "Vita": 0,
        "Mana": 0
      },
      "stack_size": 1,
      "crafts": [
        "Woodcutting"
      ],
      "other_uses": [
        "Crafts"
      ],
      "effect": "Used for cutting wood",
      "obtain": [
        "Shops"
      ],
      "comments": "Used for cutting wood",
      "npc_buys": 25
    },
    {
      "id": "ac_0_vita_100_mana_0_level_0_path_peasant_crafts_chef_max_held_in_1_slot_25_uses_1_effect_vita_restoration_merchant_suggested_price_minimum_0_maximum_0_other_uses_none_how_to_obtain_made_by_chefs_comments_none_shop_prices_npc_sells_0_npc_buys_0",
      "name": "AC : 0 Vita : 100 Mana : 0 Level: 0 Path: Peasant Crafts: Chef Max. Held in 1 Slot: 25 Uses: 1 Effect: Vita restoration Merchant suggested price: Minimum: 0 Maximum: 0 Other Uses: None How to Obtain: Made by chefs Comments: None Shop prices: NPC Sells: 0 NPC Buys: 0",
      "category": "item",
      "path": [
        "Peasant"
      ],
      "level_tier": "",
      "stats": {
        "Vita": 100,
        "Mana": 0
      },
      "stack_size": 25,
      "crafts": [
        "Chef"
      ],
      "effect": "Vita restoration",
      "obtain": [
        "Made by chefs"
      ],
      "npc_buys": 0
    },
    {
      "id": "ac_0_vita_100_mana_0_level_0_path_peasant_crafts_fishing_max_held_in_1_slot_10_uses_1_effect_vita_restoration_merchant_suggested_price_minimum_0_maximum_0_other_uses_needed_for_food_preparation_skill_how_to_obtain_fishing_comments_none_shop_prices_npc_sells_0_npc_buys_0",
      "name": "AC : 0 Vita : 100 Mana : 0 Level: 0 Path: Peasant Crafts: Fishing Max. Held in 1 Slot: 10 Uses: 1 Effect: Vita restoration Merchant suggested price: Minimum: 0 Maximum: 0 Other Uses: Needed for food preparation skill How to Obtain: Fishing Comments: None Shop prices: NPC Sells: 0 NPC Buys: 0",
      "category": "item",
      "level_tier": "",
      "stats": {
        "Vita": 100,
        "Mana": 0
      },
      "stack_size": 10,
      "crafts": [
        "Fishing"
      ],
      "other_uses": [
        "Needed for food preparation skill"
      ],
      "effect": "Vita restoration",
      "obtain": [
        "Fishing"
      ],
      "comments": null,
      "npc_buys": 0,
      "path": [
        "Peasant"
      ]
    },
    {
      "id": "ac_0_vita_100_mana_0_level_0_path_peasant_crafts_food_preparation_max_held_in_1_slot_10_uses_1_effect_vita_restoration_merchant_suggested_price_minimum_0_maximum_0_other_uses_needed_for_food_preparation_skill_how_to_obtain_fishing_comments_none_shop_prices_npc_sells_0_npc_buys_0",
      "name": "AC : 0 Vita : 100 Mana : 0 Level: 0 Path: Peasant Crafts: Food preparation Max. Held in 1 Slot: 10 Uses: 1 Effect: Vita restoration Merchant suggested price: Minimum: 0 Maximum: 0 Other Uses: Needed for food preparation skill How to Obtain: Fishing Comments: None Shop prices: NPC Sells: 0 NPC Buys: 0",
      "category": "item",
      "path": [
        "Peasant"
      ],
      "level_tier": "",
      "stats": {
        "Vita": 100,
        "Mana": 0
      },
      "stack_size": 10,
      "crafts": [
        "Food preparation"
      ],
      "other_uses": [
        "Needed for food preparation skill"
      ],
      "effect": "Vita restoration",
      "obtain": [
        "Fishing"
      ],
      "npc_buys": 0
    },
    {
      "id": "ac_0_vita_100_mana_0_level_0_path_peasant_crafts_food_preparation_max_held_in_1_slot_10_uses_1_effect_vita_restoration_merchant_suggested_price_minimum_0_maximum_0_other_uses_subpath_quest_item_how_to_obtain_dropped_by_iron_lab_tigers_comments_none_shop_prices_npc_sells_100_npc_buys_50",
      "name": "AC : 0 Vita : 100 Mana : 0 Level: 0 Path: Peasant Crafts: Food preparation Max. Held in 1 Slot: 10 Uses: 1 Effect: Vita restoration Merchant suggested price: Minimum: 0 Maximum: 0 Other Uses: Subpath quest item How to Obtain: Dropped by Iron lab tigers Comments: None Shop prices: NPC Sells: 100 NPC Buys: 50",
      "category": "item",
      "path": [
        "Peasant"
      ],
      "level_tier": "",
      "stats": {
        "Vita": 100,
        "Mana": 0
      },
      "stack_size": 10,
      "crafts": [
        "Food preparation"
      ],
      "other_uses": [
        "Subpath quest item"
      ],
      "effect": "Vita restoration",
      "obtain": [
        "Dropped by Iron lab tigers"
      ],
      "npc_buys": 50
    },
    {
      "id": "ac_0_vita_100_mana_0_level_0_path_peasant_crafts_food_preparation_max_held_in_1_slot_12_uses_1_effect_vita_restoration_merchant_suggested_price_minimum_0_maximum_0_other_uses_made_by_food_preparation_how_to_obtain_none_comments_none_shop_prices_npc_sells_0_npc_buys_0",
      "name": "AC : 0 Vita : 100 Mana : 0 Level: 0 Path: Peasant Crafts: Food preparation Max. Held in 1 Slot: 12 Uses: 1 Effect: Vita restoration Merchant suggested price: Minimum: 0 Maximum: 0 Other Uses: Made by food preparation How to Obtain: None Comments: None Shop prices: NPC Sells: 0 NPC Buys: 0",
      "category": "item",
      "path": [
        "Peasant"
      ],
      "level_tier": "",
      "stats": {
        "Vita": 100,
        "Mana": 0
      },
      "stack_size": 12,
      "crafts": [
        "Food preparation"
      ],
      "other_uses": [
        "Made by food preparation"
      ],
      "effect": "Vita restoration",
      "obtain": [
        "None"
      ],
      "npc_buys": 0
    },
    {
      "id": "ac_0_vita_100_mana_0_level_0_path_peasant_crafts_food_preparation_max_held_in_1_slot_30_uses_1_effect_vita_merchant_suggested_price_minimum_0_maximum_0_other_uses_needed_for_food_preparation_skill_how_to_obtain_dropped_by_pheasants_in_the_woodlands_comments_none_shop_prices_npc_sells_0_npc_buys_0",
      "name": "AC : 0 Vita : 100 Mana : 0 Level: 0 Path: Peasant Crafts: Food preparation Max. Held in 1 Slot: 30 Uses: 1 Effect: Vita Merchant suggested price: Minimum: 0 Maximum: 0 Other Uses: Needed for food preparation skill How to Obtain: Dropped by Pheasants in the Woodlands Comments: None Shop prices: NPC Sells: 0 NPC Buys: 0",
      "category": "item",
      "path": [
        "Peasant"
      ],
      "level_tier": "",
      "stats": {
        "Vita": 100,
        "Mana": 0
      },
      "stack_size": 30,
      "crafts": [
        "Food preparation"
      ],
      "other_uses": [
        "Needed for food preparation skill"
      ],
      "effect": "Vita",
      "obtain": [
        "Dropped by Pheasants in the Woodlands"
      ],
      "npc_buys": 0
    },
    {
      "id": "ac_0_vita_100_mana_0_level_0_path_peasant_crafts_gardening_max_held_in_1_slot_5_uses_1_effect_vita_restoration_merchant_suggested_price_minimum_0_maximum_0_other_uses_none_how_to_obtain_none_comments_dug_from_kugnae_and_wilderness_gardens_shop_prices_npc_sells_0_npc_buys_0",
      "name": "AC : 0 Vita : 100 Mana : 0 Level: 0 Path: Peasant Crafts: Gardening Max. Held in 1 Slot: 5 Uses: 1 Effect: Vita restoration Merchant suggested price: Minimum: 0 Maximum: 0 Other Uses: None How to Obtain: None Comments: Dug from Kugnae and Wilderness Gardens Shop prices: NPC Sells: 0 NPC Buys: 0",
      "category": "item",
      "path": [
        "Peasant"
      ],
      "level_tier": "",
      "stats": {
        "Vita": 100,
        "Mana": 0
      },
      "stack_size": 5,
      "crafts": [
        "Gardening"
      ],
      "effect": "Vita restoration",
      "obtain": [
        "None"
      ],
      "comments": "Dug from Kugnae and Wilderness Gardens",
      "npc_buys": 0
    },
    {
      "id": "ac_0_vita_1000_mana_0_level_0_path_peasant_crafts_food_preparation_max_held_in_1_slot_25_uses_1_effect_vita_restoration_merchant_suggested_price_minimum_0_maximum_0_other_uses_none_how_to_obtain_food_preparers_comments_prepared_from_bird_or_chicken_meat_by_players_with_food_preparation_skill_shop_prices_npc_sells_0_npc_buys_0",
      "name": "AC : 0 Vita : 1000 Mana : 0 Level: 0 Path: Peasant Crafts: Food preparation Max. Held in 1 Slot: 25 Uses: 1 Effect: Vita restoration Merchant suggested price: Minimum: 0 Maximum: 0 Other Uses: None How to Obtain: Food preparers Comments: Prepared from Bird or Chicken meat by players with Food preparation skill. Shop prices: NPC Sells: 0 NPC Buys: 0",
      "category": "item",
      "path": [
        "Peasant"
      ],
      "level_tier": "",
      "stats": {
        "Vita": 1000,
        "Mana": 0
      },
      "stack_size": 25,
      "crafts": [
        "Food preparation"
      ],
      "effect": "Vita restoration",
      "obtain": [
        "Food preparers"
      ],
      "comments": "Prepared from Bird or Chicken meat by players with Food preparation skill.",
      "npc_buys": 0
    },
    {
      "id": "ac_0_vita_1000_mana_0_level_0_path_peasant_crafts_food_preparation_max_held_in_1_slot_25_uses_1_effect_vita_restoration_merchant_suggested_price_minimum_0_maximum_0_other_uses_none_how_to_obtain_made_by_food_preparers_comments_none_shop_prices_npc_sells_0_npc_buys_0",
      "name": "AC : 0 Vita : 1000 Mana : 0 Level: 0 Path: Peasant Crafts: Food preparation Max. Held in 1 Slot: 25 Uses: 1 Effect: Vita restoration Merchant suggested price: Minimum: 0 Maximum: 0 Other Uses: None How to Obtain: Made by food preparers Comments: None Shop prices: NPC Sells: 0 NPC Buys: 0",
      "category": "item",
      "path": [
        "Peasant"
      ],
      "level_tier": "",
      "stats": {
        "Vita": 1000,
        "Mana": 0
      },
      "stack_size": 25,
      "crafts": [
        "Food preparation"
      ],
      "effect": "Vita restoration",
      "obtain": [
        "Made by food preparers"
      ],
      "npc_buys": 0
    },
    {
      "id": "ac_0_vita_1500_mana_0_level_0_path_peasant_crafts_food_preparation_max_held_in_1_slot_10_uses_1_effect_vita_restoration_merchant_suggested_price_minimum_0_maximum_0_other_uses_none_how_to_obtain_cooking_tiger_meat_comments_made_from_tiger_meat_but_barbarians_may_be_forced_to_hurt_you_if_you_cook_this_shop_prices_npc_sells_0_npc_buys_0",
      "name": "AC : 0 Vita : 1500 Mana : 0 Level: 0 Path: Peasant Crafts: Food preparation Max. Held in 1 Slot: 10 Uses: 1 Effect: Vita restoration Merchant suggested price: Minimum: 0 Maximum: 0 Other Uses: None How to Obtain: Cooking Tiger meat. Comments: Made from Tiger meat but Barbarians may be forced to hurt you if you cook this! Shop prices: NPC Sells: 0 NPC Buys: 0",
      "category": "item",
      "path": [
        "Peasant"
      ],
      "level_tier": "",
      "stats": {
        "Vita": 1500,
        "Mana": 0
      },
      "stack_size": 10,
      "crafts": [
        "Food preparation"
      ],
      "effect": "Vita restoration",
      "obtain": [
        "Cooking Tiger meat."
      ],
      "comments": "Made from Tiger meat but Barbarians may be forced to hurt you if you cook this!",
      "npc_buys": 0
    },
    {
      "id": "ac_0_vita_180_mana_0_level_0_path_peasant_crafts_fishing_max_held_in_1_slot_10_uses_1_effect_vita_restoration_merchant_suggested_price_minimum_0_maximum_0_other_uses_needed_for_food_preparation_skill_how_to_obtain_fishing_comments_none_shop_prices_npc_sells_0_npc_buys_0",
      "name": "AC : 0 Vita : 180 Mana : 0 Level: 0 Path: Peasant Crafts: Fishing Max. Held in 1 Slot: 10 Uses: 1 Effect: Vita restoration Merchant suggested price: Minimum: 0 Maximum: 0 Other Uses: Needed for food preparation skill How to Obtain: Fishing Comments: None Shop prices: NPC Sells: 0 NPC Buys: 0",
      "category": "item",
      "level_tier": "",
      "stats": {
        "Vita": 180,
        "Mana": 0
      },
      "stack_size": 10,
      "crafts": [
        "Fishing"
      ],
      "other_uses": [
        "Needed for food preparation skill"
      ],
      "effect": "Vita restoration",
      "obtain": [
        "Fishing"
      ],
      "comments": null,
      "npc_buys": 0,
      "path": [
        "Peasant"
      ]
    },
    {
      "id": "ac_0_vita_180_mana_0_level_0_path_peasant_crafts_food_preparation_max_held_in_1_slot_10_uses_1_effect_vita_restoration_merchant_suggested_price_minimum_0_maximum_0_other_uses_needed_for_food_preparation_skill_how_to_obtain_fishing_comments_none_shop_prices_npc_sells_0_npc_buys_0",
      "name": "AC : 0 Vita : 180 Mana : 0 Level: 0 Path: Peasant Crafts: Food preparation Max. Held in 1 Slot: 10 Uses: 1 Effect: Vita restoration Merchant suggested price: Minimum: 0 Maximum: 0 Other Uses: Needed for food preparation skill How to Obtain: Fishing Comments: None Shop prices: NPC Sells: 0 NPC Buys: 0",
      "category": "item",
      "path": [
        "Peasant"
      ],
      "level_tier": "",
      "stats": {
        "Vita": 180,
        "Mana": 0
      },
      "stack_size": 10,
      "crafts": [
        "Food preparation"
      ],
      "other_uses": [
        "Needed for food preparation skill"
      ],
      "effect": "Vita restoration",
      "obtain": [
        "Fishing"
      ],
      "npc_buys": 0
    },
    {
      "id": "ac_0_vita_20_mana_0_level_0_path_peasant_crafts_food_preparation_max_held_in_1_slot_100_uses_1_effect_none_merchant_suggested_price_minimum_0_maximum_0_other_uses_none_how_to_obtain_mythic_oxen_kugnae_mud_snake_comments_none_shop_prices_npc_sells_0_npc_buys_0",
      "name": "AC : 0 Vita : 20 Mana : 0 Level: 0 Path: Peasant Crafts: Food preparation Max. Held in 1 Slot: 100 Uses: 1 Effect: None Merchant suggested price: Minimum: 0 Maximum: 0 Other Uses: None How to Obtain: Mythic Oxen, Kugnae Mud Snake Comments: None Shop prices: NPC Sells: 0 NPC Buys: 0",
      "category": "item",
      "path": [
        "Peasant"
      ],
      "level_tier": "",
      "stats": {
        "Vita": 20,
        "Mana": 0
      },
      "stack_size": 100,
      "crafts": [
        "Food preparation"
      ],
      "obtain": [
        "Mythic Oxen, Kugnae Mud Snake"
      ],
      "npc_buys": 0
    },
    {
      "id": "ac_0_vita_248_mana_0_level_0_path_peasant_crafts_alchemy_max_held_in_1_slot_52_uses_1_effect_restores_248_vitaused_by_alchemists_merchant_suggested_price_minimum_0_maximum_0_other_uses_crafts_how_to_obtain_arena_shops_dropped_by_deers_comments_none_shop_prices_npc_sells_10_npc_buys_5",
      "name": "AC : 0 Vita : 248 Mana : 0 Level: 0 Path: Peasant Crafts: Alchemy Max. Held in 1 Slot: 52 Uses: 1 Effect: Restores 248 vitaUsed by Alchemists Merchant suggested price: Minimum: 0 Maximum: 0 Other Uses: Crafts How to Obtain: Arena Shops, Dropped by Deers Comments: None Shop prices: NPC Sells: 10 NPC Buys: 5",
      "category": "item",
      "path": [
        "Peasant"
      ],
      "level_tier": "",
      "stats": {
        "Vita": 248,
        "Mana": 0
      },
      "stack_size": 52,
      "crafts": [
        "Alchemy"
      ],
      "other_uses": [
        "Crafts"
      ],
      "effect": "Restores 248 vitaUsed by Alchemists",
      "obtain": [
        "Arena Shops, Dropped by Deers"
      ],
      "npc_buys": 5
    },
    {
      "id": "ac_0_vita_300_mana_0_level_0_path_peasant_crafts_chef_max_held_in_1_slot_1_uses_1_effect_vita_restoration_merchant_suggested_price_minimum_0_maximum_0_other_uses_none_how_to_obtain_none_comments_prepared_from_salt_block_water_jug_and_flour_by_players_with_food_preparation_skill_shop_prices_npc_sells_0_npc_buys_0",
      "name": "AC : 0 Vita : 300 Mana : 0 Level: 0 Path: Peasant Crafts: Chef Max. Held in 1 Slot: 1 Uses: 1 Effect: Vita restoration Merchant suggested price: Minimum: 0 Maximum: 0 Other Uses: None How to Obtain: None Comments: Prepared from Salt Block, Water Jug, and Flour by players with Food preparation skill. Shop prices: NPC Sells: 0 NPC Buys: 0",
      "category": "item",
      "path": [
        "Peasant"
      ],
      "level_tier": "",
      "stats": {
        "Vita": 300,
        "Mana": 0
      },
      "stack_size": 1,
      "crafts": [
        "Chef"
      ],
      "effect": "Vita restoration",
      "obtain": [
        "None"
      ],
      "comments": "Prepared from Salt Block, Water Jug, and Flour by players with Food preparation skill.",
      "npc_buys": 0
    },
    {
      "id": "ac_0_vita_320_mana_0_level_0_path_peasant_crafts_alchemy_max_held_in_1_slot_40_uses_1_effect_vita_restoration_merchant_suggested_price_minimum_0_maximum_0_other_uses_alchemy_lime_potions_how_to_obtain_mythic_snakes_comments_none_shop_prices_npc_sells_0_npc_buys_0",
      "name": "AC : 0 Vita : 320 Mana : 0 Level: 0 Path: Peasant Crafts: Alchemy Max. Held in 1 Slot: 40 Uses: 1 Effect: Vita restoration Merchant suggested price: Minimum: 0 Maximum: 0 Other Uses: Alchemy - lime potions How to Obtain: Mythic Snakes Comments: None Shop prices: NPC Sells: 0 NPC Buys: 0",
      "category": "item",
      "path": [
        "Peasant"
      ],
      "level_tier": "",
      "stats": {
        "Vita": 320,
        "Mana": 0
      },
      "stack_size": 40,
      "crafts": [
        "Alchemy"
      ],
      "other_uses": [
        "Alchemy - lime potions"
      ],
      "effect": "Vita restoration",
      "obtain": [
        "Mythic Snakes"
      ],
      "npc_buys": 0
    },
    {
      "id": "ac_0_vita_360_mana_0_level_0_path_peasant_crafts_fishing_max_held_in_1_slot_10_uses_1_effect_vita_restoration_merchant_suggested_price_minimum_0_maximum_0_other_uses_needed_for_food_preparation_skill_how_to_obtain_fishing_comments_none_shop_prices_npc_sells_0_npc_buys_0",
      "name": "AC : 0 Vita : 360 Mana : 0 Level: 0 Path: Peasant Crafts: Fishing Max. Held in 1 Slot: 10 Uses: 1 Effect: Vita restoration Merchant suggested price: Minimum: 0 Maximum: 0 Other Uses: Needed for food preparation skill How to Obtain: Fishing Comments: None Shop prices: NPC Sells: 0 NPC Buys: 0",
      "category": "item",
      "level_tier": "",
      "stats": {
        "Vita": 360,
        "Mana": 0
      },
      "stack_size": 10,
      "crafts": [
        "Fishing"
      ],
      "other_uses": [
        "Needed for food preparation skill"
      ],
      "effect": "Vita restoration",
      "obtain": [
        "Fishing"
      ],
      "comments": null,
      "npc_buys": 0,
      "path": [
        "Peasant"
      ]
    },
    {
      "id": "ac_0_vita_360_mana_0_level_0_path_peasant_crafts_food_preparation_max_held_in_1_slot_10_uses_1_effect_vita_restoration_merchant_suggested_price_minimum_0_maximum_0_other_uses_needed_for_food_preparation_skill_how_to_obtain_fishing_comments_none_shop_prices_npc_sells_0_npc_buys_0",
      "name": "AC : 0 Vita : 360 Mana : 0 Level: 0 Path: Peasant Crafts: Food preparation Max. Held in 1 Slot: 10 Uses: 1 Effect: Vita restoration Merchant suggested price: Minimum: 0 Maximum: 0 Other Uses: Needed for food preparation skill How to Obtain: Fishing Comments: None Shop prices: NPC Sells: 0 NPC Buys: 0",
      "category": "item",
      "path": [
        "Peasant"
      ],
      "level_tier": "",
      "stats": {
        "Vita": 360,
        "Mana": 0
      },
      "stack_size": 10,
      "crafts": [
        "Food preparation"
      ],
      "other_uses": [
        "Needed for food preparation skill"
      ],
      "effect": "Vita restoration",
      "obtain": [
        "Fishing"
      ],
      "npc_buys": 0
    },
    {
      "id": "ac_0_vita_40_mana_0_level_0_path_peasant_crafts_food_preparation_max_held_in_1_slot_30_uses_1_effect_vita_restoration_merchant_suggested_price_minimum_0_maximum_0_other_uses_food_preparation_skill_how_to_obtain_none_comments_dropped_by_various_chicken_creatures_shop_prices_npc_sells_0_npc_buys_0",
      "name": "AC : 0 Vita : 40 Mana : 0 Level: 0 Path: Peasant Crafts: Food preparation Max. Held in 1 Slot: 30 Uses: 1 Effect: Vita restoration Merchant suggested price: Minimum: 0 Maximum: 0 Other Uses: Food preparation skill How to Obtain: None Comments: Dropped by various chicken creatures Shop prices: NPC Sells: 0 NPC Buys: 0",
      "category": "item",
      "path": [
        "Peasant"
      ],
      "level_tier": "",
      "stats": {
        "Vita": 40,
        "Mana": 0
      },
      "stack_size": 30,
      "crafts": [
        "Food preparation"
      ],
      "other_uses": [
        "Food preparation skill"
      ],
      "effect": "Vita restoration",
      "obtain": [
        "None"
      ],
      "comments": "Dropped by various chicken creatures",
      "npc_buys": 0
    },
    {
      "id": "ac_0_vita_400_mana_0_level_0_path_peasant_crafts_fishing_max_held_in_1_slot_10_uses_1_effect_vita_restoration_merchant_suggested_price_minimum_0_maximum_0_other_uses_needed_for_food_preparation_skill_how_to_obtain_fishing_comments_none_shop_prices_npc_sells_0_npc_buys_0",
      "name": "AC : 0 Vita : 400 Mana : 0 Level: 0 Path: Peasant Crafts: Fishing Max. Held in 1 Slot: 10 Uses: 1 Effect: Vita restoration Merchant suggested price: Minimum: 0 Maximum: 0 Other Uses: Needed for food preparation skill How to Obtain: Fishing Comments: None Shop prices: NPC Sells: 0 NPC Buys: 0",
      "category": "item",
      "level_tier": "",
      "stats": {
        "Vita": 400,
        "Mana": 0
      },
      "stack_size": 10,
      "crafts": [
        "Fishing"
      ],
      "other_uses": [
        "Needed for food preparation skill"
      ],
      "effect": "Vita restoration",
      "obtain": [
        "Fishing"
      ],
      "comments": null,
      "npc_buys": 0,
      "path": [
        "Peasant"
      ]
    },
    {
      "id": "ac_0_vita_400_mana_0_level_0_path_peasant_crafts_food_preparation_max_held_in_1_slot_10_uses_1_effect_vita_restoration_merchant_suggested_price_minimum_0_maximum_0_other_uses_needed_for_food_preparation_skill_how_to_obtain_fishing_comments_none_shop_prices_npc_sells_0_npc_buys_0",
      "name": "AC : 0 Vita : 400 Mana : 0 Level: 0 Path: Peasant Crafts: Food preparation Max. Held in 1 Slot: 10 Uses: 1 Effect: Vita restoration Merchant suggested price: Minimum: 0 Maximum: 0 Other Uses: Needed for food preparation skill How to Obtain: Fishing Comments: None Shop prices: NPC Sells: 0 NPC Buys: 0",
      "category": "item",
      "path": [
        "Peasant"
      ],
      "level_tier": "",
      "stats": {
        "Vita": 400,
        "Mana": 0
      },
      "stack_size": 10,
      "crafts": [
        "Food preparation"
      ],
      "other_uses": [
        "Needed for food preparation skill"
      ],
      "effect": "Vita restoration",
      "obtain": [
        "Fishing"
      ],
      "npc_buys": 0
    },
    {
      "id": "ac_0_vita_440_mana_0_level_0_path_peasant_crafts_fishing_max_held_in_1_slot_10_uses_1_effect_vita_restoration_merchant_suggested_price_minimum_0_maximum_0_other_uses_needed_for_food_preparation_skill_how_to_obtain_fishing_comments_none_shop_prices_npc_sells_0_npc_buys_0",
      "name": "AC : 0 Vita : 440 Mana : 0 Level: 0 Path: Peasant Crafts: Fishing Max. Held in 1 Slot: 10 Uses: 1 Effect: Vita restoration Merchant suggested price: Minimum: 0 Maximum: 0 Other Uses: Needed for food preparation skill How to Obtain: Fishing Comments: None Shop prices: NPC Sells: 0 NPC Buys: 0",
      "category": "item",
      "level_tier": "",
      "stats": {
        "Vita": 440,
        "Mana": 0
      },
      "stack_size": 10,
      "crafts": [
        "Fishing"
      ],
      "other_uses": [
        "Needed for food preparation skill"
      ],
      "effect": "Vita restoration",
      "obtain": [
        "Fishing"
      ],
      "comments": null,
      "npc_buys": 0,
      "path": [
        "Peasant"
      ]
    },
    {
      "id": "ac_0_vita_500_mana_0_level_0_path_peasant_crafts_food_preparation_max_held_in_1_slot_50_uses_1_effect_vita_restoration_merchant_suggested_price_minimum_0_maximum_0_other_uses_needed_for_food_preparation_skill_how_to_obtain_mythic_oxen_kugnae_mud_snake_comments_none_shop_prices_npc_sells_0_npc_buys_0",
      "name": "AC : 0 Vita : 500 Mana : 0 Level: 0 Path: Peasant Crafts: Food preparation Max. Held in 1 Slot: 50 Uses: 1 Effect: Vita restoration Merchant suggested price: Minimum: 0 Maximum: 0 Other Uses: Needed for food preparation skill How to Obtain: Mythic Oxen, Kugnae Mud Snake Comments: None Shop prices: NPC Sells: 0 NPC Buys: 0",
      "category": "item",
      "path": [
        "Peasant"
      ],
      "level_tier": "",
      "stats": {
        "Vita": 500,
        "Mana": 0
      },
      "stack_size": 50,
      "crafts": [
        "Food preparation"
      ],
      "other_uses": [
        "Needed for food preparation skill"
      ],
      "effect": "Vita restoration",
      "obtain": [
        "Mythic Oxen, Kugnae Mud Snake"
      ],
      "npc_buys": 0
    },
    {
      "id": "ac_0_vita_540_mana_0_level_0_path_peasant_crafts_fishing_max_held_in_1_slot_10_uses_1_effect_vita_restoration_merchant_suggested_price_minimum_0_maximum_0_other_uses_needed_for_food_preparation_skill_how_to_obtain_fishing_comments_none_shop_prices_npc_sells_0_npc_buys_0",
      "name": "AC : 0 Vita : 540 Mana : 0 Level: 0 Path: Peasant Crafts: Fishing Max. Held in 1 Slot: 10 Uses: 1 Effect: Vita restoration Merchant suggested price: Minimum: 0 Maximum: 0 Other Uses: Needed for food preparation skill How to Obtain: Fishing Comments: None Shop prices: NPC Sells: 0 NPC Buys: 0",
      "category": "item",
      "level_tier": "",
      "stats": {
        "Vita": 540,
        "Mana": 0
      },
      "stack_size": 10,
      "crafts": [
        "Fishing"
      ],
      "other_uses": [
        "Needed for food preparation skill"
      ],
      "effect": "Vita restoration",
      "obtain": [
        "Fishing"
      ],
      "comments": null,
      "npc_buys": 0,
      "path": [
        "Peasant"
      ]
    },
    {
      "id": "ac_0_vita_540_mana_0_level_0_path_peasant_crafts_food_preparation_max_held_in_1_slot_10_uses_1_effect_vita_restoration_merchant_suggested_price_minimum_0_maximum_0_other_uses_needed_for_food_preparation_skill_how_to_obtain_fishing_comments_none_shop_prices_npc_sells_0_npc_buys_0",
      "name": "AC : 0 Vita : 540 Mana : 0 Level: 0 Path: Peasant Crafts: Food preparation Max. Held in 1 Slot: 10 Uses: 1 Effect: Vita restoration Merchant suggested price: Minimum: 0 Maximum: 0 Other Uses: Needed for food preparation skill How to Obtain: Fishing Comments: None Shop prices: NPC Sells: 0 NPC Buys: 0",
      "category": "item",
      "path": [
        "Peasant"
      ],
      "level_tier": "",
      "stats": {
        "Vita": 540,
        "Mana": 0
      },
      "stack_size": 10,
      "crafts": [
        "Food preparation"
      ],
      "other_uses": [
        "Needed for food preparation skill"
      ],
      "effect": "Vita restoration",
      "obtain": [
        "Fishing"
      ],
      "npc_buys": 0
    },
    {
      "id": "ac_0_vita_8_mana_0_level_0_path_peasant_crafts_food_preparation_max_held_in_1_slot_12_uses_1_effect_vita_restoration_merchant_suggested_price_minimum_0_maximum_0_other_uses_needed_for_food_preparation_skill_how_to_obtain_dropped_by_various_chickens_comments_none_shop_prices_npc_sells_0_npc_buys_0",
      "name": "AC : 0 Vita : 8 Mana : 0 Level: 0 Path: Peasant Crafts: Food preparation Max. Held in 1 Slot: 12 Uses: 1 Effect: Vita restoration Merchant suggested price: Minimum: 0 Maximum: 0 Other Uses: Needed for food preparation skill How to Obtain: Dropped by various chickens Comments: None Shop prices: NPC Sells: 0 NPC Buys: 0",
      "category": "item",
      "path": [
        "Peasant"
      ],
      "level_tier": "",
      "stats": {
        "Vita": 8,
        "Mana": 0
      },
      "stack_size": 12,
      "crafts": [
        "Food preparation"
      ],
      "other_uses": [
        "Needed for food preparation skill"
      ],
      "effect": "Vita restoration",
      "obtain": [
        "Dropped by various chickens"
      ],
      "npc_buys": 0
    },
    {
      "id": "ac_0_vita_900_mana_0_level_0_path_peasant_crafts_chef_max_held_in_1_slot_0_uses_1_effect_mana_restoration_merchant_suggested_price_minimum_0_maximum_0_other_uses_none_how_to_obtain_chefs_comments_none_shop_prices_npc_sells_0_npc_buys_0",
      "name": "AC : 0 Vita : 900 Mana : 0 Level: 0 Path: Peasant Crafts: Chef Max. Held in 1 Slot: 0 Uses: 1 Effect: Mana restoration Merchant suggested price: Minimum: 0 Maximum: 0 Other Uses: None How to Obtain: Chefs Comments: None Shop prices: NPC Sells: 0 NPC Buys: 0",
      "category": "item",
      "path": [
        "Peasant"
      ],
      "level_tier": "",
      "stats": {
        "Vita": 900,
        "Mana": 0
      },
      "stack_size": 0,
      "crafts": [
        "Chef"
      ],
      "effect": "Mana restoration",
      "obtain": [
        "Chefs"
      ],
      "npc_buys": 0
    },
    {
      "id": "ac_0_vita_960_mana_0_level_0_path_peasant_crafts_fishing_max_held_in_1_slot_1_uses_1_effect_vita_restoration_merchant_suggested_price_minimum_0_maximum_0_other_uses_needed_for_food_preparation_skill_how_to_obtain_none_comments_none_shop_prices_npc_sells_0_npc_buys_0",
      "name": "AC : 0 Vita : 960 Mana : 0 Level: 0 Path: Peasant Crafts: Fishing Max. Held in 1 Slot: 1 Uses: 1 Effect: Vita restoration Merchant suggested price: Minimum: 0 Maximum: 0 Other Uses: Needed for food preparation skill How to Obtain: None Comments: None Shop prices: NPC Sells: 0 NPC Buys: 0",
      "category": "item",
      "path": [
        "Peasant"
      ],
      "level_tier": "",
      "stats": {
        "Vita": 960,
        "Mana": 0
      },
      "stack_size": 1,
      "crafts": [
        "Fishing"
      ],
      "other_uses": [
        "Needed for food preparation skill"
      ],
      "effect": "Vita restoration",
      "obtain": [
        "None"
      ],
      "npc_buys": 0
    },
    {
      "id": "ac_0_vita_960_mana_0_level_0_path_peasant_crafts_food_preparation_max_held_in_1_slot_1_uses_1_effect_vita_restoration_merchant_suggested_price_minimum_0_maximum_0_other_uses_needed_for_food_preparation_skill_how_to_obtain_none_comments_none_shop_prices_npc_sells_0_npc_buys_0",
      "name": "AC : 0 Vita : 960 Mana : 0 Level: 0 Path: Peasant Crafts: Food preparation Max. Held in 1 Slot: 1 Uses: 1 Effect: Vita restoration Merchant suggested price: Minimum: 0 Maximum: 0 Other Uses: Needed for food preparation skill How to Obtain: None Comments: None Shop prices: NPC Sells: 0 NPC Buys: 0",
      "category": "item",
      "path": [
        "Peasant"
      ],
      "level_tier": "",
      "stats": {
        "Vita": 960,
        "Mana": 0
      },
      "stack_size": 1,
      "crafts": [
        "Food preparation"
      ],
      "other_uses": [
        "Needed for food preparation skill"
      ],
      "effect": "Vita restoration",
      "obtain": [
        "None"
      ],
      "npc_buys": 0
    },
    {
      "id": "items_crafts_crafts_alchemy_bone_chef_farming_fishing_food_preparation_gem_mining_scribe_vita_woodcutting_items_used_for_crafting_bombs_crafts_drops_events_keys_mana_potions_quests_rocks_scrolls_shops_spells_vita_woodlands_items_extinct_other_prices_have_been_supplied_by_the_merchants_and_are_suggested_only_and_not_to_be_used_as_the_final_authority_on_value_of_the_item_for_the_most_current_prices_consult_the_merchant_subpath_alchemy_aged_wine_ac_0_vita_5_mana_100_level_0_path_peasant_crafts_alchemy_max_held_in_1_slot_1_uses_50_effect_restores_100_mana_takes_5_vita_merchant_suggested_price_minimum_0_maximum_0_other_uses_crafts_how_to_obtain_potion_shops_comments_none_shop_prices_npc_sells_150_npc_buys_75_fine_snake_meat_ac_0_vita_320_mana_0_level_0_path_peasant_crafts_alchemy_max_held_in_1_slot_40_uses_1_effect_vita_restoration_merchant_suggested_price_minimum_0_maximum_0_other_uses_alchemy_lime_potions_how_to_obtain_mythic_snakes_comments_none_shop_prices_npc_sells_0_npc_buys_0_moon_wine_ac_0_vita_5_mana_80_level_0_path_peasant_crafts_alchemy_max_held_in_1_slot_1_uses_50_effect_none_merchant_suggested_price_minimum_0_maximum_0_other_uses_crafts_how_to_obtain_potion_shops_comments_none_shop_prices_npc_sells_100_npc_buys_50_powdered_yellow_amber_ac_0_vita_0_mana_0_level_0_path_peasant_crafts_alchemy_max_held_in_1_slot_3_uses_1_effect_creates_dart_poison_merchant_suggested_price_minimum_0_maximum_0_other_uses_crafts_how_to_obtain_created_by_alchemists_comments_none_shop_prices_npc_sells_0_npc_buys_0_bone_antlers_ac_0_vita_248_mana_0_level_0_path_peasant_crafts_alchemy_max_held_in_1_slot_52_uses_1_effect_restores_248_vitaused_by_alchemists_merchant_suggested_price_minimum_0_maximum_0_other_uses_crafts_how_to_obtain_arena_shops_dropped_by_deers_comments_none_shop_prices_npc_sells_10_npc_buys_5_chef_boiled_beef_ac_0_vita_100_mana_0_level_0_path_peasant_crafts_chef_max_held_in_1_slot_25_uses_1_effect_vita_restoration_merchant_suggested_price_minimum_0_maximum_0_other_uses_none_how_to_obtain_made_by_chefs_comments_none_shop_prices_npc_sells_0_npc_buys_0_noodles_ac_0_vita_300_mana_0_level_0_path_peasant_crafts_chef_max_held_in_1_slot_1_uses_1_effect_vita_restoration_merchant_suggested_price_minimum_0_maximum_0_other_uses_none_how_to_obtain_none_comments_prepared_from_salt_block_water_jug_and_flour_by_players_with_food_preparation_skill_shop_prices_npc_sells_0_npc_buys_0_farming_basic_sickle_ac_0_vita_0_mana_0_level_0_path_peasant_crafts_farming_max_held_in_1_slot_1_uses_1_effect_used_for_cutting_wood_merchant_suggested_price_minimum_200_maximum_100_other_uses_crafts_how_to_obtain_shops_comments_used_for_cutting_wood_shop_prices_npc_sells_200_npc_buys_100_coconut_stick_ac_0_vita_0_mana_0_level_0_path_peasant_crafts_farming_max_held_in_1_slot_1_uses_1_effect_used_for_gathering_coconuts_merchant_suggested_price_minimum_200_maximum_100_other_uses_crafts_how_to_obtain_shops_comments_shop_prices_npc_sells_200_npc_buys_100_fishing_beautiful_fish_ac_0_vita_0_mana_0_level_0_path_peasant_crafts_fishing_max_held_in_1_slot_1_uses_1_effect_vita_restoration_merchant_suggested_price_minimum_0_maximum_0_other_uses_how_to_obtain_fishing_comments_none_shop_prices_npc_sells_0_npc_buys_0_delicious_fish_ac_0_vita_960_mana_0_level_0_path_peasant_crafts_fishing_max_held_in_1_slot_1_uses_1_effect_vita_restoration_merchant_suggested_price_minimum_0_maximum_0_other_uses_needed_for_food_preparation_skill_how_to_obtain_none_comments_none_shop_prices_npc_sells_0_npc_buys_0_large_fish_ac_0_vita_440_mana_0_level_0_path_peasant_crafts_fishing_max_held_in_1_slot_10_uses_1_effect_vita_restoration_merchant_suggested_price_minimum_0_maximum_0_other_uses_needed_for_food_preparation_skill_how_to_obtain_fishing_comments_none_shop_prices_npc_sells_0_npc_buys_0_medium_fish_ac_0_vita_360_mana_0_level_0_path_peasant_crafts_fishing_max_held_in_1_slot_10_uses_1_effect_vita_restoration_merchant_suggested_price_minimum_0_maximum_0_other_uses_needed_for_food_preparation_skill_how_to_obtain_fishing_comments_none_shop_prices_npc_sells_0_npc_buys_0_scrawny_fish_ac_0_vita_180_mana_0_level_0_path_peasant_crafts_fishing_max_held_in_1_slot_10_uses_1_effect_vita_restoration_merchant_suggested_price_minimum_0_maximum_0_other_uses_needed_for_food_preparation_skill_how_to_obtain_fishing_comments_none_shop_prices_npc_sells_0_npc_buys_0_small_fish_ac_0_vita_400_mana_0_level_0_path_peasant_crafts_fishing_max_held_in_1_slot_10_uses_1_effect_vita_restoration_merchant_suggested_price_minimum_0_maximum_0_other_uses_needed_for_food_preparation_skill_how_to_obtain_fishing_comments_none_shop_prices_npc_sells_0_npc_buys_0_tasty_fish_ac_0_vita_540_mana_0_level_0_path_peasant_crafts_fishing_max_held_in_1_slot_10_uses_1_effect_vita_restoration_merchant_suggested_price_minimum_0_maximum_0_other_uses_needed_for_food_preparation_skill_how_to_obtain_fishing_comments_none_shop_prices_npc_sells_0_npc_buys_0_tiny_fish_ac_0_vita_100_mana_0_level_0_path_peasant_crafts_fishing_max_held_in_1_slot_10_uses_1_effect_vita_restoration_merchant_suggested_price_minimum_0_maximum_0_other_uses_needed_for_food_preparation_skill_how_to_obtain_fishing_comments_none_shop_prices_npc_sells_0_npc_buys_0_food_preparation_beef_ac_0_vita_20_mana_0_level_0_path_peasant_crafts_food_preparation_max_held_in_1_slot_100_uses_1_effect_none_merchant_suggested_price_minimum_0_maximum_0_other_uses_none_how_to_obtain_mythic_oxen_kugnae_mud_snake_comments_none_shop_prices_npc_sells_0_npc_buys_0_boiled_fish_ac_0_vita_1000_mana_0_level_0_path_peasant_crafts_food_preparation_max_held_in_1_slot_25_uses_1_effect_vita_restoration_merchant_suggested_price_minimum_0_maximum_0_other_uses_none_how_to_obtain_made_by_food_preparers_comments_none_shop_prices_npc_sells_0_npc_buys_0_broiled_meat_ac_0_vita_1500_mana_0_level_0_path_peasant_crafts_food_preparation_max_held_in_1_slot_10_uses_1_effect_vita_restoration_merchant_suggested_price_minimum_0_maximum_0_other_uses_none_how_to_obtain_cooking_tiger_meat_comments_made_from_tiger_meat_but_barbarians_may_be_forced_to_hurt_you_if_you_cook_this_shop_prices_npc_sells_0_npc_buys_0_chicken_meat_ac_0_vita_40_mana_0_level_0_path_peasant_crafts_food_preparation_max_held_in_1_slot_30_uses_1_effect_vita_restoration_merchant_suggested_price_minimum_0_maximum_0_other_uses_food_preparation_skill_how_to_obtain_none_comments_dropped_by_various_chicken_creatures_shop_prices_npc_sells_0_npc_buys_0_delicious_fish_ac_0_vita_960_mana_0_level_0_path_peasant_crafts_food_preparation_max_held_in_1_slot_1_uses_1_effect_vita_restoration_merchant_suggested_price_minimum_0_maximum_0_other_uses_needed_for_food_preparation_skill_how_to_obtain_none_comments_none_shop_prices_npc_sells_0_npc_buys_0_large_fish_ac_0_vita_440_mana_0_level_0_path_peasant_crafts_fishing_max_held_in_1_slot_10_uses_1_effect_vita_restoration_merchant_suggested_price_minimum_0_maximum_0_other_uses_needed_for_food_preparation_skill_how_to_obtain_fishing_comments_none_shop_prices_npc_sells_0_npc_buys_0_lean_beef_ac_0_vita_500_mana_0_level_0_path_peasant_crafts_food_preparation_max_held_in_1_slot_50_uses_1_effect_vita_restoration_merchant_suggested_price_minimum_0_maximum_0_other_uses_needed_for_food_preparation_skill_how_to_obtain_mythic_oxen_kugnae_mud_snake_comments_none_shop_prices_npc_sells_0_npc_buys_0_medium_fish_ac_0_vita_360_mana_0_level_0_path_peasant_crafts_food_preparation_max_held_in_1_slot_10_uses_1_effect_vita_restoration_merchant_suggested_price_minimum_0_maximum_0_other_uses_needed_for_food_preparation_skill_how_to_obtain_fishing_comments_none_shop_prices_npc_sells_0_npc_buys_0_scrawny_fish_ac_0_vita_180_mana_0_level_0_path_peasant_crafts_food_preparation_max_held_in_1_slot_10_uses_1_effect_vita_restoration_merchant_suggested_price_minimum_0_maximum_0_other_uses_needed_for_food_preparation_skill_how_to_obtain_fishing_comments_none_shop_prices_npc_sells_0_npc_buys_0_small_fish_ac_0_vita_400_mana_0_level_0_path_peasant_crafts_food_preparation_max_held_in_1_slot_10_uses_1_effect_vita_restoration_merchant_suggested_price_minimum_0_maximum_0_other_uses_needed_for_food_preparation_skill_how_to_obtain_fishing_comments_none_shop_prices_npc_sells_0_npc_buys_0_tasty_fish_ac_0_vita_540_mana_0_level_0_path_peasant_crafts_food_preparation_max_held_in_1_slot_10_uses_1_effect_vita_restoration_merchant_suggested_price_minimum_0_maximum_0_other_uses_needed_for_food_preparation_skill_how_to_obtain_fishing_comments_none_shop_prices_npc_sells_0_npc_buys_0_tiny_fish_ac_0_vita_100_mana_0_level_0_path_peasant_crafts_food_preparation_max_held_in_1_slot_10_uses_1_effect_vita_restoration_merchant_suggested_price_minimum_0_maximum_0_other_uses_needed_for_food_preparation_skill_how_to_obtain_fishing_comments_none_shop_prices_npc_sells_0_npc_buys_0_gem_amber_ac_0_vita_0_mana_0_level_0_path_peasant_crafts_gemcutting_max_held_in_1_slot_100_uses_1_effect_none_merchant_suggested_price_minimum_0_maximum_0_other_uses_crafts_how_to_obtain_dropped_by_many_creatures_comments_none_shop_prices_npc_sells_0_npc_buys_0_dark_amber_ac_0_vita_0_mana_0_level_0_path_peasant_crafts_gemcutting_max_held_in_1_slot_100_uses_1_effect_none_merchant_suggested_price_minimum_0_maximum_0_other_uses_crafts_how_to_obtain_dropped_by_many_creatures_comments_none_shop_prices_npc_sells_0_npc_buys_0_white_amber_ac_0_vita_0_mana_0_level_0_path_peasant_crafts_gemcutting_max_held_in_1_slot_20_uses_1_effect_none_merchant_suggested_price_minimum_0_maximum_0_other_uses_crafts_how_to_obtain_dropped_by_many_creatures_comments_none_shop_prices_npc_sells_0_npc_buys_0_yellow_amber_ac_0_vita_0_mana_0_level_0_path_peasant_crafts_gemcutting_max_held_in_1_slot_20_uses_1_effect_none_merchant_suggested_price_minimum_0_maximum_0_other_uses_crafts_how_to_obtain_dropped_by_many_creatures_comments_none_shop_prices_npc_sells_0_npc_buys_0_mining_mining_shovel_ac_0_vita_0_mana_0_level_0_path_peasant_crafts_mining_max_held_in_1_slot_1_uses_1_effect_used_for_mining_merchant_suggested_price_minimum_20_maximum_40_other_uses_crafts_how_to_obtain_shops_comments_shop_prices_npc_sells_40_npc_buys_20_scribe_amber_ac_0_vita_0_mana_0_level_0_path_peasant_crafts_scribe_max_held_in_1_slot_100_uses_1_effect_none_merchant_suggested_price_minimum_0_maximum_0_other_uses_crafts_how_to_obtain_dropped_by_many_creatures_comments_none_shop_prices_npc_sells_0_npc_buys_0_dark_amber_ac_0_vita_0_mana_0_level_0_path_peasant_crafts_scribe_max_held_in_1_slot_100_uses_1_effect_none_merchant_suggested_price_minimum_0_maximum_0_other_uses_crafts_how_to_obtain_dropped_by_many_creatures_comments_none_shop_prices_npc_sells_0_npc_buys_0_ink_ac_0_vita_0_mana_0_level_0_path_peasant_crafts_scribe_max_held_in_1_slot_1_uses_1_effect_needed_for_spells_and_the_scribe_craft_merchant_suggested_price_minimum_0_maximum_0_other_uses_needed_to_make_most_scrolls_how_to_obtain_buy_in_messenger_shops_comments_none_shop_prices_npc_sells_100_npc_buys_50_moon_paper_ac_0_vita_0_mana_0_level_0_path_peasant_crafts_scribe_max_held_in_1_slot_1_uses_1_effect_none_merchant_suggested_price_minimum_0_maximum_0_other_uses_needed_to_make_scroll_of_defense_how_to_obtain_buy_in_kugnae_baek_s_shop_comments_none_shop_prices_npc_sells_5_000_npc_buys_2_500_white_paper_ac_0_vita_0_mana_0_level_0_path_peasant_crafts_scribe_max_held_in_1_slot_1_uses_1_effect_none_merchant_suggested_price_minimum_0_maximum_0_other_uses_needed_to_make_most_scrolls_how_to_obtain_buy_in_messenger_shops_comments_none_shop_prices_npc_sells_100_npc_buys_50_vita_bird_meat_ac_0_vita_100_mana_0_level_0_path_peasant_crafts_food_preparation_max_held_in_1_slot_30_uses_1_effect_vita_merchant_suggested_price_minimum_0_maximum_0_other_uses_needed_for_food_preparation_skill_how_to_obtain_dropped_by_pheasants_in_the_woodlands_comments_none_shop_prices_npc_sells_0_npc_buys_0_boiled_pork_ac_0_vita_900_mana_0_level_0_path_peasant_crafts_chef_max_held_in_1_slot_0_uses_1_effect_mana_restoration_merchant_suggested_price_minimum_0_maximum_0_other_uses_none_how_to_obtain_chefs_comments_none_shop_prices_npc_sells_0_npc_buys_0_egg_ac_0_vita_8_mana_0_level_0_path_peasant_crafts_food_preparation_max_held_in_1_slot_12_uses_1_effect_vita_restoration_merchant_suggested_price_minimum_0_maximum_0_other_uses_needed_for_food_preparation_skill_how_to_obtain_dropped_by_various_chickens_comments_none_shop_prices_npc_sells_0_npc_buys_0_fried_egg_ac_0_vita_100_mana_0_level_0_path_peasant_crafts_food_preparation_max_held_in_1_slot_12_uses_1_effect_vita_restoration_merchant_suggested_price_minimum_0_maximum_0_other_uses_made_by_food_preparation_how_to_obtain_none_comments_none_shop_prices_npc_sells_0_npc_buys_0_medium_fish_ac_0_vita_360_mana_0_level_0_path_peasant_crafts_fishing_max_held_in_1_slot_10_uses_1_effect_vita_restoration_merchant_suggested_price_minimum_0_maximum_0_other_uses_needed_for_food_preparation_skill_how_to_obtain_fishing_comments_none_shop_prices_npc_sells_0_npc_buys_0_peas_ac_0_vita_100_mana_0_level_0_path_peasant_crafts_gardening_max_held_in_1_slot_5_uses_1_effect_vita_restoration_merchant_suggested_price_minimum_0_maximum_0_other_uses_none_how_to_obtain_none_comments_dug_from_kugnae_and_wilderness_gardens_shop_prices_npc_sells_0_npc_buys_0_roast_chicken_ac_0_vita_1000_mana_0_level_0_path_peasant_crafts_food_preparation_max_held_in_1_slot_25_uses_1_effect_vita_restoration_merchant_suggested_price_minimum_0_maximum_0_other_uses_none_how_to_obtain_food_preparers_comments_prepared_from_bird_or_chicken_meat_by_players_with_food_preparation_skill_shop_prices_npc_sells_0_npc_buys_0_scrawny_fish_ac_0_vita_180_mana_0_level_0_path_peasant_crafts_fishing_max_held_in_1_slot_10_uses_1_effect_vita_restoration_merchant_suggested_price_minimum_0_maximum_0_other_uses_needed_for_food_preparation_skill_how_to_obtain_fishing_comments_none_shop_prices_npc_sells_0_npc_buys_0_small_fish_ac_0_vita_400_mana_0_level_0_path_peasant_crafts_fishing_max_held_in_1_slot_10_uses_1_effect_vita_restoration_merchant_suggested_price_minimum_0_maximum_0_other_uses_needed_for_food_preparation_skill_how_to_obtain_fishing_comments_none_shop_prices_npc_sells_0_npc_buys_0_tasty_fish_ac_0_vita_540_mana_0_level_0_path_peasant_crafts_fishing_max_held_in_1_slot_10_uses_1_effect_vita_restoration_merchant_suggested_price_minimum_0_maximum_0_other_uses_needed_for_food_preparation_skill_how_to_obtain_fishing_comments_none_shop_prices_npc_sells_0_npc_buys_0_tiger_meat_ac_0_vita_100_mana_0_level_0_path_peasant_crafts_food_preparation_max_held_in_1_slot_10_uses_1_effect_vita_restoration_merchant_suggested_price_minimum_0_maximum_0_other_uses_subpath_quest_item_how_to_obtain_dropped_by_iron_lab_tigers_comments_none_shop_prices_npc_sells_100_npc_buys_50_tiny_fish_ac_0_vita_100_mana_0_level_0_path_peasant_crafts_fishing_max_held_in_1_slot_10_uses_1_effect_vita_restoration_merchant_suggested_price_minimum_0_maximum_0_other_uses_needed_for_food_preparation_skill_how_to_obtain_fishing_comments_none_shop_prices_npc_sells_0_npc_buys_0_woodcutting_axe_ac_0_vita_0_mana_0_level_0_path_peasant_crafts_woodcutting_max_held_in_1_slot_1_uses_1_effect_used_for_cutting_wood_merchant_suggested_price_minimum_50_maximum_50_other_uses_crafts_how_to_obtain_shops_comments_used_for_cutting_wood_shop_prices_npc_sells_50_npc_buys_25",
      "name": "Items » Crafts Crafts Alchemy / Bone / Chef / Farming / Fishing / Food preparation / Gem / Mining / Scribe / Vita / Woodcutting Items used for crafting. Bombs / Crafts / Drops / Events / Keys / Mana / Potions / Quests Rocks / Scrolls / Shops / Spells / Vita / Woodlands Items / Extinct / Other Prices have been supplied by the Merchants and are suggested only and not to be used as the final authority on value of the item. For the most current prices consult the Merchant Subpath. Alchemy Aged wine AC : 0 Vita : -5 Mana : 100 Level: 0 Path: Peasant Crafts: Alchemy Max. Held in 1 Slot: 1 Uses: 50 Effect: Restores 100 mana, takes 5 vita Merchant suggested price: Minimum: 0 Maximum: 0 Other Uses: Crafts How to Obtain: Potion Shops Comments: None Shop prices: NPC Sells: 150 NPC Buys: 75 Fine snake meat AC : 0 Vita : 320 Mana : 0 Level: 0 Path: Peasant Crafts: Alchemy Max. Held in 1 Slot: 40 Uses: 1 Effect: Vita restoration Merchant suggested price: Minimum: 0 Maximum: 0 Other Uses: Alchemy - lime potions How to Obtain: Mythic Snakes Comments: None Shop prices: NPC Sells: 0 NPC Buys: 0 Moon wine AC : 0 Vita : -5 Mana : 80 Level: 0 Path: Peasant Crafts: Alchemy Max. Held in 1 Slot: 1 Uses: 50 Effect: None Merchant suggested price: Minimum: 0 Maximum: 0 Other Uses: Crafts How to Obtain: Potion Shops Comments: None Shop prices: NPC Sells: 100 NPC Buys: 50 Powdered yellow amber AC : 0 Vita : 0 Mana : 0 Level: 0 Path: Peasant Crafts: Alchemy Max. Held in 1 Slot: 3 Uses: 1 Effect: Creates dart poison Merchant suggested price: Minimum: 0 Maximum: 0 Other Uses: Crafts How to Obtain: Created by Alchemists Comments: None Shop prices: NPC Sells: 0 NPC Buys: 0 Bone Antlers AC : 0 Vita : 248 Mana : 0 Level: 0 Path: Peasant Crafts: Alchemy Max. Held in 1 Slot: 52 Uses: 1 Effect: Restores 248 vitaUsed by Alchemists Merchant suggested price: Minimum: 0 Maximum: 0 Other Uses: Crafts How to Obtain: Arena Shops, Dropped by Deers Comments: None Shop prices: NPC Sells: 10 NPC Buys: 5 Chef Boiled beef AC : 0 Vita : 100 Mana : 0 Level: 0 Path: Peasant Crafts: Chef Max. Held in 1 Slot: 25 Uses: 1 Effect: Vita restoration Merchant suggested price: Minimum: 0 Maximum: 0 Other Uses: None How to Obtain: Made by chefs Comments: None Shop prices: NPC Sells: 0 NPC Buys: 0 Noodles AC : 0 Vita : 300 Mana : 0 Level: 0 Path: Peasant Crafts: Chef Max. Held in 1 Slot: 1 Uses: 1 Effect: Vita restoration Merchant suggested price: Minimum: 0 Maximum: 0 Other Uses: None How to Obtain: None Comments: Prepared from Salt Block, Water Jug, and Flour by players with Food preparation skill. Shop prices: NPC Sells: 0 NPC Buys: 0 Farming Basic sickle AC : 0 Vita : 0 Mana : 0 Level: 0 Path: Peasant Crafts: Farming Max. Held in 1 Slot: 1 Uses: 1 Effect: Used for cutting wood Merchant suggested price: Minimum: 200 Maximum: 100 Other Uses: Crafts How to Obtain: Shops Comments: Used for cutting wood Shop prices: NPC Sells: 200 NPC Buys: 100 Coconut stick AC : 0 Vita : 0 Mana : 0 Level: 0 Path: Peasant Crafts: Farming Max. Held in 1 Slot: 1 Uses: 1 Effect: Used for gathering coconuts Merchant suggested price: Minimum: 200 Maximum: 100 Other Uses: Crafts How to Obtain: Shops Comments: Shop prices: NPC Sells: 200 NPC Buys: 100 Fishing Beautiful fish AC : 0 Vita : 0 Mana : 0 Level: 0 Path: Peasant Crafts: Fishing Max. Held in 1 Slot: 1 Uses: 1 Effect: Vita restoration Merchant suggested price: Minimum: 0 Maximum: 0 Other Uses: How to Obtain: Fishing Comments: None Shop prices: NPC Sells: 0 NPC Buys: 0 Delicious fish AC : 0 Vita : 960 Mana : 0 Level: 0 Path: Peasant Crafts: Fishing Max. Held in 1 Slot: 1 Uses: 1 Effect: Vita restoration Merchant suggested price: Minimum: 0 Maximum: 0 Other Uses: Needed for food preparation skill How to Obtain: None Comments: None Shop prices: NPC Sells: 0 NPC Buys: 0 Large fish AC : 0 Vita : 440 Mana : 0 Level: 0 Path: Peasant Crafts: Fishing Max. Held in 1 Slot: 10 Uses: 1 Effect: Vita restoration Merchant suggested price: Minimum: 0 Maximum: 0 Other Uses: Needed for food preparation skill How to Obtain: Fishing Comments: None Shop prices: NPC Sells: 0 NPC Buys: 0 Medium fish AC : 0 Vita : 360 Mana : 0 Level: 0 Path: Peasant Crafts: Fishing Max. Held in 1 Slot: 10 Uses: 1 Effect: Vita restoration Merchant suggested price: Minimum: 0 Maximum: 0 Other Uses: Needed for food preparation skill How to Obtain: Fishing Comments: None Shop prices: NPC Sells: 0 NPC Buys: 0 Scrawny fish AC : 0 Vita : 180 Mana : 0 Level: 0 Path: Peasant Crafts: Fishing Max. Held in 1 Slot: 10 Uses: 1 Effect: Vita restoration Merchant suggested price: Minimum: 0 Maximum: 0 Other Uses: Needed for food preparation skill How to Obtain: Fishing Comments: None Shop prices: NPC Sells: 0 NPC Buys: 0 Small fish AC : 0 Vita : 400 Mana : 0 Level: 0 Path: Peasant Crafts: Fishing Max. Held in 1 Slot: 10 Uses: 1 Effect: Vita restoration Merchant suggested price: Minimum: 0 Maximum: 0 Other Uses: Needed for food preparation skill How to Obtain: Fishing Comments: None Shop prices: NPC Sells: 0 NPC Buys: 0 Tasty fish AC : 0 Vita : 540 Mana : 0 Level: 0 Path: Peasant Crafts: Fishing Max. Held in 1 Slot: 10 Uses: 1 Effect: Vita restoration Merchant suggested price: Minimum: 0 Maximum: 0 Other Uses: Needed for food preparation skill How to Obtain: Fishing Comments: None Shop prices: NPC Sells: 0 NPC Buys: 0 Tiny fish AC : 0 Vita : 100 Mana : 0 Level: 0 Path: Peasant Crafts: Fishing Max. Held in 1 Slot: 10 Uses: 1 Effect: Vita restoration Merchant suggested price: Minimum: 0 Maximum: 0 Other Uses: Needed for food preparation skill How to Obtain: Fishing Comments: None Shop prices: NPC Sells: 0 NPC Buys: 0 Food preparation Beef AC : 0 Vita : 20 Mana : 0 Level: 0 Path: Peasant Crafts: Food preparation Max. Held in 1 Slot: 100 Uses: 1 Effect: None Merchant suggested price: Minimum: 0 Maximum: 0 Other Uses: None How to Obtain: Mythic Oxen, Kugnae Mud Snake Comments: None Shop prices: NPC Sells: 0 NPC Buys: 0 Boiled fish AC : 0 Vita : 1000 Mana : 0 Level: 0 Path: Peasant Crafts: Food preparation Max. Held in 1 Slot: 25 Uses: 1 Effect: Vita restoration Merchant suggested price: Minimum: 0 Maximum: 0 Other Uses: None How to Obtain: Made by food preparers Comments: None Shop prices: NPC Sells: 0 NPC Buys: 0 Broiled meat AC : 0 Vita : 1500 Mana : 0 Level: 0 Path: Peasant Crafts: Food preparation Max. Held in 1 Slot: 10 Uses: 1 Effect: Vita restoration Merchant suggested price: Minimum: 0 Maximum: 0 Other Uses: None How to Obtain: Cooking Tiger meat. Comments: Made from Tiger meat but Barbarians may be forced to hurt you if you cook this! Shop prices: NPC Sells: 0 NPC Buys: 0 Chicken meat AC : 0 Vita : 40 Mana : 0 Level: 0 Path: Peasant Crafts: Food preparation Max. Held in 1 Slot: 30 Uses: 1 Effect: Vita restoration Merchant suggested price: Minimum: 0 Maximum: 0 Other Uses: Food preparation skill How to Obtain: None Comments: Dropped by various chicken creatures Shop prices: NPC Sells: 0 NPC Buys: 0 Delicious fish AC : 0 Vita : 960 Mana : 0 Level: 0 Path: Peasant Crafts: Food preparation Max. Held in 1 Slot: 1 Uses: 1 Effect: Vita restoration Merchant suggested price: Minimum: 0 Maximum: 0 Other Uses: Needed for food preparation skill How to Obtain: None Comments: None Shop prices: NPC Sells: 0 NPC Buys: 0 Large fish AC : 0 Vita : 440 Mana : 0 Level: 0 Path: Peasant Crafts: Fishing Max. Held in 1 Slot: 10 Uses: 1 Effect: Vita restoration Merchant suggested price: Minimum: 0 Maximum: 0 Other Uses: Needed for food preparation skill How to Obtain: Fishing Comments: None Shop prices: NPC Sells: 0 NPC Buys: 0 Lean beef AC : 0 Vita : 500 Mana : 0 Level: 0 Path: Peasant Crafts: Food preparation Max. Held in 1 Slot: 50 Uses: 1 Effect: Vita restoration Merchant suggested price: Minimum: 0 Maximum: 0 Other Uses: Needed for food preparation skill How to Obtain: Mythic Oxen, Kugnae Mud Snake Comments: None Shop prices: NPC Sells: 0 NPC Buys: 0 Medium fish AC : 0 Vita : 360 Mana : 0 Level: 0 Path: Peasant Crafts: Food preparation Max. Held in 1 Slot: 10 Uses: 1 Effect: Vita restoration Merchant suggested price: Minimum: 0 Maximum: 0 Other Uses: Needed for food preparation skill How to Obtain: Fishing Comments: None Shop prices: NPC Sells: 0 NPC Buys: 0 Scrawny fish AC : 0 Vita : 180 Mana : 0 Level: 0 Path: Peasant Crafts: Food preparation Max. Held in 1 Slot: 10 Uses: 1 Effect: Vita restoration Merchant suggested price: Minimum: 0 Maximum: 0 Other Uses: Needed for food preparation skill How to Obtain: Fishing Comments: None Shop prices: NPC Sells: 0 NPC Buys: 0 Small fish AC : 0 Vita : 400 Mana : 0 Level: 0 Path: Peasant Crafts: Food preparation Max. Held in 1 Slot: 10 Uses: 1 Effect: Vita restoration Merchant suggested price: Minimum: 0 Maximum: 0 Other Uses: Needed for food preparation skill How to Obtain: Fishing Comments: None Shop prices: NPC Sells: 0 NPC Buys: 0 Tasty fish AC : 0 Vita : 540 Mana : 0 Level: 0 Path: Peasant Crafts: Food preparation Max. Held in 1 Slot: 10 Uses: 1 Effect: Vita restoration Merchant suggested price: Minimum: 0 Maximum: 0 Other Uses: Needed for food preparation skill How to Obtain: Fishing Comments: None Shop prices: NPC Sells: 0 NPC Buys: 0 Tiny fish AC : 0 Vita : 100 Mana : 0 Level: 0 Path: Peasant Crafts: Food preparation Max. Held in 1 Slot: 10 Uses: 1 Effect: Vita restoration Merchant suggested price: Minimum: 0 Maximum: 0 Other Uses: Needed for food preparation skill How to Obtain: Fishing Comments: None Shop prices: NPC Sells: 0 NPC Buys: 0 Gem Amber AC : 0 Vita : 0 Mana : 0 Level: 0 Path: Peasant Crafts: Gemcutting Max. Held in 1 Slot: 100 Uses: 1 Effect: None Merchant suggested price: Minimum: 0 Maximum: 0 Other Uses: Crafts How to Obtain: Dropped by many creatures Comments: None Shop prices: NPC Sells: 0 NPC Buys: 0 Dark amber AC : 0 Vita : 0 Mana : 0 Level: 0 Path: Peasant Crafts: Gemcutting Max. Held in 1 Slot: 100 Uses: 1 Effect: None Merchant suggested price: Minimum: 0 Maximum: 0 Other Uses: Crafts How to Obtain: Dropped by many creatures Comments: None Shop prices: NPC Sells: 0 NPC Buys: 0 White amber AC : 0 Vita : 0 Mana : 0 Level: 0 Path: Peasant Crafts: Gemcutting Max. Held in 1 Slot: 20 Uses: 1 Effect: None Merchant suggested price: Minimum: 0 Maximum: 0 Other Uses: Crafts How to Obtain: Dropped by many creatures Comments: None Shop prices: NPC Sells: 0 NPC Buys: 0 Yellow amber AC : 0 Vita : 0 Mana : 0 Level: 0 Path: Peasant Crafts: Gemcutting Max. Held in 1 Slot: 20 Uses: 1 Effect: None Merchant suggested price: Minimum: 0 Maximum: 0 Other Uses: Crafts How to Obtain: Dropped by many creatures Comments: None Shop prices: NPC Sells: 0 NPC Buys: 0 Mining Mining shovel AC : 0 Vita : 0 Mana : 0 Level: 0 Path: Peasant Crafts: Mining Max. Held in 1 Slot: 1 Uses: 1 Effect: Used for mining Merchant suggested price: Minimum: 20 Maximum: 40 Other Uses: Crafts How to Obtain: Shops Comments: Shop prices: NPC Sells: 40 NPC Buys: 20 Scribe Amber AC : 0 Vita : 0 Mana : 0 Level: 0 Path: Peasant Crafts: Scribe Max. Held in 1 Slot: 100 Uses: 1 Effect: None Merchant suggested price: Minimum: 0 Maximum: 0 Other Uses: Crafts How to Obtain: Dropped by many creatures Comments: None Shop prices: NPC Sells: 0 NPC Buys: 0 Dark amber AC : 0 Vita : 0 Mana : 0 Level: 0 Path: Peasant Crafts: Scribe Max. Held in 1 Slot: 100 Uses: 1 Effect: None Merchant suggested price: Minimum: 0 Maximum: 0 Other Uses: Crafts How to Obtain: Dropped by many creatures Comments: None Shop prices: NPC Sells: 0 NPC Buys: 0 Ink AC : 0 Vita : 0 Mana : 0 Level: 0 Path: Peasant Crafts: Scribe Max. Held in 1 Slot: 1 Uses: 1 Effect: Needed for spells and the Scribe craft Merchant suggested price: Minimum: 0 Maximum: 0 Other Uses: Needed to make most Scrolls How to Obtain: Buy in Messenger shops Comments: None Shop prices: NPC Sells: 100 NPC Buys: 50 Moon paper AC : 0 Vita : 0 Mana : 0 Level: 0 Path: Peasant Crafts: Scribe Max. Held in 1 Slot: 1 Uses: 1 Effect: None Merchant suggested price: Minimum: 0 Maximum: 0 Other Uses: Needed to make Scroll of defense How to Obtain: Buy in Kugnae, Baek's shop Comments: None Shop prices: NPC Sells: 5,000 NPC Buys: 2,500 White paper AC : 0 Vita : 0 Mana : 0 Level: 0 Path: Peasant Crafts: Scribe Max. Held in 1 Slot: 1 Uses: 1 Effect: None Merchant suggested price: Minimum: 0 Maximum: 0 Other Uses: Needed to make most Scrolls How to Obtain: Buy in Messenger shops Comments: None Shop prices: NPC Sells: 100 NPC Buys: 50 Vita Bird meat AC : 0 Vita : 100 Mana : 0 Level: 0 Path: Peasant Crafts: Food preparation Max. Held in 1 Slot: 30 Uses: 1 Effect: Vita Merchant suggested price: Minimum: 0 Maximum: 0 Other Uses: Needed for food preparation skill How to Obtain: Dropped by Pheasants in the Woodlands Comments: None Shop prices: NPC Sells: 0 NPC Buys: 0 Boiled pork AC : 0 Vita : 900 Mana : 0 Level: 0 Path: Peasant Crafts: Chef Max. Held in 1 Slot: 0 Uses: 1 Effect: Mana restoration Merchant suggested price: Minimum: 0 Maximum: 0 Other Uses: None How to Obtain: Chefs Comments: None Shop prices: NPC Sells: 0 NPC Buys: 0 Egg AC : 0 Vita : 8 Mana : 0 Level: 0 Path: Peasant Crafts: Food preparation Max. Held in 1 Slot: 12 Uses: 1 Effect: Vita restoration Merchant suggested price: Minimum: 0 Maximum: 0 Other Uses: Needed for food preparation skill How to Obtain: Dropped by various chickens Comments: None Shop prices: NPC Sells: 0 NPC Buys: 0 Fried egg AC : 0 Vita : 100 Mana : 0 Level: 0 Path: Peasant Crafts: Food preparation Max. Held in 1 Slot: 12 Uses: 1 Effect: Vita restoration Merchant suggested price: Minimum: 0 Maximum: 0 Other Uses: Made by food preparation How to Obtain: None Comments: None Shop prices: NPC Sells: 0 NPC Buys: 0 Medium fish AC : 0 Vita : 360 Mana : 0 Level: 0 Path: Peasant Crafts: Fishing Max. Held in 1 Slot: 10 Uses: 1 Effect: Vita restoration Merchant suggested price: Minimum: 0 Maximum: 0 Other Uses: Needed for food preparation skill How to Obtain: Fishing Comments: None Shop prices: NPC Sells: 0 NPC Buys: 0 Peas AC : 0 Vita : 100 Mana : 0 Level: 0 Path: Peasant Crafts: Gardening Max. Held in 1 Slot: 5 Uses: 1 Effect: Vita restoration Merchant suggested price: Minimum: 0 Maximum: 0 Other Uses: None How to Obtain: None Comments: Dug from Kugnae and Wilderness Gardens Shop prices: NPC Sells: 0 NPC Buys: 0 Roast chicken AC : 0 Vita : 1000 Mana : 0 Level: 0 Path: Peasant Crafts: Food preparation Max. Held in 1 Slot: 25 Uses: 1 Effect: Vita restoration Merchant suggested price: Minimum: 0 Maximum: 0 Other Uses: None How to Obtain: Food preparers Comments: Prepared from Bird or Chicken meat by players with Food preparation skill. Shop prices: NPC Sells: 0 NPC Buys: 0 Scrawny fish AC : 0 Vita : 180 Mana : 0 Level: 0 Path: Peasant Crafts: Fishing Max. Held in 1 Slot: 10 Uses: 1 Effect: Vita restoration Merchant suggested price: Minimum: 0 Maximum: 0 Other Uses: Needed for food preparation skill How to Obtain: Fishing Comments: None Shop prices: NPC Sells: 0 NPC Buys: 0 Small fish AC : 0 Vita : 400 Mana : 0 Level: 0 Path: Peasant Crafts: Fishing Max. Held in 1 Slot: 10 Uses: 1 Effect: Vita restoration Merchant suggested price: Minimum: 0 Maximum: 0 Other Uses: Needed for food preparation skill How to Obtain: Fishing Comments: None Shop prices: NPC Sells: 0 NPC Buys: 0 Tasty fish AC : 0 Vita : 540 Mana : 0 Level: 0 Path: Peasant Crafts: Fishing Max. Held in 1 Slot: 10 Uses: 1 Effect: Vita restoration Merchant suggested price: Minimum: 0 Maximum: 0 Other Uses: Needed for food preparation skill How to Obtain: Fishing Comments: None Shop prices: NPC Sells: 0 NPC Buys: 0 Tiger meat AC : 0 Vita : 100 Mana : 0 Level: 0 Path: Peasant Crafts: Food preparation Max. Held in 1 Slot: 10 Uses: 1 Effect: Vita restoration Merchant suggested price: Minimum: 0 Maximum: 0 Other Uses: Subpath quest item How to Obtain: Dropped by Iron lab tigers Comments: None Shop prices: NPC Sells: 100 NPC Buys: 50 Tiny fish AC : 0 Vita : 100 Mana : 0 Level: 0 Path: Peasant Crafts: Fishing Max. Held in 1 Slot: 10 Uses: 1 Effect: Vita restoration Merchant suggested price: Minimum: 0 Maximum: 0 Other Uses: Needed for food preparation skill How to Obtain: Fishing Comments: None Shop prices: NPC Sells: 0 NPC Buys: 0 Woodcutting Axe AC : 0 Vita : 0 Mana : 0 Level: 0 Path: Peasant Crafts: Woodcutting Max. Held in 1 Slot: 1 Uses: 1 Effect: Used for cutting wood Merchant suggested price: Minimum: 50 Maximum: 50 Other Uses: Crafts How to Obtain: Shops Comments: Used for cutting wood Shop prices: NPC Sells: 50 NPC Buys: 25",
      "category": "item",
      "path": [
        "Peasant"
      ],
      "level_tier": "",
      "stats": {
        "Vita": -5,
        "Mana": 100
      },
      "stack_size": 1,
      "crafts": [
        "Alchemy"
      ],
      "other_uses": [
        "Crafts"
      ],
      "effect": "Restores 100 mana, takes 5 vita",
      "obtain": [
        "Potion Shops"
      ],
      "npc_buys": 75
    },
    {
      "id": "items_bombs_bombs_fun_in_the_arenas_bombs_crafts_drops_events_keys_mana_potions_quests_rocks_scrolls_shops_spells_vita_woodlands_items_extinct_other_prices_have_been_supplied_by_the_merchants_and_are_suggested_only_and_not_to_be_used_as_the_final_authority_on_value_of_the_item_for_the_most_current_prices_consult_the_merchant_subpath_deadly_earth_vita_0_mana_0_level_99_path_geomancer_max_held_in_1_slot_1_uses_1_crafts_none_other_uses_none_merchant_suggested_price_minimum_0_maximum_0_effect_explosion_how_to_obtain_kugnae_arena_shop_comments_none_shop_prices_npc_sells_1_000_npc_buys_500_flash_dust_vita_0_mana_0_level_6_path_peasant_max_held_in_1_slot_1_uses_1_crafts_none_other_uses_none_merchant_suggested_price_minimum_0_maximum_0_effect_used_by_peasent_level_6_needed_to_make_hot_coal_how_to_obtain_arena_shops_comments_none_shop_prices_npc_sells_5_npc_buys_2_flash_powder_vita_0_mana_0_level_26_path_peasant_max_held_in_1_slot_1_uses_1_crafts_none_other_uses_used_to_make_hot_coal_for_lanterns_merchant_suggested_price_minimum_0_maximum_0_effect_used_by_peasent_level_6_how_to_obtain_arena_shops_comments_none_shop_prices_npc_sells_5_npc_buys_2_holy_dust_vita_0_mana_0_level_60_path_poet_max_held_in_1_slot_1_uses_1_crafts_none_other_uses_none_merchant_suggested_price_minimum_0_maximum_0_effect_explosion_how_to_obtain_arena_shops_comments_none_shop_prices_npc_sells_60_npc_buys_30_holy_powder_vita_0_mana_0_level_99_path_peasant_max_held_in_1_slot_1_uses_1_crafts_none_other_uses_none_merchant_suggested_price_minimum_0_maximum_0_effect_explosion_how_to_obtain_arena_shops_comments_none_shop_prices_npc_sells_500_npc_buys_250_ice_shards_vita_0_mana_0_level_70_path_geomancer_max_held_in_1_slot_1_uses_1_crafts_none_other_uses_none_merchant_suggested_price_minimum_0_maximum_0_effect_explosion_how_to_obtain_arena_shops_comments_none_shop_prices_npc_sells_100_npc_buys_50_moon_powder_vita_0_mana_0_level_99_path_peasant_max_held_in_1_slot_1_uses_1_crafts_none_other_uses_none_merchant_suggested_price_minimum_0_maximum_0_effect_used_by_peasent_level_99_how_to_obtain_arena_shops_comments_none_shop_prices_npc_sells_150_npc_buys_75_rogue_s_powder_vita_0_mana_0_level_30_path_rogue_max_held_in_1_slot_1_uses_1_crafts_none_other_uses_none_merchant_suggested_price_minimum_0_maximum_0_effect_used_by_rogue_level_30_how_to_obtain_arena_shops_comments_none_shop_prices_npc_sells_16_npc_buys_8_shard_bomb_vita_0_mana_0_level_55_path_warrior_max_held_in_1_slot_1_uses_1_crafts_none_other_uses_none_merchant_suggested_price_minimum_0_maximum_0_effect_explosion_how_to_obtain_arena_shops_comments_none_shop_prices_npc_sells_80_npc_buys_40_shatter_bomb_vita_0_mana_0_level_99_path_warrior_max_held_in_1_slot_1_uses_1_crafts_none_other_uses_none_merchant_suggested_price_minimum_0_maximum_0_effect_explosion_how_to_obtain_arena_shops_comments_none_shop_prices_npc_sells_400_npc_buys_200_spark_powder_vita_0_mana_0_level_50_path_peasant_max_held_in_1_slot_1_uses_1_crafts_none_other_uses_none_merchant_suggested_price_minimum_0_maximum_0_effect_used_by_peasent_level_50_how_to_obtain_arena_shops_comments_none_shop_prices_npc_sells_40_npc_buys_20_spy_s_explosives_vita_0_mana_0_level_70_path_spy_max_held_in_1_slot_1_uses_1_crafts_none_other_uses_none_merchant_suggested_price_minimum_0_maximum_0_effect_explosion_how_to_obtain_arena_shops_comments_none_shop_prices_npc_sells_100_npc_buys_50_star_powder_vita_0_mana_0_level_40_path_peasant_max_held_in_1_slot_1_uses_1_crafts_none_other_uses_none_merchant_suggested_price_minimum_0_maximum_0_effect_used_by_peasent_level_80_can_be_used_as_a_star_item_in_mage_armor_quest_how_to_obtain_arena_shops_comments_none_shop_prices_npc_sells_100_npc_buys_50_stealth_explosives_vita_0_mana_0_level_99_path_rogue_max_held_in_1_slot_1_uses_1_crafts_none_other_uses_none_merchant_suggested_price_minimum_0_maximum_0_effect_used_by_rogue_level_99_how_to_obtain_buya_arena_shop_comments_none_shop_prices_npc_sells_200_npc_buys_100_stealth_powder_vita_0_mana_0_level_62_path_rogue_max_held_in_1_slot_1_uses_1_crafts_none_other_uses_none_merchant_suggested_price_minimum_0_maximum_0_effect_used_by_rogue_level_62_how_to_obtain_buya_arena_shop_comments_none_shop_prices_npc_sells_80_npc_buys_40_sun_powder_vita_0_mana_0_level_99_path_peasant_max_held_in_1_slot_1_uses_1_crafts_none_other_uses_none_merchant_suggested_price_minimum_0_maximum_0_effect_explosion_how_to_obtain_arena_shops_comments_none_shop_prices_npc_sells_200_npc_buys_100",
      "name": "Items | Bombs Bombs Fun in the Arenas! Bombs / Crafts / Drops / Events / Keys / Mana / Potions / Quests Rocks / Scrolls / Shops / Spells / Vita / Woodlands Items / Extinct / Other Prices have been supplied by the Merchants and are suggested only and not to be used as the final authority on value of the item. For the most current prices consult the Merchant Subpath. Deadly earth Vita : 0 Mana : 0 Level: 99 Path: Geomancer Max. Held in 1 Slot: 1 Uses: 1 Crafts: None Other Uses: None Merchant suggested price: Minimum: 0 Maximum: 0 Effect: Explosion How to Obtain: Kugnae Arena Shop Comments: None Shop prices: NPC Sells: 1,000 NPC Buys: 500 Flash dust Vita : 0 Mana : 0 Level: 6 Path: Peasant Max. Held in 1 Slot: 1 Uses: 1 Crafts: None Other Uses: None Merchant suggested price: Minimum: 0 Maximum: 0 Effect: Used by Peasent Level 6+Needed to make Hot coal How to Obtain: Arena Shops Comments: None Shop prices: NPC Sells: 5 NPC Buys: 2 Flash powder Vita : 0 Mana : 0 Level: 26 Path: Peasant Max. Held in 1 Slot: 1 Uses: 1 Crafts: None Other Uses: Used to make hot coal for lanterns Merchant suggested price: Minimum: 0 Maximum: 0 Effect: Used by Peasent Level 6+ How to Obtain: Arena Shops Comments: None Shop prices: NPC Sells: 5 NPC Buys: 2 Holy dust Vita : 0 Mana : 0 Level: 60 Path: Poet Max. Held in 1 Slot: 1 Uses: 1 Crafts: None Other Uses: None Merchant suggested price: Minimum: 0 Maximum: 0 Effect: Explosion How to Obtain: Arena Shops Comments: None Shop prices: NPC Sells: 60 NPC Buys: 30 Holy powder Vita : 0 Mana : 0 Level: 99 Path: Peasant Max. Held in 1 Slot: 1 Uses: 1 Crafts: None Other Uses: None Merchant suggested price: Minimum: 0 Maximum: 0 Effect: Explosion How to Obtain: Arena Shops Comments: None Shop prices: NPC Sells: 500 NPC Buys: 250 Ice shards Vita : 0 Mana : 0 Level: 70 Path: Geomancer Max. Held in 1 Slot: 1 Uses: 1 Crafts: None Other Uses: None Merchant suggested price: Minimum: 0 Maximum: 0 Effect: Explosion How to Obtain: Arena Shops Comments: None Shop prices: NPC Sells: 100 NPC Buys: 50 Moon powder Vita : 0 Mana : 0 Level: 99 Path: Peasant Max. Held in 1 Slot: 1 Uses: 1 Crafts: None Other Uses: None Merchant suggested price: Minimum: 0 Maximum: 0 Effect: Used by Peasent Level 99 How to Obtain: Arena Shops Comments: None Shop prices: NPC Sells: 150 NPC Buys: 75 Rogue's powder Vita : 0 Mana : 0 Level: 30 Path: Rogue Max. Held in 1 Slot: 1 Uses: 1 Crafts: None Other Uses: None Merchant suggested price: Minimum: 0 Maximum: 0 Effect: Used by Rogue Level 30+ How to Obtain: Arena Shops Comments: None Shop prices: NPC Sells: 16 NPC Buys: 8 Shard bomb Vita : 0 Mana : 0 Level: 55 Path: Warrior Max. Held in 1 Slot: 1 Uses: 1 Crafts: None Other Uses: None Merchant suggested price: Minimum: 0 Maximum: 0 Effect: Explosion How to Obtain: Arena Shops Comments: None Shop prices: NPC Sells: 80 NPC Buys: 40 Shatter bomb Vita : 0 Mana : 0 Level: 99 Path: Warrior Max. Held in 1 Slot: 1 Uses: 1 Crafts: None Other Uses: None Merchant suggested price: Minimum: 0 Maximum: 0 Effect: Explosion How to Obtain: Arena Shops Comments: None Shop prices: NPC Sells: 400 NPC Buys: 200 Spark powder Vita : 0 Mana : 0 Level: 50 Path: Peasant Max. Held in 1 Slot: 1 Uses: 1 Crafts: None Other Uses: None Merchant suggested price: Minimum: 0 Maximum: 0 Effect: Used by Peasent Level 50+ How to Obtain: Arena Shops Comments: None Shop prices: NPC Sells: 40 NPC Buys: 20 Spy's explosives Vita : 0 Mana : 0 Level: 70 Path: Spy Max. Held in 1 Slot: 1 Uses: 1 Crafts: None Other Uses: None Merchant suggested price: Minimum: 0 Maximum: 0 Effect: Explosion How to Obtain: Arena Shops Comments: None Shop prices: NPC Sells: 100 NPC Buys: 50 Star powder Vita : 0 Mana : 0 Level: 40 Path: Peasant Max. Held in 1 Slot: 1 Uses: 1 Crafts: None Other Uses: None Merchant suggested price: Minimum: 0 Maximum: 0 Effect: Used by Peasent Level 80+Can be used as a star item in Mage Armor Quest How to Obtain: Arena Shops Comments: None Shop prices: NPC Sells: 100 NPC Buys: 50 Stealth explosives Vita : 0 Mana : 0 Level: 99 Path: Rogue Max. Held in 1 Slot: 1 Uses: 1 Crafts: None Other Uses: None Merchant suggested price: Minimum: 0 Maximum: 0 Effect: Used by Rogue Level 99 How to Obtain: Buya Arena Shop Comments: None Shop prices: NPC Sells: 200 NPC Buys: 100 Stealth powder Vita : 0 Mana : 0 Level: 62 Path: Rogue Max. Held in 1 Slot: 1 Uses: 1 Crafts: None Other Uses: None Merchant suggested price: Minimum: 0 Maximum: 0 Effect: Used by Rogue Level 62+ How to Obtain: Buya Arena Shop Comments: None Shop prices: NPC Sells: 80 NPC Buys: 40 Sun powder Vita : 0 Mana : 0 Level: 99 Path: Peasant Max. Held in 1 Slot: 1 Uses: 1 Crafts: None Other Uses: None Merchant suggested price: Minimum: 0 Maximum: 0 Effect: Explosion How to Obtain: Arena Shops Comments: None Shop prices: NPC Sells: 200 NPC Buys: 100",
      "category": "item",
      "path": [
        "Geomancer"
      ],
      "level_tier": "",
      "stats": {
        "Vita": 0,
        "Mana": 0
      },
      "stack_size": 1,
      "effect": "Explosion",
      "obtain": [
        "Kugnae Arena Shop"
      ],
      "npc_buys": 500
    },
    {
      "id": "items_drops_drops_items_dropped_by_creatures_bombs_crafts_drops_events_keys_mana_potions_quests_rocks_scrolls_shops_spells_vita_woodlands_items_extinct_other_prices_have_been_supplied_by_the_merchants_and_are_suggested_only_and_not_to_be_used_as_the_final_authority_on_value_of_the_item_for_the_most_current_prices_consult_the_merchant_subpath_acorn_vita_8_mana_0_level_0_path_peasant_max_held_in_1_slot_201_uses_1_crafts_none_other_uses_spells_merchant_suggested_price_minimum_0_maximum_0_effect_needed_for_spells_how_to_obtain_squirrel_and_green_squirrels_comments_none_shop_prices_npc_sells_10_npc_buys_10_amber_vita_0_mana_0_level_0_path_peasant_max_held_in_1_slot_100_uses_1_crafts_gemcutting_other_uses_crafts_merchant_suggested_price_minimum_0_maximum_0_effect_none_how_to_obtain_dropped_by_many_creatures_comments_none_shop_prices_npc_sells_0_npc_buys_0_amethyst_vita_0_mana_0_level_0_path_peasant_max_held_in_1_slot_1_uses_1_crafts_none_other_uses_none_merchant_suggested_price_minimum_0_maximum_0_effect_none_how_to_obtain_white_wolf_comments_needed_for_mage_dog_spell_shop_prices_npc_sells_0_npc_buys_600_azure_silk_vita_0_mana_0_level_0_path_peasant_max_held_in_1_slot_1_uses_1_crafts_none_other_uses_none_merchant_suggested_price_minimum_0_maximum_0_effect_none_how_to_obtain_woodlands_rabbit_cave_comments_none_shop_prices_npc_sells_0_npc_buys_0_bear_s_liver_vita_500_mana_0_level_0_path_peasant_max_held_in_1_slot_100_uses_1_crafts_none_other_uses_none_merchant_suggested_price_minimum_0_maximum_0_effect_vita_restoration_how_to_obtain_shops_monsters_poet_call_of_the_wild_spell_comments_none_shop_prices_npc_sells_20_npc_buys_10_bears_tooth_vita_0_mana_0_level_0_path_peasant_max_held_in_1_slot_1_uses_1_crafts_none_other_uses_none_merchant_suggested_price_minimum_0_maximum_0_effect_none_how_to_obtain_woodlands_bear_cave_comments_none_shop_prices_npc_sells_0_npc_buys_0_beautiful_leather_vita_0_mana_0_level_0_path_peasant_max_held_in_1_slot_28_uses_1_crafts_none_other_uses_none_merchant_suggested_price_minimum_0_maximum_0_effect_none_how_to_obtain_woodlands_snake_cave_comments_none_shop_prices_npc_sells_0_npc_buys_0_beef_vita_20_mana_0_level_0_path_peasant_max_held_in_1_slot_100_uses_1_crafts_food_preparation_other_uses_none_merchant_suggested_price_minimum_0_maximum_0_effect_none_how_to_obtain_mythic_oxen_kugnae_mud_snake_comments_none_shop_prices_npc_sells_0_npc_buys_0_bird_meat_vita_100_mana_0_level_0_path_peasant_max_held_in_1_slot_30_uses_1_crafts_food_preparation_other_uses_needed_for_food_preparation_skill_merchant_suggested_price_minimum_0_maximum_0_effect_vita_how_to_obtain_dropped_by_pheasants_in_the_woodlands_comments_none_shop_prices_npc_sells_0_npc_buys_0_bloodstained_quill_vita_0_mana_0_level_0_path_peasant_max_held_in_1_slot_1_uses_1_crafts_none_other_uses_none_merchant_suggested_price_minimum_0_maximum_0_effect_none_how_to_obtain_woodlands_rabbit_cave_comments_none_shop_prices_npc_sells_0_npc_buys_0_bottle_of_venom_vita_0_mana_0_level_0_path_peasant_max_held_in_1_slot_5_uses_1_crafts_none_other_uses_none_merchant_suggested_price_minimum_0_maximum_0_effect_none_how_to_obtain_woodlands_snake_cave_comments_none_shop_prices_npc_sells_0_npc_buys_0_bottled_dog_breath_vita_0_mana_0_level_0_path_peasant_max_held_in_1_slot_1_uses_1_crafts_none_other_uses_none_merchant_suggested_price_minimum_0_maximum_0_effect_none_how_to_obtain_woodlands_dog_cave_comments_none_shop_prices_npc_sells_0_npc_buys_0_boxed_ectoplasm_vita_0_mana_0_level_0_path_peasant_max_held_in_1_slot_1_uses_1_crafts_none_other_uses_none_merchant_suggested_price_minimum_0_maximum_0_effect_none_how_to_obtain_woodlands_dog_cave_comments_none_shop_prices_npc_sells_0_npc_buys_0_bulk_of_sand_vita_0_mana_0_level_0_path_peasant_max_held_in_1_slot_1_uses_1_crafts_none_other_uses_none_merchant_suggested_price_minimum_0_maximum_0_effect_none_how_to_obtain_woodlands_lobster_cave_comments_none_shop_prices_npc_sells_0_npc_buys_0_canine_tooth_vita_0_mana_0_level_0_path_peasant_max_held_in_1_slot_3_uses_1_crafts_none_other_uses_none_merchant_suggested_price_minimum_0_maximum_0_effect_none_how_to_obtain_woodlands_dog_cave_comments_none_shop_prices_npc_sells_0_npc_buys_0_chicken_meat_vita_40_mana_0_level_0_path_peasant_max_held_in_1_slot_30_uses_1_crafts_food_preparation_other_uses_food_preparation_skill_merchant_suggested_price_minimum_0_maximum_0_effect_vita_restoration_how_to_obtain_none_comments_dropped_by_various_chicken_creatures_shop_prices_npc_sells_0_npc_buys_0_corrupted_cloth_vita_0_mana_0_level_0_path_peasant_max_held_in_1_slot_1_uses_1_crafts_none_other_uses_none_merchant_suggested_price_minimum_0_maximum_0_effect_none_how_to_obtain_woodlands_raheem_desert_cave_comments_none_shop_prices_npc_sells_0_npc_buys_0_crystal_water_vita_0_mana_0_level_0_path_peasant_max_held_in_1_slot_1_uses_1_crafts_none_other_uses_none_merchant_suggested_price_minimum_0_maximum_0_effect_none_how_to_obtain_woodlands_raheem_desert_cave_comments_none_shop_prices_npc_sells_0_npc_buys_0_dark_amber_vita_0_mana_0_level_0_path_peasant_max_held_in_1_slot_100_uses_1_crafts_gemcutting_other_uses_crafts_merchant_suggested_price_minimum_0_maximum_0_effect_none_how_to_obtain_dropped_by_many_creatures_comments_none_shop_prices_npc_sells_0_npc_buys_0_dark_essence_vita_0_mana_0_level_0_path_peasant_max_held_in_1_slot_1_uses_1_crafts_none_other_uses_none_merchant_suggested_price_minimum_0_maximum_0_effect_none_how_to_obtain_woodlands_raheem_desert_cave_comments_none_shop_prices_npc_sells_0_npc_buys_0_egg_vita_8_mana_0_level_0_path_peasant_max_held_in_1_slot_12_uses_1_crafts_food_preparation_other_uses_needed_for_food_preparation_skill_merchant_suggested_price_minimum_0_maximum_0_effect_vita_restoration_how_to_obtain_dropped_by_various_chickens_comments_none_shop_prices_npc_sells_0_npc_buys_0_fighter_essence_vita_0_mana_0_level_0_path_peasant_max_held_in_1_slot_1_uses_1_crafts_none_other_uses_none_merchant_suggested_price_minimum_0_maximum_0_effect_none_how_to_obtain_woodlands_bear_cave_comments_none_shop_prices_npc_sells_0_npc_buys_0_fine_rabbit_meat_vita_200_mana_0_level_0_path_peasant_max_held_in_1_slot_100_uses_1_crafts_none_other_uses_none_merchant_suggested_price_minimum_0_maximum_0_effect_vita_restoration_how_to_obtain_mythic_rabbits_comments_none_shop_prices_npc_sells_0_npc_buys_0_fine_silk_vita_0_mana_0_level_0_path_peasant_max_held_in_1_slot_1_uses_1_crafts_none_other_uses_none_merchant_suggested_price_minimum_0_maximum_0_effect_none_how_to_obtain_woodlands_rabbit_cave_comments_none_shop_prices_npc_sells_0_npc_buys_0_fine_snake_meat_vita_320_mana_0_level_0_path_peasant_max_held_in_1_slot_40_uses_1_crafts_alchemy_other_uses_alchemy_lime_potions_merchant_suggested_price_minimum_0_maximum_0_effect_vita_restoration_how_to_obtain_mythic_snakes_comments_none_shop_prices_npc_sells_0_npc_buys_0_finest_snake_meat_vita_0_mana_0_level_0_path_peasant_max_held_in_1_slot_1_uses_1_crafts_none_other_uses_none_merchant_suggested_price_minimum_0_maximum_0_effect_none_how_to_obtain_dropped_by_mud_snake_in_kugnae_snake_cave_comments_none_shop_prices_npc_sells_0_npc_buys_0_focusing_water_vita_0_mana_0_level_0_path_peasant_max_held_in_1_slot_1_uses_1_crafts_none_other_uses_none_merchant_suggested_price_minimum_0_maximum_0_effect_none_how_to_obtain_woodlands_raheem_desert_cave_comments_none_shop_prices_npc_sells_0_npc_buys_0_fox_fur_vita_8_mana_0_level_0_path_peasant_max_held_in_1_slot_100_uses_1_crafts_none_other_uses_none_merchant_suggested_price_minimum_0_maximum_0_effect_none_how_to_obtain_various_foxes_comments_none_shop_prices_npc_sells_0_npc_buys_0_ghostly_essence_vita_0_mana_0_level_0_path_peasant_max_held_in_1_slot_1_uses_4_crafts_none_other_uses_none_merchant_suggested_price_minimum_0_maximum_0_effect_none_how_to_obtain_woodlands_dog_cave_comments_none_shop_prices_npc_sells_0_npc_buys_0_ginseng_vita_2000_mana_0_level_0_path_peasant_max_held_in_1_slot_1_uses_1_crafts_none_other_uses_none_merchant_suggested_price_minimum_0_maximum_0_effect_vita_restoration_how_to_obtain_various_rats_comments_none_shop_prices_npc_sells_0_npc_buys_0_ginseng_piece_vita_60_mana_0_level_0_path_peasant_max_held_in_1_slot_1_uses_1_crafts_none_other_uses_none_merchant_suggested_price_minimum_0_maximum_0_effect_vita_restoration_how_to_obtain_various_rats_comments_none_shop_prices_npc_sells_0_npc_buys_0_gold_acorn_vita_8_mana_0_level_0_path_peasant_max_held_in_1_slot_1_uses_1_crafts_none_other_uses_move_to_other_towns_merchant_suggested_price_minimum_0_maximum_0_effect_vita_restoration_how_to_obtain_various_squirrels_comments_none_shop_prices_npc_sells_0_npc_buys_0_grain_of_sand_vita_0_mana_0_level_0_path_peasant_max_held_in_1_slot_1_uses_1_crafts_none_other_uses_none_merchant_suggested_price_minimum_0_maximum_0_effect_none_how_to_obtain_woodlands_lobster_cave_comments_none_shop_prices_npc_sells_0_npc_buys_0_green_squirrel_pelt_vita_8_mana_0_level_0_path_peasant_max_held_in_1_slot_1_uses_1_crafts_none_other_uses_needed_to_enter_leviathan_quest_area_merchant_suggested_price_minimum_0_maximum_0_effect_vita_restoration_how_to_obtain_green_squirrels_comments_none_shop_prices_npc_sells_0_npc_buys_0_healing_water_vita_0_mana_0_level_0_path_peasant_max_held_in_1_slot_1_uses_1_crafts_none_other_uses_none_merchant_suggested_price_minimum_0_maximum_0_effect_none_how_to_obtain_woodlands_raheem_desert_cave_comments_none_shop_prices_npc_sells_0_npc_buys_0_horse_meat_vita_200_mana_0_level_0_path_peasant_max_held_in_1_slot_100_uses_1_crafts_none_other_uses_none_merchant_suggested_price_minimum_0_maximum_0_effect_vita_restoration_how_to_obtain_mythic_horse_cave_comments_can_be_sold_in_shops_shop_prices_npc_sells_12_npc_buys_12_iron_statue_vita_0_mana_250_level_0_path_peasant_max_held_in_1_slot_1_uses_40_crafts_none_other_uses_none_merchant_suggested_price_minimum_0_maximum_0_effect_mana_restoration_how_to_obtain_dropped_by_gim_yi_in_iron_labrynth_comments_none_shop_prices_npc_sells_0_npc_buys_0_lava_pincer_vita_0_mana_0_level_0_path_peasant_max_held_in_1_slot_1_uses_1_crafts_none_other_uses_none_merchant_suggested_price_minimum_1_500_maximum_3_000_effect_none_how_to_obtain_woodlands_lobster_boss_comments_none_shop_prices_npc_sells_0_npc_buys_0_lean_beef_vita_500_mana_0_level_0_path_peasant_max_held_in_1_slot_50_uses_1_crafts_food_preparation_other_uses_needed_for_food_preparation_skill_merchant_suggested_price_minimum_0_maximum_0_effect_vita_restoration_how_to_obtain_mythic_oxen_kugnae_mud_snake_comments_none_shop_prices_npc_sells_0_npc_buys_0_lucky_rabbits_foot_vita_0_mana_0_level_0_path_peasant_max_held_in_1_slot_1_uses_1_crafts_none_other_uses_none_merchant_suggested_price_minimum_0_maximum_0_effect_none_how_to_obtain_woodlands_rabbit_cave_comments_none_shop_prices_npc_sells_0_npc_buys_0_magical_parchment_vita_0_mana_0_level_0_path_peasant_max_held_in_1_slot_1_uses_1_crafts_none_other_uses_none_merchant_suggested_price_minimum_0_maximum_0_effect_none_how_to_obtain_woodlands_rabbit_cave_comments_none_shop_prices_npc_sells_0_npc_buys_0_magical_texts_vita_0_mana_0_level_0_path_peasant_max_held_in_1_slot_1_uses_1_crafts_none_other_uses_none_merchant_suggested_price_minimum_0_maximum_0_effect_none_how_to_obtain_woodlands_rabbit_cave_comments_none_shop_prices_npc_sells_0_npc_buys_0_malodorous_fish_vita_80_mana_0_level_0_path_peasant_max_held_in_1_slot_100_uses_1_crafts_none_other_uses_trade_for_items_in_chum_s_fish_hut_hamgyong_nam_do_merchant_suggested_price_minimum_0_maximum_0_effect_vita_restoration_how_to_obtain_river_ogres_comments_none_shop_prices_npc_sells_0_npc_buys_0_mountain_ginseng_vita_10000_mana_0_level_0_path_peasant_max_held_in_1_slot_10_uses_1_crafts_none_other_uses_spells_merchant_suggested_price_minimum_2_000_maximum_5_000_effect_vita_restoration_how_to_obtain_clan_shops_comments_dropped_by_town_rabbit_cave_bosses_shop_prices_npc_sells_2_000_npc_buys_1_000_poisoned_water_vita_0_mana_0_level_0_path_peasant_max_held_in_1_slot_1_uses_1_crafts_none_other_uses_none_merchant_suggested_price_minimum_0_maximum_0_effect_none_how_to_obtain_woodlands_raheem_desert_cave_comments_none_shop_prices_npc_sells_0_npc_buys_0_pork_vita_128_mana_0_level_0_path_peasant_max_held_in_1_slot_1_uses_1_crafts_none_other_uses_none_merchant_suggested_price_minimum_0_maximum_0_effect_vita_restoration_how_to_obtain_dropped_in_mythic_pig_cave_and_kugnae_snake_cave_comments_none_shop_prices_npc_sells_10_npc_buys_5_prism_amber_vita_0_mana_0_level_0_path_peasant_max_held_in_1_slot_1_uses_1_crafts_none_other_uses_none_merchant_suggested_price_minimum_0_maximum_0_effect_none_how_to_obtain_woodlands_dog_cave_comments_none_shop_prices_npc_sells_0_npc_buys_0_putrid_fish_vita_120_mana_0_level_0_path_peasant_max_held_in_1_slot_100_uses_1_crafts_none_other_uses_trade_for_items_in_chum_s_fish_hut_hamgyong_nam_do_merchant_suggested_price_minimum_0_maximum_0_effect_vita_restoration_how_to_obtain_river_ogres_comments_none_shop_prices_npc_sells_0_npc_buys_0_rabbit_meat_vita_48_mana_0_level_0_path_peasant_max_held_in_1_slot_200_uses_1_crafts_none_other_uses_spell_item_merchant_suggested_price_minimum_0_maximum_0_effect_needs_for_spells_how_to_obtain_dropped_by_various_rabbits_comments_none_shop_prices_npc_sells_2_npc_buys_2_rabbits_foot_vita_0_mana_0_level_0_path_peasant_max_held_in_1_slot_1_uses_1_crafts_none_other_uses_none_merchant_suggested_price_minimum_0_maximum_0_effect_none_how_to_obtain_woodlands_rabbit_cave_comments_none_shop_prices_npc_sells_0_npc_buys_0_rabid_saliva_vita_0_mana_0_level_0_path_peasant_max_held_in_1_slot_1_uses_2_crafts_none_other_uses_none_merchant_suggested_price_minimum_0_maximum_0_effect_none_how_to_obtain_woodlands_dog_cave_comments_none_shop_prices_npc_sells_0_npc_buys_0_red_fox_fur_vita_8_mana_0_level_0_path_peasant_max_held_in_1_slot_100_uses_1_crafts_none_other_uses_none_merchant_suggested_price_minimum_0_maximum_0_effect_none_how_to_obtain_various_foxes_comments_none_shop_prices_npc_sells_0_npc_buys_0_repugnant_fish_vita_80_mana_0_level_0_path_peasant_max_held_in_1_slot_100_uses_1_crafts_none_other_uses_trade_for_items_in_chum_s_fish_hut_hamgyong_nam_do_merchant_suggested_price_minimum_0_maximum_0_effect_vita_restoration_how_to_obtain_river_ogres_comments_none_shop_prices_npc_sells_0_npc_buys_0_ripped_talon_vita_0_mana_0_level_0_path_peasant_max_held_in_1_slot_1_uses_1_crafts_none_other_uses_none_merchant_suggested_price_minimum_0_maximum_0_effect_none_how_to_obtain_woodlands_bear_cave_comments_none_shop_prices_npc_sells_0_npc_buys_0_rock_vita_0_mana_0_level_0_path_peasant_max_held_in_1_slot_1_uses_1_crafts_none_other_uses_none_merchant_suggested_price_minimum_0_maximum_0_effect_none_how_to_obtain_woodlands_raheem_desert_cave_comments_none_shop_prices_npc_sells_0_npc_buys_0_sacred_oil_vita_0_mana_0_level_0_path_peasant_max_held_in_1_slot_1_uses_1_crafts_none_other_uses_none_merchant_suggested_price_minimum_0_maximum_0_effect_none_how_to_obtain_woodlands_raheem_desert_cave_comments_none_shop_prices_npc_sells_0_npc_buys_0_scaled_leather_vita_0_mana_0_level_0_path_peasant_max_held_in_1_slot_10_uses_1_crafts_none_other_uses_none_merchant_suggested_price_minimum_0_maximum_0_effect_none_how_to_obtain_woodlands_snake_cave_comments_none_shop_prices_npc_sells_0_npc_buys_0_scorpions_stinger_vita_0_mana_0_level_0_path_peasant_max_held_in_1_slot_1_uses_1_crafts_none_other_uses_none_merchant_suggested_price_minimum_0_maximum_0_effect_none_how_to_obtain_woodlands_raheem_desert_cave_comments_none_shop_prices_npc_sells_0_npc_buys_0_seaweed_vita_400_mana_0_level_0_path_peasant_max_held_in_1_slot_25_uses_1_crafts_none_other_uses_none_merchant_suggested_price_minimum_0_maximum_0_effect_vita_restoration_how_to_obtain_dropped_by_island_lobsters_in_hausson_dropped_by_most_snakes_in_woodlands_snake_cave_comments_none_shop_prices_npc_sells_0_npc_buys_0_silk_vita_0_mana_0_level_0_path_peasant_max_held_in_1_slot_1_uses_1_crafts_none_other_uses_none_merchant_suggested_price_minimum_0_maximum_0_effect_none_how_to_obtain_woodlands_rabbit_cave_comments_none_shop_prices_npc_sells_0_npc_buys_0_snake_leather_vita_0_mana_0_level_0_path_peasant_max_held_in_1_slot_10_uses_1_crafts_none_other_uses_none_merchant_suggested_price_minimum_0_maximum_0_effect_none_how_to_obtain_woodlands_snake_cave_comments_none_shop_prices_npc_sells_0_npc_buys_0_snake_meat_vita_100_mana_0_level_0_path_peasant_max_held_in_1_slot_100_uses_1_crafts_none_other_uses_crafts_merchant_suggested_price_minimum_0_maximum_0_effect_vita_restoration_how_to_obtain_various_snakes_comments_none_shop_prices_npc_sells_0_npc_buys_0_snake_tongue_vita_0_mana_0_level_0_path_peasant_max_held_in_1_slot_5_uses_1_crafts_none_other_uses_none_merchant_suggested_price_minimum_0_maximum_0_effect_none_how_to_obtain_woodlands_snake_cave_comments_none_shop_prices_npc_sells_0_npc_buys_0_splendid_silk_vita_0_mana_0_level_0_path_peasant_max_held_in_1_slot_1_uses_1_crafts_none_other_uses_none_merchant_suggested_price_minimum_0_maximum_0_effect_none_how_to_obtain_woodlands_rabbit_cave_comments_none_shop_prices_npc_sells_0_npc_buys_0_spring_water_vita_0_mana_0_level_0_path_peasant_max_held_in_1_slot_1_uses_1_crafts_none_other_uses_none_merchant_suggested_price_minimum_0_maximum_0_effect_none_how_to_obtain_woodlands_raheem_desert_cave_comments_none_shop_prices_npc_sells_0_npc_buys_0_sunken_silk_vita_0_mana_0_level_0_path_peasant_max_held_in_1_slot_1_uses_1_crafts_none_other_uses_none_merchant_suggested_price_minimum_0_maximum_0_effect_none_how_to_obtain_woodlands_raheem_desert_cave_comments_none_shop_prices_npc_sells_0_npc_buys_0_tako_ink_vita_0_mana_0_level_0_path_peasant_max_held_in_1_slot_10_uses_1_crafts_none_other_uses_none_merchant_suggested_price_minimum_0_maximum_0_effect_none_how_to_obtain_woodlands_snake_cave_comments_none_shop_prices_npc_sells_0_npc_buys_0_tattered_leather_vita_0_mana_0_level_0_path_peasant_max_held_in_1_slot_20_uses_1_crafts_none_other_uses_none_merchant_suggested_price_minimum_0_maximum_0_effect_none_how_to_obtain_woodlands_snake_cave_comments_none_shop_prices_npc_sells_0_npc_buys_0_tiger_meat_vita_100_mana_0_level_0_path_peasant_max_held_in_1_slot_10_uses_1_crafts_food_preparation_other_uses_subpath_quest_item_merchant_suggested_price_minimum_0_maximum_0_effect_vita_restoration_how_to_obtain_dropped_by_iron_lab_tigers_comments_none_shop_prices_npc_sells_100_npc_buys_50_tiger_s_heart_vita_1000_mana_0_level_0_path_peasant_max_held_in_1_slot_20_uses_1_crafts_none_other_uses_none_merchant_suggested_price_minimum_0_maximum_0_effect_vita_restoration_how_to_obtain_shops_monsters_poet_call_of_the_wild_spell_comments_none_shop_prices_npc_sells_60_npc_buys_30_tormented_tome_vita_0_mana_0_level_0_path_peasant_max_held_in_1_slot_1_uses_1_crafts_none_other_uses_none_merchant_suggested_price_minimum_0_maximum_0_effect_none_how_to_obtain_woodlands_raheem_desert_cave_comments_none_shop_prices_npc_sells_0_npc_buys_0_torn_paw_vita_0_mana_0_level_0_path_peasant_max_held_in_1_slot_2_uses_1_crafts_none_other_uses_none_merchant_suggested_price_minimum_0_maximum_0_effect_none_how_to_obtain_woodlands_dog_cave_comments_none_shop_prices_npc_sells_0_npc_buys_0_unleashed_anger_vita_0_mana_0_level_0_path_peasant_max_held_in_1_slot_1_uses_1_crafts_none_other_uses_none_merchant_suggested_price_minimum_0_maximum_0_effect_none_how_to_obtain_woodlands_bear_cave_comments_none_shop_prices_npc_sells_0_npc_buys_0_venom_sac_vita_0_mana_0_level_0_path_peasant_max_held_in_1_slot_5_uses_1_crafts_none_other_uses_none_merchant_suggested_price_minimum_0_maximum_0_effect_none_how_to_obtain_woodlands_snake_cave_comments_none_shop_prices_npc_sells_0_npc_buys_0_vile_vial_vita_0_mana_0_level_0_path_peasant_max_held_in_1_slot_1_uses_1_crafts_none_other_uses_none_merchant_suggested_price_minimum_0_maximum_0_effect_none_how_to_obtain_woodlands_lobster_cave_comments_none_shop_prices_npc_sells_0_npc_buys_0_wagging_tail_vita_0_mana_0_level_0_path_peasant_max_held_in_1_slot_3_uses_1_crafts_none_other_uses_none_merchant_suggested_price_minimum_0_maximum_0_effect_none_how_to_obtain_woodlands_dog_cave_comments_none_shop_prices_npc_sells_0_npc_buys_0_white_amber_vita_0_mana_0_level_0_path_peasant_max_held_in_1_slot_20_uses_1_crafts_gemcutting_other_uses_crafts_merchant_suggested_price_minimum_0_maximum_0_effect_none_how_to_obtain_dropped_by_many_creatures_comments_none_shop_prices_npc_sells_0_npc_buys_0_wicked_wool_vita_0_mana_0_level_0_path_peasant_max_held_in_1_slot_1_uses_1_crafts_none_other_uses_none_merchant_suggested_price_minimum_0_maximum_0_effect_none_how_to_obtain_woodlands_raheem_desert_cave_comments_none_shop_prices_npc_sells_0_npc_buys_0_wolf_meat_vita_48_mana_0_level_0_path_peasant_max_held_in_1_slot_1_uses_1_crafts_none_other_uses_needed_for_chung_ryong_helm_et_merchant_suggested_price_minimum_0_maximum_0_effect_vita_restoration_how_to_obtain_dropped_by_various_wolves_comments_none_shop_prices_npc_sells_4_npc_buys_2_yellow_amber_vita_0_mana_0_level_0_path_peasant_max_held_in_1_slot_20_uses_1_crafts_gemcutting_other_uses_crafts_merchant_suggested_price_minimum_0_maximum_0_effect_none_how_to_obtain_dropped_by_many_creatures_comments_none_shop_prices_npc_sells_0_npc_buys_0_young_ginseng_vita_40_mana_0_level_0_path_peasant_max_held_in_1_slot_1_uses_1_crafts_none_other_uses_none_merchant_suggested_price_minimum_0_maximum_0_effect_vita_restoration_how_to_obtain_chu_rua_comments_none_shop_prices_npc_sells_0_npc_buys_0",
      "name": "Items | Drops Drops Items dropped by creatures. Bombs / Crafts / Drops / Events / Keys / Mana / Potions / Quests Rocks / Scrolls / Shops / Spells / Vita / Woodlands Items / Extinct / Other Prices have been supplied by the Merchants and are suggested only and not to be used as the final authority on value of the item. For the most current prices consult the Merchant Subpath. Acorn Vita : 8 Mana : 0 Level: 0 Path: Peasant Max. Held in 1 Slot: 201 Uses: 1 Crafts: None Other Uses: Spells Merchant suggested price: Minimum: 0 Maximum: 0 Effect: Needed for spells How to Obtain: Squirrel and Green squirrels Comments: None Shop prices: NPC Sells: 10 NPC Buys: 10 Amber Vita : 0 Mana : 0 Level: 0 Path: Peasant Max. Held in 1 Slot: 100 Uses: 1 Crafts: Gemcutting Other Uses: Crafts Merchant suggested price: Minimum: 0 Maximum: 0 Effect: None How to Obtain: Dropped by many creatures Comments: None Shop prices: NPC Sells: 0 NPC Buys: 0 Amethyst Vita : 0 Mana : 0 Level: 0 Path: Peasant Max. Held in 1 Slot: 1 Uses: 1 Crafts: None Other Uses: None Merchant suggested price: Minimum: 0 Maximum: 0 Effect: None How to Obtain: White wolf Comments: Needed for mage dog spell Shop prices: NPC Sells: 0 NPC Buys: 600 Azure silk Vita : 0 Mana : 0 Level: 0 Path: Peasant Max. Held in 1 Slot: 1 Uses: 1 Crafts: None Other Uses: None Merchant suggested price: Minimum: 0 Maximum: 0 Effect: None How to Obtain: Woodlands Rabbit Cave Comments: None Shop prices: NPC Sells: 0 NPC Buys: 0 Bear's liver Vita : 500 Mana : 0 Level: 0 Path: Peasant Max. Held in 1 Slot: 100 Uses: 1 Crafts: None Other Uses: None Merchant suggested price: Minimum: 0 Maximum: 0 Effect: Vita restoration How to Obtain: Shops, monsters, poet Call of the Wild spell Comments: None Shop prices: NPC Sells: 20 NPC Buys: 10 Bears tooth Vita : 0 Mana : 0 Level: 0 Path: Peasant Max. Held in 1 Slot: 1 Uses: 1 Crafts: None Other Uses: None Merchant suggested price: Minimum: 0 Maximum: 0 Effect: None How to Obtain: Woodlands Bear Cave Comments: None Shop prices: NPC Sells: 0 NPC Buys: 0 Beautiful leather Vita : 0 Mana : 0 Level: 0 Path: Peasant Max. Held in 1 Slot: 28 Uses: 1 Crafts: None Other Uses: None Merchant suggested price: Minimum: 0 Maximum: 0 Effect: None How to Obtain: Woodlands Snake Cave Comments: None Shop prices: NPC Sells: 0 NPC Buys: 0 Beef Vita : 20 Mana : 0 Level: 0 Path: Peasant Max. Held in 1 Slot: 100 Uses: 1 Crafts: Food preparation Other Uses: None Merchant suggested price: Minimum: 0 Maximum: 0 Effect: None How to Obtain: Mythic Oxen, Kugnae Mud Snake Comments: None Shop prices: NPC Sells: 0 NPC Buys: 0 Bird meat Vita : 100 Mana : 0 Level: 0 Path: Peasant Max. Held in 1 Slot: 30 Uses: 1 Crafts: Food preparation Other Uses: Needed for food preparation skill Merchant suggested price: Minimum: 0 Maximum: 0 Effect: Vita How to Obtain: Dropped by Pheasants in the Woodlands Comments: None Shop prices: NPC Sells: 0 NPC Buys: 0 Bloodstained quill Vita : 0 Mana : 0 Level: 0 Path: Peasant Max. Held in 1 Slot: 1 Uses: 1 Crafts: None Other Uses: None Merchant suggested price: Minimum: 0 Maximum: 0 Effect: None How to Obtain: Woodlands Rabbit Cave Comments: None Shop prices: NPC Sells: 0 NPC Buys: 0 Bottle of venom Vita : 0 Mana : 0 Level: 0 Path: Peasant Max. Held in 1 Slot: 5 Uses: 1 Crafts: None Other Uses: None Merchant suggested price: Minimum: 0 Maximum: 0 Effect: None How to Obtain: Woodlands Snake Cave Comments: None Shop prices: NPC Sells: 0 NPC Buys: 0 Bottled dog breath Vita : 0 Mana : 0 Level: 0 Path: Peasant Max. Held in 1 Slot: 1 Uses: 1 Crafts: None Other Uses: None Merchant suggested price: Minimum: 0 Maximum: 0 Effect: None How to Obtain: Woodlands Dog Cave Comments: None Shop prices: NPC Sells: 0 NPC Buys: 0 Boxed ectoplasm Vita : 0 Mana : 0 Level: 0 Path: Peasant Max. Held in 1 Slot: 1 Uses: 1 Crafts: None Other Uses: None Merchant suggested price: Minimum: 0 Maximum: 0 Effect: None How to Obtain: Woodlands Dog Cave Comments: None Shop prices: NPC Sells: 0 NPC Buys: 0 Bulk of sand Vita : 0 Mana : 0 Level: 0 Path: Peasant Max. Held in 1 Slot: 1 Uses: 1 Crafts: None Other Uses: None Merchant suggested price: Minimum: 0 Maximum: 0 Effect: None How to Obtain: Woodlands Lobster Cave Comments: None Shop prices: NPC Sells: 0 NPC Buys: 0 Canine tooth Vita : 0 Mana : 0 Level: 0 Path: Peasant Max. Held in 1 Slot: 3 Uses: 1 Crafts: None Other Uses: None Merchant suggested price: Minimum: 0 Maximum: 0 Effect: None How to Obtain: Woodlands Dog Cave Comments: None Shop prices: NPC Sells: 0 NPC Buys: 0 Chicken meat Vita : 40 Mana : 0 Level: 0 Path: Peasant Max. Held in 1 Slot: 30 Uses: 1 Crafts: Food preparation Other Uses: Food preparation skill Merchant suggested price: Minimum: 0 Maximum: 0 Effect: Vita restoration How to Obtain: None Comments: Dropped by various chicken creatures Shop prices: NPC Sells: 0 NPC Buys: 0 Corrupted cloth Vita : 0 Mana : 0 Level: 0 Path: Peasant Max. Held in 1 Slot: 1 Uses: 1 Crafts: None Other Uses: None Merchant suggested price: Minimum: 0 Maximum: 0 Effect: None How to Obtain: Woodlands Raheem Desert Cave Comments: None Shop prices: NPC Sells: 0 NPC Buys: 0 Crystal water Vita : 0 Mana : 0 Level: 0 Path: Peasant Max. Held in 1 Slot: 1 Uses: 1 Crafts: None Other Uses: None Merchant suggested price: Minimum: 0 Maximum: 0 Effect: None How to Obtain: Woodlands Raheem Desert Cave Comments: None Shop prices: NPC Sells: 0 NPC Buys: 0 Dark amber Vita : 0 Mana : 0 Level: 0 Path: Peasant Max. Held in 1 Slot: 100 Uses: 1 Crafts: Gemcutting Other Uses: Crafts Merchant suggested price: Minimum: 0 Maximum: 0 Effect: None How to Obtain: Dropped by many creatures Comments: None Shop prices: NPC Sells: 0 NPC Buys: 0 Dark essence Vita : 0 Mana : 0 Level: 0 Path: Peasant Max. Held in 1 Slot: 1 Uses: 1 Crafts: None Other Uses: None Merchant suggested price: Minimum: 0 Maximum: 0 Effect: None How to Obtain: Woodlands Raheem Desert Cave Comments: None Shop prices: NPC Sells: 0 NPC Buys: 0 Egg Vita : 8 Mana : 0 Level: 0 Path: Peasant Max. Held in 1 Slot: 12 Uses: 1 Crafts: Food preparation Other Uses: Needed for food preparation skill Merchant suggested price: Minimum: 0 Maximum: 0 Effect: Vita restoration How to Obtain: Dropped by various chickens Comments: None Shop prices: NPC Sells: 0 NPC Buys: 0 Fighter essence Vita : 0 Mana : 0 Level: 0 Path: Peasant Max. Held in 1 Slot: 1 Uses: 1 Crafts: None Other Uses: None Merchant suggested price: Minimum: 0 Maximum: 0 Effect: None How to Obtain: Woodlands Bear Cave Comments: None Shop prices: NPC Sells: 0 NPC Buys: 0 Fine rabbit meat Vita : 200 Mana : 0 Level: 0 Path: Peasant Max. Held in 1 Slot: 100 Uses: 1 Crafts: None Other Uses: None Merchant suggested price: Minimum: 0 Maximum: 0 Effect: Vita restoration How to Obtain: Mythic rabbits Comments: None Shop prices: NPC Sells: 0 NPC Buys: 0 Fine silk Vita : 0 Mana : 0 Level: 0 Path: Peasant Max. Held in 1 Slot: 1 Uses: 1 Crafts: None Other Uses: None Merchant suggested price: Minimum: 0 Maximum: 0 Effect: None How to Obtain: Woodlands Rabbit Cave Comments: None Shop prices: NPC Sells: 0 NPC Buys: 0 Fine snake meat Vita : 320 Mana : 0 Level: 0 Path: Peasant Max. Held in 1 Slot: 40 Uses: 1 Crafts: Alchemy Other Uses: Alchemy - lime potions Merchant suggested price: Minimum: 0 Maximum: 0 Effect: Vita restoration How to Obtain: Mythic Snakes Comments: None Shop prices: NPC Sells: 0 NPC Buys: 0 Finest snake meat Vita : 0 Mana : 0 Level: 0 Path: Peasant Max. Held in 1 Slot: 1 Uses: 1 Crafts: None Other Uses: None Merchant suggested price: Minimum: 0 Maximum: 0 Effect: None How to Obtain: Dropped by Mud snake in Kugnae snake cave Comments: None Shop prices: NPC Sells: 0 NPC Buys: 0 Focusing water Vita : 0 Mana : 0 Level: 0 Path: Peasant Max. Held in 1 Slot: 1 Uses: 1 Crafts: None Other Uses: None Merchant suggested price: Minimum: 0 Maximum: 0 Effect: None How to Obtain: Woodlands Raheem Desert Cave Comments: None Shop prices: NPC Sells: 0 NPC Buys: 0 Fox fur Vita : 8 Mana : 0 Level: 0 Path: Peasant Max. Held in 1 Slot: 100 Uses: 1 Crafts: None Other Uses: None Merchant suggested price: Minimum: 0 Maximum: 0 Effect: None How to Obtain: Various foxes Comments: None Shop prices: NPC Sells: 0 NPC Buys: 0 Ghostly essence Vita : 0 Mana : 0 Level: 0 Path: Peasant Max. Held in 1 Slot: 1 Uses: 4 Crafts: None Other Uses: None Merchant suggested price: Minimum: 0 Maximum: 0 Effect: None How to Obtain: Woodlands Dog Cave Comments: None Shop prices: NPC Sells: 0 NPC Buys: 0 Ginseng Vita : 2000 Mana : 0 Level: 0 Path: Peasant Max. Held in 1 Slot: 1 Uses: 1 Crafts: None Other Uses: None Merchant suggested price: Minimum: 0 Maximum: 0 Effect: Vita restoration How to Obtain: Various rats Comments: None Shop prices: NPC Sells: 0 NPC Buys: 0 Ginseng piece Vita : 60 Mana : 0 Level: 0 Path: Peasant Max. Held in 1 Slot: 1 Uses: 1 Crafts: None Other Uses: None Merchant suggested price: Minimum: 0 Maximum: 0 Effect: Vita restoration How to Obtain: Various rats Comments: None Shop prices: NPC Sells: 0 NPC Buys: 0 Gold acorn Vita : 8 Mana : 0 Level: 0 Path: Peasant Max. Held in 1 Slot: 1 Uses: 1 Crafts: None Other Uses: Move to other towns Merchant suggested price: Minimum: 0 Maximum: 0 Effect: Vita restoration How to Obtain: Various squirrels Comments: None Shop prices: NPC Sells: 0 NPC Buys: 0 Grain of sand Vita : 0 Mana : 0 Level: 0 Path: Peasant Max. Held in 1 Slot: 1 Uses: 1 Crafts: None Other Uses: None Merchant suggested price: Minimum: 0 Maximum: 0 Effect: None How to Obtain: Woodlands Lobster Cave Comments: None Shop prices: NPC Sells: 0 NPC Buys: 0 Green squirrel pelt Vita : 8 Mana : 0 Level: 0 Path: Peasant Max. Held in 1 Slot: 1 Uses: 1 Crafts: None Other Uses: Needed to enter Leviathan Quest area Merchant suggested price: Minimum: 0 Maximum: 0 Effect: Vita restoration How to Obtain: Green squirrels Comments: None Shop prices: NPC Sells: 0 NPC Buys: 0 Healing water Vita : 0 Mana : 0 Level: 0 Path: Peasant Max. Held in 1 Slot: 1 Uses: 1 Crafts: None Other Uses: None Merchant suggested price: Minimum: 0 Maximum: 0 Effect: None How to Obtain: Woodlands Raheem Desert Cave Comments: None Shop prices: NPC Sells: 0 NPC Buys: 0 Horse meat Vita : 200 Mana : 0 Level: 0 Path: Peasant Max. Held in 1 Slot: 100 Uses: 1 Crafts: None Other Uses: None Merchant suggested price: Minimum: 0 Maximum: 0 Effect: Vita restoration How to Obtain: Mythic horse cave Comments: Can be sold in shops Shop prices: NPC Sells: 12 NPC Buys: 12 Iron statue Vita : 0 Mana : 250 Level: 0 Path: Peasant Max. Held in 1 Slot: 1 Uses: 40 Crafts: None Other Uses: None Merchant suggested price: Minimum: 0 Maximum: 0 Effect: Mana restoration How to Obtain: Dropped by Gim-yi in Iron Labrynth Comments: None Shop prices: NPC Sells: 0 NPC Buys: 0 Lava pincer Vita : 0 Mana : 0 Level: 0 Path: Peasant Max. Held in 1 Slot: 1 Uses: 1 Crafts: None Other Uses: None Merchant suggested price: Minimum: 1,500 Maximum: 3,000 Effect: None How to Obtain: Woodlands Lobster Boss Comments: None Shop prices: NPC Sells: 0 NPC Buys: 0 Lean beef Vita : 500 Mana : 0 Level: 0 Path: Peasant Max. Held in 1 Slot: 50 Uses: 1 Crafts: Food preparation Other Uses: Needed for food preparation skill Merchant suggested price: Minimum: 0 Maximum: 0 Effect: Vita restoration How to Obtain: Mythic Oxen, Kugnae Mud Snake Comments: None Shop prices: NPC Sells: 0 NPC Buys: 0 Lucky rabbits foot Vita : 0 Mana : 0 Level: 0 Path: Peasant Max. Held in 1 Slot: 1 Uses: 1 Crafts: None Other Uses: None Merchant suggested price: Minimum: 0 Maximum: 0 Effect: None How to Obtain: Woodlands Rabbit Cave Comments: None Shop prices: NPC Sells: 0 NPC Buys: 0 Magical parchment Vita : 0 Mana : 0 Level: 0 Path: Peasant Max. Held in 1 Slot: 1 Uses: 1 Crafts: None Other Uses: None Merchant suggested price: Minimum: 0 Maximum: 0 Effect: None How to Obtain: Woodlands Rabbit Cave Comments: None Shop prices: NPC Sells: 0 NPC Buys: 0 Magical texts Vita : 0 Mana : 0 Level: 0 Path: Peasant Max. Held in 1 Slot: 1 Uses: 1 Crafts: None Other Uses: None Merchant suggested price: Minimum: 0 Maximum: 0 Effect: None How to Obtain: Woodlands Rabbit Cave Comments: None Shop prices: NPC Sells: 0 NPC Buys: 0 Malodorous fish Vita : 80 Mana : 0 Level: 0 Path: Peasant Max. Held in 1 Slot: 100 Uses: 1 Crafts: None Other Uses: Trade for items in Chum's Fish Hut, Hamgyong nam-do Merchant suggested price: Minimum: 0 Maximum: 0 Effect: Vita restoration How to Obtain: River Ogres Comments: None Shop prices: NPC Sells: 0 NPC Buys: 0 Mountain ginseng Vita : 10000 Mana : 0 Level: 0 Path: Peasant Max. Held in 1 Slot: 10 Uses: 1 Crafts: None Other Uses: Spells Merchant suggested price: Minimum: 2,000 Maximum: 5,000 Effect: Vita restoration How to Obtain: Clan Shops Comments: Dropped by Town Rabbit Cave bosses Shop prices: NPC Sells: 2,000 NPC Buys: 1,000 Poisoned water Vita : 0 Mana : 0 Level: 0 Path: Peasant Max. Held in 1 Slot: 1 Uses: 1 Crafts: None Other Uses: None Merchant suggested price: Minimum: 0 Maximum: 0 Effect: None How to Obtain: Woodlands Raheem Desert Cave Comments: None Shop prices: NPC Sells: 0 NPC Buys: 0 Pork Vita : 128 Mana : 0 Level: 0 Path: Peasant Max. Held in 1 Slot: 1 Uses: 1 Crafts: None Other Uses: None Merchant suggested price: Minimum: 0 Maximum: 0 Effect: Vita restoration How to Obtain: Dropped in Mythic Pig Cave and Kugnae Snake Cave Comments: None Shop prices: NPC Sells: 10 NPC Buys: 5 Prism amber Vita : 0 Mana : 0 Level: 0 Path: Peasant Max. Held in 1 Slot: 1 Uses: 1 Crafts: None Other Uses: None Merchant suggested price: Minimum: 0 Maximum: 0 Effect: None How to Obtain: Woodlands Dog Cave Comments: None Shop prices: NPC Sells: 0 NPC Buys: 0 Putrid fish Vita : 120 Mana : 0 Level: 0 Path: Peasant Max. Held in 1 Slot: 100 Uses: 1 Crafts: None Other Uses: Trade for items in Chum's Fish Hut, Hamgyong nam-do Merchant suggested price: Minimum: 0 Maximum: 0 Effect: Vita restoration How to Obtain: River Ogres Comments: None Shop prices: NPC Sells: 0 NPC Buys: 0 Rabbit meat Vita : 48 Mana : 0 Level: 0 Path: Peasant Max. Held in 1 Slot: 200 Uses: 1 Crafts: None Other Uses: Spell item Merchant suggested price: Minimum: 0 Maximum: 0 Effect: Needs for spells How to Obtain: Dropped by various rabbits Comments: None Shop prices: NPC Sells: 2 NPC Buys: 2 Rabbits foot Vita : 0 Mana : 0 Level: 0 Path: Peasant Max. Held in 1 Slot: 1 Uses: 1 Crafts: None Other Uses: None Merchant suggested price: Minimum: 0 Maximum: 0 Effect: None How to Obtain: Woodlands Rabbit Cave Comments: None Shop prices: NPC Sells: 0 NPC Buys: 0 Rabid saliva Vita : 0 Mana : 0 Level: 0 Path: Peasant Max. Held in 1 Slot: 1 Uses: 2 Crafts: None Other Uses: None Merchant suggested price: Minimum: 0 Maximum: 0 Effect: None How to Obtain: Woodlands Dog Cave Comments: None Shop prices: NPC Sells: 0 NPC Buys: 0 Red fox fur Vita : 8 Mana : 0 Level: 0 Path: Peasant Max. Held in 1 Slot: 100 Uses: 1 Crafts: None Other Uses: None Merchant suggested price: Minimum: 0 Maximum: 0 Effect: None How to Obtain: Various foxes Comments: None Shop prices: NPC Sells: 0 NPC Buys: 0 Repugnant fish Vita : 80 Mana : 0 Level: 0 Path: Peasant Max. Held in 1 Slot: 100 Uses: 1 Crafts: None Other Uses: Trade for items in Chum's Fish Hut, Hamgyong nam-do Merchant suggested price: Minimum: 0 Maximum: 0 Effect: Vita restoration How to Obtain: River Ogres Comments: None Shop prices: NPC Sells: 0 NPC Buys: 0 Ripped talon Vita : 0 Mana : 0 Level: 0 Path: Peasant Max. Held in 1 Slot: 1 Uses: 1 Crafts: None Other Uses: None Merchant suggested price: Minimum: 0 Maximum: 0 Effect: None How to Obtain: Woodlands Bear Cave Comments: None Shop prices: NPC Sells: 0 NPC Buys: 0 Rock Vita : 0 Mana : 0 Level: 0 Path: Peasant Max. Held in 1 Slot: 1 Uses: 1 Crafts: None Other Uses: None Merchant suggested price: Minimum: 0 Maximum: 0 Effect: None How to Obtain: Woodlands Raheem Desert Cave Comments: None Shop prices: NPC Sells: 0 NPC Buys: 0 Sacred oil Vita : 0 Mana : 0 Level: 0 Path: Peasant Max. Held in 1 Slot: 1 Uses: 1 Crafts: None Other Uses: None Merchant suggested price: Minimum: 0 Maximum: 0 Effect: None How to Obtain: Woodlands Raheem Desert Cave Comments: None Shop prices: NPC Sells: 0 NPC Buys: 0 Scaled leather Vita : 0 Mana : 0 Level: 0 Path: Peasant Max. Held in 1 Slot: 10 Uses: 1 Crafts: None Other Uses: None Merchant suggested price: Minimum: 0 Maximum: 0 Effect: None How to Obtain: Woodlands Snake Cave Comments: None Shop prices: NPC Sells: 0 NPC Buys: 0 Scorpions stinger Vita : 0 Mana : 0 Level: 0 Path: Peasant Max. Held in 1 Slot: 1 Uses: 1 Crafts: None Other Uses: None Merchant suggested price: Minimum: 0 Maximum: 0 Effect: None How to Obtain: Woodlands Raheem Desert Cave Comments: None Shop prices: NPC Sells: 0 NPC Buys: 0 Seaweed Vita : 400 Mana : 0 Level: 0 Path: Peasant Max. Held in 1 Slot: 25 Uses: 1 Crafts: None Other Uses: None Merchant suggested price: Minimum: 0 Maximum: 0 Effect: Vita restoration How to Obtain: Dropped by Island Lobsters in Hausson. Dropped by most snakes in Woodlands Snake Cave. Comments: None Shop prices: NPC Sells: 0 NPC Buys: 0 Silk Vita : 0 Mana : 0 Level: 0 Path: Peasant Max. Held in 1 Slot: 1 Uses: 1 Crafts: None Other Uses: None Merchant suggested price: Minimum: 0 Maximum: 0 Effect: None How to Obtain: Woodlands Rabbit Cave Comments: None Shop prices: NPC Sells: 0 NPC Buys: 0 Snake leather Vita : 0 Mana : 0 Level: 0 Path: Peasant Max. Held in 1 Slot: 10 Uses: 1 Crafts: None Other Uses: None Merchant suggested price: Minimum: 0 Maximum: 0 Effect: None How to Obtain: Woodlands Snake Cave Comments: None Shop prices: NPC Sells: 0 NPC Buys: 0 Snake meat Vita : 100 Mana : 0 Level: 0 Path: Peasant Max. Held in 1 Slot: 100 Uses: 1 Crafts: None Other Uses: Crafts Merchant suggested price: Minimum: 0 Maximum: 0 Effect: Vita restoration How to Obtain: Various snakes Comments: None Shop prices: NPC Sells: 0 NPC Buys: 0 Snake tongue Vita : 0 Mana : 0 Level: 0 Path: Peasant Max. Held in 1 Slot: 5 Uses: 1 Crafts: None Other Uses: None Merchant suggested price: Minimum: 0 Maximum: 0 Effect: None How to Obtain: Woodlands Snake Cave Comments: None Shop prices: NPC Sells: 0 NPC Buys: 0 Splendid silk Vita : 0 Mana : 0 Level: 0 Path: Peasant Max. Held in 1 Slot: 1 Uses: 1 Crafts: None Other Uses: None Merchant suggested price: Minimum: 0 Maximum: 0 Effect: None How to Obtain: Woodlands Rabbit Cave Comments: None Shop prices: NPC Sells: 0 NPC Buys: 0 Spring water Vita : 0 Mana : 0 Level: 0 Path: Peasant Max. Held in 1 Slot: 1 Uses: 1 Crafts: None Other Uses: None Merchant suggested price: Minimum: 0 Maximum: 0 Effect: None How to Obtain: Woodlands Raheem Desert Cave Comments: None Shop prices: NPC Sells: 0 NPC Buys: 0 Sunken silk Vita : 0 Mana : 0 Level: 0 Path: Peasant Max. Held in 1 Slot: 1 Uses: 1 Crafts: None Other Uses: None Merchant suggested price: Minimum: 0 Maximum: 0 Effect: None How to Obtain: Woodlands Raheem Desert Cave Comments: None Shop prices: NPC Sells: 0 NPC Buys: 0 Tako ink Vita : 0 Mana : 0 Level: 0 Path: Peasant Max. Held in 1 Slot: 10 Uses: 1 Crafts: None Other Uses: None Merchant suggested price: Minimum: 0 Maximum: 0 Effect: None How to Obtain: Woodlands Snake Cave Comments: None Shop prices: NPC Sells: 0 NPC Buys: 0 Tattered leather Vita : 0 Mana : 0 Level: 0 Path: Peasant Max. Held in 1 Slot: 20 Uses: 1 Crafts: None Other Uses: None Merchant suggested price: Minimum: 0 Maximum: 0 Effect: None How to Obtain: Woodlands Snake Cave Comments: None Shop prices: NPC Sells: 0 NPC Buys: 0 Tiger meat Vita : 100 Mana : 0 Level: 0 Path: Peasant Max. Held in 1 Slot: 10 Uses: 1 Crafts: Food preparation Other Uses: Subpath quest item Merchant suggested price: Minimum: 0 Maximum: 0 Effect: Vita restoration How to Obtain: Dropped by Iron lab tigers Comments: None Shop prices: NPC Sells: 100 NPC Buys: 50 Tiger's heart Vita : 1000 Mana : 0 Level: 0 Path: Peasant Max. Held in 1 Slot: 20 Uses: 1 Crafts: None Other Uses: None Merchant suggested price: Minimum: 0 Maximum: 0 Effect: Vita restoration How to Obtain: Shops, monsters, poet Call of the Wild spell Comments: None Shop prices: NPC Sells: 60 NPC Buys: 30 Tormented tome Vita : 0 Mana : 0 Level: 0 Path: Peasant Max. Held in 1 Slot: 1 Uses: 1 Crafts: None Other Uses: None Merchant suggested price: Minimum: 0 Maximum: 0 Effect: None How to Obtain: Woodlands Raheem Desert Cave Comments: None Shop prices: NPC Sells: 0 NPC Buys: 0 Torn paw Vita : 0 Mana : 0 Level: 0 Path: Peasant Max. Held in 1 Slot: 2 Uses: 1 Crafts: None Other Uses: None Merchant suggested price: Minimum: 0 Maximum: 0 Effect: None How to Obtain: Woodlands Dog Cave Comments: None Shop prices: NPC Sells: 0 NPC Buys: 0 Unleashed anger Vita : 0 Mana : 0 Level: 0 Path: Peasant Max. Held in 1 Slot: 1 Uses: 1 Crafts: None Other Uses: None Merchant suggested price: Minimum: 0 Maximum: 0 Effect: None How to Obtain: Woodlands Bear Cave Comments: None Shop prices: NPC Sells: 0 NPC Buys: 0 Venom sac Vita : 0 Mana : 0 Level: 0 Path: Peasant Max. Held in 1 Slot: 5 Uses: 1 Crafts: None Other Uses: None Merchant suggested price: Minimum: 0 Maximum: 0 Effect: None How to Obtain: Woodlands Snake Cave Comments: None Shop prices: NPC Sells: 0 NPC Buys: 0 Vile vial Vita : 0 Mana : 0 Level: 0 Path: Peasant Max. Held in 1 Slot: 1 Uses: 1 Crafts: None Other Uses: None Merchant suggested price: Minimum: 0 Maximum: 0 Effect: None How to Obtain: Woodlands Lobster Cave Comments: None Shop prices: NPC Sells: 0 NPC Buys: 0 Wagging tail Vita : 0 Mana : 0 Level: 0 Path: Peasant Max. Held in 1 Slot: 3 Uses: 1 Crafts: None Other Uses: None Merchant suggested price: Minimum: 0 Maximum: 0 Effect: None How to Obtain: Woodlands Dog Cave Comments: None Shop prices: NPC Sells: 0 NPC Buys: 0 White amber Vita : 0 Mana : 0 Level: 0 Path: Peasant Max. Held in 1 Slot: 20 Uses: 1 Crafts: Gemcutting Other Uses: Crafts Merchant suggested price: Minimum: 0 Maximum: 0 Effect: None How to Obtain: Dropped by many creatures Comments: None Shop prices: NPC Sells: 0 NPC Buys: 0 Wicked wool Vita : 0 Mana : 0 Level: 0 Path: Peasant Max. Held in 1 Slot: 1 Uses: 1 Crafts: None Other Uses: None Merchant suggested price: Minimum: 0 Maximum: 0 Effect: None How to Obtain: Woodlands Raheem Desert Cave Comments: None Shop prices: NPC Sells: 0 NPC Buys: 0 Wolf meat Vita : 48 Mana : 0 Level: 0 Path: Peasant Max. Held in 1 Slot: 1 Uses: 1 Crafts: None Other Uses: Needed for chung ryong helm(et) Merchant suggested price: Minimum: 0 Maximum: 0 Effect: Vita restoration How to Obtain: Dropped by various wolves Comments: None Shop prices: NPC Sells: 4 NPC Buys: 2 Yellow amber Vita : 0 Mana : 0 Level: 0 Path: Peasant Max. Held in 1 Slot: 20 Uses: 1 Crafts: Gemcutting Other Uses: Crafts Merchant suggested price: Minimum: 0 Maximum: 0 Effect: None How to Obtain: Dropped by many creatures Comments: None Shop prices: NPC Sells: 0 NPC Buys: 0 Young ginseng Vita : 40 Mana : 0 Level: 0 Path: Peasant Max. Held in 1 Slot: 1 Uses: 1 Crafts: None Other Uses: None Merchant suggested price: Minimum: 0 Maximum: 0 Effect: Vita restoration How to Obtain: Chu rua Comments: None Shop prices: NPC Sells: 0 NPC Buys: 0",
      "category": "item",
      "path": [
        "Peasant"
      ],
      "level_tier": "",
      "stats": {
        "Vita": 8,
        "Mana": 0
      },
      "stack_size": 201,
      "other_uses": [
        "Spells"
      ],
      "effect": "Needed for spells",
      "obtain": [
        "Squirrel and Green squirrels"
      ],
      "npc_buys": 10
    },
    {
      "id": "items_events_events_items_found_or_used_during_events_bombs_crafts_drops_events_keys_mana_potions_quests_rocks_scrolls_shops_spells_vita_woodlands_items_extinct_other_prices_have_been_supplied_by_the_merchants_and_are_suggested_only_and_not_to_be_used_as_the_final_authority_on_value_of_the_item_for_the_most_current_prices_consult_the_merchant_subpath_ancient_coin_vita_0_mana_0_level_0_path_peasant_max_held_in_1_slot_1_uses_1_crafts_none_other_uses_none_merchant_suggested_price_minimum_0_maximum_0_effect_cash_how_to_obtain_lost_mines_comments_none_shop_prices_npc_sells_0_npc_buys_0_banana_vita_0_mana_0_level_0_path_peasant_max_held_in_1_slot_1_uses_1_crafts_none_other_uses_none_merchant_suggested_price_minimum_0_maximum_0_effect_vita_restoration_how_to_obtain_early_pirate_events_comments_none_shop_prices_npc_sells_0_npc_buys_0_copper_acorn_vita_8_mana_0_level_0_path_peasant_max_held_in_1_slot_1_uses_1_crafts_none_other_uses_none_merchant_suggested_price_minimum_0_maximum_0_effect_vita_restoration_how_to_obtain_lost_mines_comments_none_shop_prices_npc_sells_0_npc_buys_0_lag_flute_vita_0_mana_0_level_0_path_peasant_max_held_in_1_slot_5_uses_1_crafts_none_other_uses_none_merchant_suggested_price_minimum_0_maximum_0_effect_makes_a_player_use_the_sleep_emotion_casts_naptime_on_others_how_to_obtain_dropped_during_april_fools_by_creatures_called_lag_minion_and_deecee_comments_none_shop_prices_npc_sells_0_npc_buys_0_lag_rage_vita_0_mana_0_level_0_path_peasant_max_held_in_1_slot_5_uses_1_crafts_none_other_uses_none_merchant_suggested_price_minimum_0_maximum_0_effect_casts_kwi_sin_whirlwind_leaving_you_at_10_vita_how_to_obtain_dropped_during_april_fools_by_creatures_called_lag_minion_and_deecee_comments_none_shop_prices_npc_sells_0_npc_buys_0_leech_juice_vita_0_mana_0_level_0_path_peasant_max_held_in_1_slot_4_uses_1_crafts_none_other_uses_gives_up_to_33_vita_restoration_when_used_merchant_suggested_price_minimum_0_maximum_0_effect_vita_restoration_33_how_to_obtain_lost_mines_comments_dropped_by_leeches_in_lost_mine_events_shop_prices_npc_sells_0_npc_buys_0_onyx_shard_vita_50_mana_1000_level_0_path_peasant_max_held_in_1_slot_1_uses_5_crafts_none_other_uses_none_merchant_suggested_price_minimum_0_maximum_0_effect_mana_restoration_how_to_obtain_the_shattering_event_comments_none_shop_prices_npc_sells_0_npc_buys_0_watermelon_vita_800_mana_0_level_0_path_peasant_max_held_in_1_slot_1_uses_1_crafts_none_other_uses_none_merchant_suggested_price_minimum_0_maximum_0_effect_vita_restoration_how_to_obtain_halloween_events_comments_none_shop_prices_npc_sells_0_npc_buys_0",
      "name": "Items | Events Events Items found or used during Events Bombs / Crafts / Drops / Events / Keys / Mana / Potions / Quests Rocks / Scrolls / Shops / Spells / Vita / Woodlands Items / Extinct / Other Prices have been supplied by the Merchants and are suggested only and not to be used as the final authority on value of the item. For the most current prices consult the Merchant Subpath. Ancient coin Vita : 0 Mana : 0 Level: 0 Path: Peasant Max. Held in 1 Slot: 1 Uses: 1 Crafts: None Other Uses: None Merchant suggested price: Minimum: 0 Maximum: 0 Effect: Cash How to Obtain: Lost Mines Comments: None Shop prices: NPC Sells: 0 NPC Buys: 0 Banana Vita : 0 Mana : 0 Level: 0 Path: Peasant Max. Held in 1 Slot: 1 Uses: 1 Crafts: None Other Uses: None Merchant suggested price: Minimum: 0 Maximum: 0 Effect: Vita restoration How to Obtain: Early Pirate Events Comments: None Shop prices: NPC Sells: 0 NPC Buys: 0 Copper acorn Vita : 8 Mana : 0 Level: 0 Path: Peasant Max. Held in 1 Slot: 1 Uses: 1 Crafts: None Other Uses: None Merchant suggested price: Minimum: 0 Maximum: 0 Effect: Vita restoration How to Obtain: Lost Mines Comments: None Shop prices: NPC Sells: 0 NPC Buys: 0 Lag flute Vita : 0 Mana : 0 Level: 0 Path: Peasant Max. Held in 1 Slot: 5 Uses: 1 Crafts: None Other Uses: None Merchant suggested price: Minimum: 0 Maximum: 0 Effect: makes a player use the sleep Emotion, Casts Naptime on others. How to Obtain: Dropped during April Fools' by creatures called Lag minion and DeeCee Comments: None Shop prices: NPC Sells: 0 NPC Buys: 0 Lag rage Vita : 0 Mana : 0 Level: 0 Path: Peasant Max. Held in 1 Slot: 5 Uses: 1 Crafts: None Other Uses: None Merchant suggested price: Minimum: 0 Maximum: 0 Effect: Casts Kwi-Sin Whirlwind, leaving you at 10 vita How to Obtain: Dropped during April Fools' by creatures called Lag minion and DeeCee Comments: None Shop prices: NPC Sells: 0 NPC Buys: 0 Leech juice Vita : 0 Mana : 0 Level: 0 Path: Peasant Max. Held in 1 Slot: 4 Uses: 1 Crafts: None Other Uses: Gives up to 33% vita restoration when used Merchant suggested price: Minimum: 0 Maximum: 0 Effect: Vita restoration - 33% How to Obtain: Lost Mines Comments: Dropped by Leeches in Lost Mine events Shop prices: NPC Sells: 0 NPC Buys: 0 Onyx shard Vita : -50 Mana : 1000 Level: 0 Path: Peasant Max. Held in 1 Slot: 1 Uses: 5 Crafts: None Other Uses: None Merchant suggested price: Minimum: 0 Maximum: 0 Effect: Mana restoration How to Obtain: The Shattering Event Comments: None Shop prices: NPC Sells: 0 NPC Buys: 0 Watermelon Vita : 800 Mana : 0 Level: 0 Path: Peasant Max. Held in 1 Slot: 1 Uses: 1 Crafts: None Other Uses: None Merchant suggested price: Minimum: 0 Maximum: 0 Effect: Vita restoration How to Obtain: Halloween events Comments: None Shop prices: NPC Sells: 0 NPC Buys: 0",
      "category": "item",
      "path": [
        "Peasant"
      ],
      "level_tier": "",
      "stats": {
        "Vita": 0,
        "Mana": 0
      },
      "stack_size": 1,
      "effect": "Cash",
      "obtain": [
        "Lost Mines"
      ],
      "npc_buys": 0
    },
    {
      "id": "items_keys_keys_keys_of_all_types_bombs_crafts_drops_events_keys_mana_potions_quests_rocks_scrolls_shops_spells_vita_woodlands_items_extinct_other_prices_have_been_supplied_by_the_merchants_and_are_suggested_only_and_not_to_be_used_as_the_final_authority_on_value_of_the_item_for_the_most_current_prices_consult_the_merchant_subpath_baekho_key_vita_0_mana_0_level_0_path_peasant_max_held_in_1_slot_1_uses_1_crafts_none_other_uses_change_totem_at_shrinesjoin_npc_subpath_at_kugnae_scroll_shop_merchant_suggested_price_minimum_0_maximum_0_effect_none_how_to_obtain_mythic_tiger_key_bosses_comments_needed_for_lesser_alliance_with_mythic_monkey_shop_prices_npc_sells_0_npc_buys_0_buya_key_vita_0_mana_0_level_0_path_peasant_max_held_in_1_slot_1_uses_1_crafts_none_other_uses_none_merchant_suggested_price_minimum_0_maximum_0_effect_key_held_by_buya_goverment_used_to_secure_palace_doors_how_to_obtain_none_comments_used_by_buya_royals_shop_prices_npc_sells_0_npc_buys_0_carnage_key_vita_0_mana_0_level_0_path_peasant_max_held_in_1_slot_1_uses_1_crafts_none_other_uses_none_merchant_suggested_price_minimum_0_maximum_0_effect_open_close_doors_of_carnage_games_how_to_obtain_none_comments_key_held_by_carnage_hosts_shop_prices_npc_sells_0_npc_buys_0_chung_ryong_key_vita_0_mana_0_level_0_path_peasant_max_held_in_1_slot_1_uses_1_crafts_none_other_uses_change_totem_at_shrinesjoin_npc_subpath_at_kugnae_scroll_shop_merchant_suggested_price_minimum_0_maximum_0_effect_none_how_to_obtain_mythic_dragon_key_bosses_comments_needed_for_lesser_alliance_with_mythic_dog_shop_prices_npc_sells_0_npc_buys_0_clan_key_vita_0_mana_0_level_0_path_peasant_max_held_in_1_slot_1_uses_1_crafts_none_other_uses_none_merchant_suggested_price_minimum_0_maximum_0_effect_open_close_clan_hall_doors_how_to_obtain_none_comments_key_held_by_clan_primogen_and_council_shop_prices_npc_sells_0_npc_buys_0_fox_hunt_key_vita_0_mana_0_level_0_path_peasant_max_held_in_1_slot_1_uses_1_crafts_none_other_uses_none_merchant_suggested_price_minimum_0_maximum_0_effect_open_close_doors_of_fox_hunt_games_how_to_obtain_none_comments_key_held_by_fox_hunt_hosts_shop_prices_npc_sells_0_npc_buys_0_hyun_moo_key_vita_0_mana_0_level_0_path_peasant_max_held_in_1_slot_1_uses_1_crafts_none_other_uses_change_totem_at_shrinesjoin_npc_subpath_at_kugnae_scroll_shop_merchant_suggested_price_minimum_0_maximum_0_effect_none_how_to_obtain_mythic_snake_key_bosses_comments_needed_for_lesser_alliance_with_mythic_pig_shop_prices_npc_sells_0_npc_buys_0_iron_key_vita_0_mana_0_level_0_path_peasant_max_held_in_1_slot_1_uses_1_crafts_none_other_uses_none_merchant_suggested_price_minimum_0_maximum_0_effect_opens_treasure_boxes_in_iron_labs_how_to_obtain_dropped_by_giant_iron_tiger_comments_none_shop_prices_npc_sells_0_npc_buys_0_ju_jak_key_vita_0_mana_0_level_0_path_peasant_max_held_in_1_slot_1_uses_1_crafts_none_other_uses_change_totem_at_shrinesjoin_npc_subpath_at_kugnae_scroll_shop_merchant_suggested_price_minimum_0_maximum_0_effect_none_how_to_obtain_mythic_sheep_key_bosses_comments_needed_for_lesser_alliance_with_mythic_ox_shop_prices_npc_sells_0_npc_buys_0_key_to_earth_vita_0_mana_0_level_0_path_peasant_max_held_in_1_slot_1_uses_1_crafts_none_other_uses_none_merchant_suggested_price_minimum_0_maximum_0_effect_none_how_to_obtain_mythic_rabbit_key_bosses_comments_needed_for_lesser_alliance_with_mythic_rooster_shop_prices_npc_sells_0_npc_buys_0_key_to_fire_vita_0_mana_0_level_0_path_peasant_max_held_in_1_slot_1_uses_1_crafts_none_other_uses_none_merchant_suggested_price_minimum_0_maximum_0_effect_none_how_to_obtain_mythic_monkey_key_bosses_comments_needed_for_lesser_alliance_with_mythic_tiger_shop_prices_npc_sells_0_npc_buys_0_key_to_heaven_vita_0_mana_0_level_0_path_peasant_max_held_in_1_slot_1_uses_1_crafts_none_other_uses_none_merchant_suggested_price_minimum_0_maximum_0_effect_none_how_to_obtain_mythic_rooster_key_bosses_comments_needed_for_lesser_alliance_with_mythic_rabbit_shop_prices_npc_sells_0_npc_buys_0_key_to_mountain_vita_0_mana_0_level_0_path_peasant_max_held_in_1_slot_1_uses_1_crafts_none_other_uses_none_merchant_suggested_price_minimum_0_maximum_0_effect_none_how_to_obtain_mythic_pig_key_bosses_comments_needed_for_lesser_alliance_with_mythic_sheep_shop_prices_npc_sells_0_npc_buys_0_key_to_pond_vita_0_mana_0_level_0_path_peasant_max_held_in_1_slot_1_uses_1_crafts_none_other_uses_none_merchant_suggested_price_minimum_0_maximum_0_effect_none_how_to_obtain_mythic_rat_key_bosses_comments_needed_for_lesser_alliance_with_mythic_horse_shop_prices_npc_sells_0_npc_buys_0_key_to_thunder_vita_0_mana_0_level_0_path_peasant_max_held_in_1_slot_1_uses_1_crafts_none_other_uses_none_merchant_suggested_price_minimum_0_maximum_0_effect_none_how_to_obtain_mythic_horse_key_bosses_comments_needed_for_lesser_alliance_with_mythic_rat_shop_prices_npc_sells_0_npc_buys_0_key_to_water_vita_0_mana_0_level_0_path_peasant_max_held_in_1_slot_1_uses_1_crafts_none_other_uses_none_merchant_suggested_price_minimum_0_maximum_0_effect_none_how_to_obtain_mythic_ox_key_bosses_comments_needed_for_lesser_alliance_with_mythic_sheep_shop_prices_npc_sells_0_npc_buys_0_key_to_wind_vita_0_mana_0_level_0_path_peasant_max_held_in_1_slot_1_uses_1_crafts_none_other_uses_none_merchant_suggested_price_minimum_0_maximum_0_effect_none_how_to_obtain_mythic_dog_key_bosses_comments_needed_for_lesser_alliance_with_mythic_sheep_shop_prices_npc_sells_0_npc_buys_0_kugnae_key_vita_0_mana_0_level_0_path_peasant_max_held_in_1_slot_1_uses_1_crafts_none_other_uses_none_merchant_suggested_price_minimum_0_maximum_0_effect_key_held_by_koguryo_goverment_used_to_secure_palace_doors_how_to_obtain_none_comments_used_by_koguryo_royals_shop_prices_npc_sells_0_npc_buys_0_nagnang_key_vita_0_mana_0_level_0_path_peasant_max_held_in_1_slot_1_uses_1_crafts_none_other_uses_none_merchant_suggested_price_minimum_0_maximum_0_effect_key_held_by_nangen_goverment_used_to_secure_palace_doors_how_to_obtain_none_comments_used_by_nangen_royals_shop_prices_npc_sells_0_npc_buys_0_skeleton_key_vita_0_mana_0_level_0_path_peasant_max_held_in_1_slot_1_uses_1_crafts_none_other_uses_none_merchant_suggested_price_minimum_0_maximum_0_effect_key_used_to_open_various_locks_how_to_obtain_spy_subpath_comments_those_who_helped_rescue_elders_from_spy_dungeon_in_yuri_58_shop_prices_npc_sells_0_npc_buys_0_sute_key_vita_0_mana_0_level_0_path_peasant_max_held_in_1_slot_1_uses_1_crafts_none_other_uses_none_merchant_suggested_price_minimum_0_maximum_0_effect_none_how_to_obtain_sute_comments_none_shop_prices_npc_sells_0_npc_buys_0",
      "name": "Items | Keys Keys Keys of all types. Bombs / Crafts / Drops / Events / Keys / Mana / Potions / Quests Rocks / Scrolls / Shops / Spells / Vita / Woodlands Items / Extinct / Other Prices have been supplied by the Merchants and are suggested only and not to be used as the final authority on value of the item. For the most current prices consult the Merchant Subpath. Baekho key Vita : 0 Mana : 0 Level: 0 Path: Peasant Max. Held in 1 Slot: 1 Uses: 1 Crafts: None Other Uses: Change totem at shrinesJoin NPC subpath at Kugnae Scroll shop Merchant suggested price: Minimum: 0 Maximum: 0 Effect: None How to Obtain: Mythic Tiger Key Bosses Comments: Needed for Lesser Alliance with Mythic Monkey Shop prices: NPC Sells: 0 NPC Buys: 0 Buya key Vita : 0 Mana : 0 Level: 0 Path: Peasant Max. Held in 1 Slot: 1 Uses: 1 Crafts: None Other Uses: None Merchant suggested price: Minimum: 0 Maximum: 0 Effect: Key held by Buya goverment, used to secure palace doors How to Obtain: None Comments: Used by Buya royals Shop prices: NPC Sells: 0 NPC Buys: 0 Carnage key Vita : 0 Mana : 0 Level: 0 Path: Peasant Max. Held in 1 Slot: 1 Uses: 1 Crafts: None Other Uses: None Merchant suggested price: Minimum: 0 Maximum: 0 Effect: Open/close doors of carnage games How to Obtain: None Comments: Key held by Carnage hosts Shop prices: NPC Sells: 0 NPC Buys: 0 Chung ryong key Vita : 0 Mana : 0 Level: 0 Path: Peasant Max. Held in 1 Slot: 1 Uses: 1 Crafts: None Other Uses: Change totem at shrinesJoin NPC subpath at Kugnae Scroll shop Merchant suggested price: Minimum: 0 Maximum: 0 Effect: None How to Obtain: Mythic Dragon Key Bosses Comments: Needed for Lesser Alliance with Mythic Dog Shop prices: NPC Sells: 0 NPC Buys: 0 Clan key Vita : 0 Mana : 0 Level: 0 Path: Peasant Max. Held in 1 Slot: 1 Uses: 1 Crafts: None Other Uses: None Merchant suggested price: Minimum: 0 Maximum: 0 Effect: Open/close clan hall doors How to Obtain: None Comments: Key held by Clan Primogen and council Shop prices: NPC Sells: 0 NPC Buys: 0 Fox hunt key Vita : 0 Mana : 0 Level: 0 Path: Peasant Max. Held in 1 Slot: 1 Uses: 1 Crafts: None Other Uses: None Merchant suggested price: Minimum: 0 Maximum: 0 Effect: Open/close doors of fox hunt games How to Obtain: None Comments: Key held by Fox hunt hosts Shop prices: NPC Sells: 0 NPC Buys: 0 Hyun moo key Vita : 0 Mana : 0 Level: 0 Path: Peasant Max. Held in 1 Slot: 1 Uses: 1 Crafts: None Other Uses: Change totem at shrinesJoin NPC subpath at Kugnae Scroll shop Merchant suggested price: Minimum: 0 Maximum: 0 Effect: None How to Obtain: Mythic Snake Key Bosses Comments: Needed for Lesser Alliance with Mythic Pig Shop prices: NPC Sells: 0 NPC Buys: 0 Iron key Vita : 0 Mana : 0 Level: 0 Path: Peasant Max. Held in 1 Slot: 1 Uses: 1 Crafts: None Other Uses: None Merchant suggested price: Minimum: 0 Maximum: 0 Effect: Opens treasure boxes in Iron Labs How to Obtain: Dropped by Giant Iron Tiger Comments: None Shop prices: NPC Sells: 0 NPC Buys: 0 Ju jak key Vita : 0 Mana : 0 Level: 0 Path: Peasant Max. Held in 1 Slot: 1 Uses: 1 Crafts: None Other Uses: Change totem at shrinesJoin NPC subpath at Kugnae Scroll shop Merchant suggested price: Minimum: 0 Maximum: 0 Effect: None How to Obtain: Mythic Sheep Key Bosses Comments: Needed for Lesser Alliance with Mythic Ox Shop prices: NPC Sells: 0 NPC Buys: 0 Key to earth Vita : 0 Mana : 0 Level: 0 Path: Peasant Max. Held in 1 Slot: 1 Uses: 1 Crafts: None Other Uses: None Merchant suggested price: Minimum: 0 Maximum: 0 Effect: None How to Obtain: Mythic Rabbit Key Bosses Comments: Needed for Lesser Alliance with Mythic Rooster Shop prices: NPC Sells: 0 NPC Buys: 0 Key to fire Vita : 0 Mana : 0 Level: 0 Path: Peasant Max. Held in 1 Slot: 1 Uses: 1 Crafts: None Other Uses: None Merchant suggested price: Minimum: 0 Maximum: 0 Effect: None How to Obtain: Mythic Monkey Key Bosses Comments: Needed for Lesser Alliance with Mythic Tiger Shop prices: NPC Sells: 0 NPC Buys: 0 Key to heaven Vita : 0 Mana : 0 Level: 0 Path: Peasant Max. Held in 1 Slot: 1 Uses: 1 Crafts: None Other Uses: None Merchant suggested price: Minimum: 0 Maximum: 0 Effect: None How to Obtain: Mythic Rooster Key Bosses Comments: Needed for Lesser Alliance with Mythic Rabbit Shop prices: NPC Sells: 0 NPC Buys: 0 Key to mountain Vita : 0 Mana : 0 Level: 0 Path: Peasant Max. Held in 1 Slot: 1 Uses: 1 Crafts: None Other Uses: None Merchant suggested price: Minimum: 0 Maximum: 0 Effect: None How to Obtain: Mythic Pig Key Bosses Comments: Needed for Lesser Alliance with Mythic Sheep Shop prices: NPC Sells: 0 NPC Buys: 0 Key to pond Vita : 0 Mana : 0 Level: 0 Path: Peasant Max. Held in 1 Slot: 1 Uses: 1 Crafts: None Other Uses: None Merchant suggested price: Minimum: 0 Maximum: 0 Effect: None How to Obtain: Mythic Rat Key Bosses Comments: Needed for Lesser Alliance with Mythic Horse Shop prices: NPC Sells: 0 NPC Buys: 0 Key to thunder Vita : 0 Mana : 0 Level: 0 Path: Peasant Max. Held in 1 Slot: 1 Uses: 1 Crafts: None Other Uses: None Merchant suggested price: Minimum: 0 Maximum: 0 Effect: None How to Obtain: Mythic Horse Key Bosses Comments: Needed for Lesser Alliance with Mythic Rat Shop prices: NPC Sells: 0 NPC Buys: 0 Key to water Vita : 0 Mana : 0 Level: 0 Path: Peasant Max. Held in 1 Slot: 1 Uses: 1 Crafts: None Other Uses: None Merchant suggested price: Minimum: 0 Maximum: 0 Effect: None How to Obtain: Mythic Ox Key Bosses Comments: Needed for Lesser Alliance with Mythic Sheep Shop prices: NPC Sells: 0 NPC Buys: 0 Key to wind Vita : 0 Mana : 0 Level: 0 Path: Peasant Max. Held in 1 Slot: 1 Uses: 1 Crafts: None Other Uses: None Merchant suggested price: Minimum: 0 Maximum: 0 Effect: None How to Obtain: Mythic Dog Key Bosses Comments: Needed for Lesser Alliance with Mythic Sheep Shop prices: NPC Sells: 0 NPC Buys: 0 Kugnae key Vita : 0 Mana : 0 Level: 0 Path: Peasant Max. Held in 1 Slot: 1 Uses: 1 Crafts: None Other Uses: None Merchant suggested price: Minimum: 0 Maximum: 0 Effect: Key held by Koguryo goverment, used to secure palace doors How to Obtain: None Comments: Used by Koguryo royals Shop prices: NPC Sells: 0 NPC Buys: 0 Nagnang key Vita : 0 Mana : 0 Level: 0 Path: Peasant Max. Held in 1 Slot: 1 Uses: 1 Crafts: None Other Uses: None Merchant suggested price: Minimum: 0 Maximum: 0 Effect: Key held by Nangen goverment, used to secure palace doors How to Obtain: None Comments: Used by Nangen royals Shop prices: NPC Sells: 0 NPC Buys: 0 Skeleton key Vita : 0 Mana : 0 Level: 0 Path: Peasant Max. Held in 1 Slot: 1 Uses: 1 Crafts: None Other Uses: None Merchant suggested price: Minimum: 0 Maximum: 0 Effect: Key used to open various locks How to Obtain: Spy subpath Comments: Those who helped rescue elders from Spy Dungeon in Yuri 58 Shop prices: NPC Sells: 0 NPC Buys: 0 Sute key Vita : 0 Mana : 0 Level: 0 Path: Peasant Max. Held in 1 Slot: 1 Uses: 1 Crafts: None Other Uses: None Merchant suggested price: Minimum: 0 Maximum: 0 Effect: None How to Obtain: Sute Comments: None Shop prices: NPC Sells: 0 NPC Buys: 0",
      "category": "item",
      "path": [
        "Peasant"
      ],
      "level_tier": "",
      "stats": {
        "Vita": 0,
        "Mana": 0
      },
      "stack_size": 1,
      "other_uses": [
        "Change totem at shrinesJoin NPC subpath at Kugnae Scroll shop"
      ],
      "obtain": [
        "Mythic Tiger Key Bosses"
      ],
      "comments": "Needed for Lesser Alliance with Mythic Monkey",
      "npc_buys": 0
    },
    {
      "id": "items_mana_restoration_mana_restoration_various_items_you_can_use_to_restore_your_mana_bombs_crafts_drops_events_keys_mana_potions_quests_rocks_scrolls_shops_spells_vita_woodlands_items_extinct_other_prices_have_been_supplied_by_the_merchants_and_are_suggested_only_and_not_to_be_used_as_the_final_authority_on_value_of_the_item_for_the_most_current_prices_consult_the_merchant_subpath_aged_wine_vita_5_mana_100_level_0_path_peasant_max_held_in_1_slot_1_uses_50_crafts_alchemy_other_uses_crafts_merchant_suggested_price_minimum_0_maximum_0_effect_restores_100_mana_takes_5_vita_how_to_obtain_potion_shops_comments_none_shop_prices_npc_sells_150_npc_buys_75_herb_pipe_vita_15_mana_300_level_0_path_peasant_max_held_in_1_slot_1_uses_100_crafts_none_other_uses_none_merchant_suggested_price_minimum_0_maximum_0_effect_mana_restoration_how_to_obtain_arena_and_alchemist_shops_guild_halls_comments_none_shop_prices_npc_sells_400_npc_buys_200_iron_statue_vita_0_mana_250_level_0_path_peasant_max_held_in_1_slot_1_uses_40_crafts_none_other_uses_none_merchant_suggested_price_minimum_0_maximum_0_effect_mana_restoration_how_to_obtain_dropped_by_gim_yi_in_iron_labrynth_comments_none_shop_prices_npc_sells_0_npc_buys_0_memory_blossom_vita_0_mana_30_level_0_path_peasant_max_held_in_1_slot_1_uses_200_crafts_none_other_uses_none_merchant_suggested_price_minimum_0_maximum_0_effect_mana_restoration_how_to_obtain_bohdi_s_sanctum_monk_subpath_area_comments_none_shop_prices_npc_sells_400_npc_buys_200_moon_wine_vita_5_mana_80_level_0_path_peasant_max_held_in_1_slot_1_uses_50_crafts_alchemy_other_uses_crafts_merchant_suggested_price_minimum_0_maximum_0_effect_none_how_to_obtain_potion_shops_comments_none_shop_prices_npc_sells_100_npc_buys_50_ogre_cider_vita_10_mana_100_level_0_path_peasant_max_held_in_1_slot_1_uses_20_crafts_none_other_uses_none_merchant_suggested_price_minimum_0_maximum_0_effect_mana_restoration_how_to_obtain_home_of_ugh_hamgyong_nam_do_comments_none_shop_prices_npc_sells_100_npc_buys_50_ogre_drought_vita_25_mana_325_level_0_path_peasant_max_held_in_1_slot_1_uses_39_crafts_none_other_uses_none_merchant_suggested_price_minimum_0_maximum_0_effect_mana_restoration_how_to_obtain_home_of_ugh_hamgyong_nam_do_comments_none_shop_prices_npc_sells_100_npc_buys_50_onyx_shard_vita_50_mana_1000_level_0_path_peasant_max_held_in_1_slot_1_uses_5_crafts_none_other_uses_none_merchant_suggested_price_minimum_0_maximum_0_effect_mana_restoration_how_to_obtain_the_shattering_event_comments_none_shop_prices_npc_sells_0_npc_buys_0_rice_wine_vita_0_mana_30_level_0_path_peasant_max_held_in_1_slot_1_uses_200_crafts_none_other_uses_mana_restoration_merchant_suggested_price_minimum_0_maximum_0_effect_restores_30_mana_how_to_obtain_taverns_comments_none_shop_prices_npc_sells_10_npc_buys_5_rich_wine_vita_10_mana_350_level_0_path_peasant_max_held_in_1_slot_1_uses_80_crafts_none_other_uses_mana_restoration_merchant_suggested_price_minimum_300_maximum_600_effect_restores_350_mana_and_takes_10_vita_how_to_obtain_bagai_shop_comments_restores_350_mana_shop_prices_npc_sells_600_npc_buys_300_root_liquor_vita_1_mana_30_level_0_path_peasant_max_held_in_1_slot_1_uses_200_crafts_none_other_uses_mana_restoration_merchant_suggested_price_minimum_0_maximum_0_effect_restores_30_mana_and_takes_1_vita_how_to_obtain_taverns_comments_none_shop_prices_npc_sells_10_npc_buys_5_sea_poems_vita_1_mana_500_level_0_path_peasant_max_held_in_1_slot_1_uses_64_crafts_none_other_uses_subpath_spell_item_merchant_suggested_price_minimum_0_maximum_0_effect_mana_restoration_how_to_obtain_random_merchant_comments_none_shop_prices_npc_sells_5_000_npc_buys_0_sonhi_pipe_vita_50_mana_450_level_0_path_peasant_max_held_in_1_slot_1_uses_50_crafts_none_other_uses_none_merchant_suggested_price_minimum_0_maximum_0_effect_mana_restoration_how_to_obtain_kaming_s_encampment_messenger_comments_none_shop_prices_npc_sells_200_npc_buys_100_thick_wine_vita_5_mana_40_level_0_path_peasant_max_held_in_1_slot_1_uses_50_crafts_none_other_uses_mana_restoration_merchant_suggested_price_minimum_0_maximum_0_effect_restores_40_mana_and_5_vita_how_to_obtain_taverns_comments_none_shop_prices_npc_sells_10_npc_buys_5_wine_vita_5_mana_25_level_0_path_peasant_max_held_in_1_slot_1_uses_50_crafts_none_other_uses_mana_restoration_merchant_suggested_price_minimum_0_maximum_0_effect_restores_25_mana_and_5_vita_how_to_obtain_taverns_comments_none_shop_prices_npc_sells_10_npc_buys_5",
      "name": "Items | Mana Restoration Mana Restoration Various items you can use to restore your mana. Bombs / Crafts / Drops / Events / Keys / Mana / Potions / Quests Rocks / Scrolls / Shops / Spells / Vita / Woodlands Items / Extinct / Other Prices have been supplied by the Merchants and are suggested only and not to be used as the final authority on value of the item. For the most current prices consult the Merchant Subpath. Aged wine Vita : -5 Mana : 100 Level: 0 Path: Peasant Max. Held in 1 Slot: 1 Uses: 50 Crafts: Alchemy Other Uses: Crafts Merchant suggested price: Minimum: 0 Maximum: 0 Effect: Restores 100 mana, takes 5 vita How to Obtain: Potion Shops Comments: None Shop prices: NPC Sells: 150 NPC Buys: 75 Herb pipe Vita : -15 Mana : 300 Level: 0 Path: Peasant Max. Held in 1 Slot: 1 Uses: 100 Crafts: None Other Uses: None Merchant suggested price: Minimum: 0 Maximum: 0 Effect: Mana restoration How to Obtain: Arena and Alchemist Shops, Guild Halls Comments: None Shop prices: NPC Sells: 400 NPC Buys: 200 Iron statue Vita : 0 Mana : 250 Level: 0 Path: Peasant Max. Held in 1 Slot: 1 Uses: 40 Crafts: None Other Uses: None Merchant suggested price: Minimum: 0 Maximum: 0 Effect: Mana restoration How to Obtain: Dropped by Gim-yi in Iron Labrynth Comments: None Shop prices: NPC Sells: 0 NPC Buys: 0 Memory blossom Vita : 0 Mana : 30 Level: 0 Path: Peasant Max. Held in 1 Slot: 1 Uses: 200 Crafts: None Other Uses: None Merchant suggested price: Minimum: 0 Maximum: 0 Effect: Mana restoration How to Obtain: Bohdi's Sanctum - Monk subpath area Comments: None Shop prices: NPC Sells: 400 NPC Buys: 200 Moon wine Vita : -5 Mana : 80 Level: 0 Path: Peasant Max. Held in 1 Slot: 1 Uses: 50 Crafts: Alchemy Other Uses: Crafts Merchant suggested price: Minimum: 0 Maximum: 0 Effect: None How to Obtain: Potion Shops Comments: None Shop prices: NPC Sells: 100 NPC Buys: 50 Ogre cider Vita : -10 Mana : 100 Level: 0 Path: Peasant Max. Held in 1 Slot: 1 Uses: 20 Crafts: None Other Uses: None Merchant suggested price: Minimum: 0 Maximum: 0 Effect: Mana restoration How to Obtain: Home of Ugh, Hamgyong nam-do Comments: None Shop prices: NPC Sells: 100 NPC Buys: 50 Ogre drought Vita : -25 Mana : 325 Level: 0 Path: Peasant Max. Held in 1 Slot: 1 Uses: 39 Crafts: None Other Uses: None Merchant suggested price: Minimum: 0 Maximum: 0 Effect: Mana restoration How to Obtain: Home of Ugh, Hamgyong nam-do Comments: None Shop prices: NPC Sells: 100 NPC Buys: 50 Onyx shard Vita : -50 Mana : 1000 Level: 0 Path: Peasant Max. Held in 1 Slot: 1 Uses: 5 Crafts: None Other Uses: None Merchant suggested price: Minimum: 0 Maximum: 0 Effect: Mana restoration How to Obtain: The Shattering Event Comments: None Shop prices: NPC Sells: 0 NPC Buys: 0 Rice wine Vita : 0 Mana : 30 Level: 0 Path: Peasant Max. Held in 1 Slot: 1 Uses: 200 Crafts: None Other Uses: Mana restoration Merchant suggested price: Minimum: 0 Maximum: 0 Effect: Restores 30 mana How to Obtain: Taverns Comments: None Shop prices: NPC Sells: 10 NPC Buys: 5 Rich wine Vita : -10 Mana : 350 Level: 0 Path: Peasant Max. Held in 1 Slot: 1 Uses: 80 Crafts: None Other Uses: Mana restoration Merchant suggested price: Minimum: 300 Maximum: 600 Effect: Restores 350 mana and takes 10 vita How to Obtain: Bagai Shop Comments: Restores 350 mana Shop prices: NPC Sells: 600 NPC Buys: 300 Root liquor Vita : -1 Mana : 30 Level: 0 Path: Peasant Max. Held in 1 Slot: 1 Uses: 200 Crafts: None Other Uses: Mana restoration Merchant suggested price: Minimum: 0 Maximum: 0 Effect: Restores 30 mana and takes 1 vita How to Obtain: Taverns Comments: None Shop prices: NPC Sells: 10 NPC Buys: 5 Sea poems Vita : -1 Mana : 500 Level: 0 Path: Peasant Max. Held in 1 Slot: 1 Uses: 64 Crafts: None Other Uses: Subpath spell item Merchant suggested price: Minimum: 0 Maximum: 0 Effect: Mana restoration How to Obtain: Random Merchant Comments: None Shop prices: NPC Sells: 5,000 NPC Buys: 0 Sonhi pipe Vita : -50 Mana : 450 Level: 0 Path: Peasant Max. Held in 1 Slot: 1 Uses: 50 Crafts: None Other Uses: None Merchant suggested price: Minimum: 0 Maximum: 0 Effect: Mana restoration How to Obtain: KaMing's Encampment Messenger Comments: None Shop prices: NPC Sells: 200 NPC Buys: 100 Thick wine Vita : 5 Mana : 40 Level: 0 Path: Peasant Max. Held in 1 Slot: 1 Uses: 50 Crafts: None Other Uses: Mana restoration Merchant suggested price: Minimum: 0 Maximum: 0 Effect: Restores 40 mana and 5 vita How to Obtain: Taverns Comments: None Shop prices: NPC Sells: 10 NPC Buys: 5 Wine Vita : 5 Mana : 25 Level: 0 Path: Peasant Max. Held in 1 Slot: 1 Uses: 50 Crafts: None Other Uses: Mana restoration Merchant suggested price: Minimum: 0 Maximum: 0 Effect: Restores 25 mana and 5 vita How to Obtain: Taverns Comments: None Shop prices: NPC Sells: 10 NPC Buys: 5",
      "category": "item",
      "path": [
        "Peasant"
      ],
      "level_tier": "",
      "stats": {
        "Vita": -5,
        "Mana": 100
      },
      "stack_size": 1,
      "crafts": [
        "Alchemy"
      ],
      "other_uses": [
        "Crafts"
      ],
      "effect": "Restores 100 mana, takes 5 vita",
      "obtain": [
        "Potion Shops"
      ],
      "npc_buys": 75
    },
    {
      "id": "items_other_other_all_the_items_in_nexus_that_don_t_have_that_special_category_bombs_crafts_drops_events_keys_mana_potions_quests_rocks_scrolls_shops_spells_vita_woodlands_items_extinct_other_prices_have_been_supplied_by_the_merchants_and_are_suggested_only_and_not_to_be_used_as_the_final_authority_on_value_of_the_item_for_the_most_current_prices_consult_the_merchant_subpath_daffodil_vita_0_mana_0_level_0_path_peasant_max_held_in_1_slot_1_uses_1_crafts_none_other_uses_make_bouquets_merchant_suggested_price_minimum_0_maximum_0_effect_none_how_to_obtain_created_by_druids_comments_make_great_decorations_shop_prices_npc_sells_0_npc_buys_0_dawn_tulip_vita_0_mana_0_level_0_path_peasant_max_held_in_1_slot_1_uses_1_crafts_none_other_uses_make_bouquets_merchant_suggested_price_minimum_0_maximum_0_effect_none_how_to_obtain_created_by_druids_comments_make_great_decorations_shop_prices_npc_sells_0_npc_buys_0_divine_chronicles_vita_0_mana_0_level_0_path_peasant_max_held_in_1_slot_1_uses_1_crafts_none_other_uses_none_merchant_suggested_price_minimum_0_maximum_0_effect_read_diviner_s_scroll_how_to_obtain_library_comments_none_shop_prices_npc_sells_1_000_npc_buys_0_dragon_s_tooth_vita_0_mana_0_level_0_path_peasant_max_held_in_1_slot_1_uses_1_crafts_none_other_uses_none_merchant_suggested_price_minimum_0_maximum_0_effect_allows_the_character_to_morph_into_a_serpentine_dragon_how_to_obtain_go_to_the_final_room_of_nexus_museum_and_talk_to_the_caretaker_click_caretaker_s_gift_to_obtain_one_comments_the_color_of_the_morphed_dragon_depends_on_the_dye_the_character_is_using_on_his_armor_shop_prices_npc_sells_0_npc_buys_0_gold_bar_vita_0_mana_0_level_0_path_peasant_max_held_in_1_slot_1_uses_1_crafts_none_other_uses_none_merchant_suggested_price_minimum_0_maximum_0_effect_1000_coins_in_1_stack_how_to_obtain_none_comments_none_shop_prices_npc_sells_0_npc_buys_0_golden_sunset_vita_0_mana_0_level_0_path_peasant_max_held_in_1_slot_1_uses_1_crafts_none_other_uses_make_bouquets_merchant_suggested_price_minimum_0_maximum_0_effect_none_how_to_obtain_created_by_druids_comments_make_great_decorations_shop_prices_npc_sells_0_npc_buys_0_graced_by_the_muse_vita_0_mana_0_level_0_path_peasant_max_held_in_1_slot_1_uses_1_crafts_none_other_uses_none_merchant_suggested_price_minimum_0_maximum_0_effect_read_muse_s_scroll_how_to_obtain_library_comments_none_shop_prices_npc_sells_1_000_npc_buys_0_greater_tulip_vita_0_mana_0_level_0_path_peasant_max_held_in_1_slot_1_uses_1_crafts_none_other_uses_make_bouquets_merchant_suggested_price_minimum_0_maximum_0_effect_none_how_to_obtain_created_by_druids_comments_make_great_decorations_shop_prices_npc_sells_0_npc_buys_0_heaven_s_bell_vita_0_mana_0_level_0_path_peasant_max_held_in_1_slot_1_uses_1_crafts_none_other_uses_make_bouquets_merchant_suggested_price_minimum_0_maximum_0_effect_none_how_to_obtain_created_by_druids_comments_make_great_decorations_shop_prices_npc_sells_0_npc_buys_0_legend_vita_0_mana_0_level_0_path_peasant_max_held_in_1_slot_1_uses_1_crafts_none_other_uses_none_merchant_suggested_price_minimum_0_maximum_0_effect_tales_of_history_and_legendsprovides_clues_to_many_quests_how_to_obtain_library_comments_none_shop_prices_npc_sells_1_000_npc_buys_0_midnight_s_reign_vita_0_mana_0_level_0_path_peasant_max_held_in_1_slot_1_uses_1_crafts_none_other_uses_make_bouquets_merchant_suggested_price_minimum_0_maximum_0_effect_none_how_to_obtain_created_by_druids_comments_make_great_decorations_shop_prices_npc_sells_0_npc_buys_0_old_poppy_vita_0_mana_0_level_0_path_peasant_max_held_in_1_slot_1_uses_1_crafts_none_other_uses_make_bouquets_merchant_suggested_price_minimum_0_maximum_0_effect_none_how_to_obtain_created_by_druids_comments_make_great_decorations_shop_prices_npc_sells_0_npc_buys_0_penny_vita_0_mana_0_level_0_path_peasant_max_held_in_1_slot_1_uses_1_crafts_none_other_uses_none_merchant_suggested_price_minimum_0_maximum_0_effect_1_coin_how_to_obtain_none_comments_none_shop_prices_npc_sells_0_npc_buys_0_pennyroll_vita_0_mana_0_level_0_path_peasant_max_held_in_1_slot_1_uses_1_crafts_none_other_uses_none_merchant_suggested_price_minimum_0_maximum_0_effect_2_to_99_coins_how_to_obtain_none_comments_none_shop_prices_npc_sells_0_npc_buys_0_ranger_code_vita_0_mana_0_level_0_path_peasant_max_held_in_1_slot_1_uses_1_crafts_none_other_uses_none_merchant_suggested_price_minimum_0_maximum_0_effect_read_ranger_s_scroll_how_to_obtain_library_comments_none_shop_prices_npc_sells_1_000_npc_buys_0_rose_vita_0_mana_0_level_0_path_peasant_max_held_in_1_slot_1_uses_1_crafts_none_other_uses_make_bouquets_merchant_suggested_price_minimum_0_maximum_0_effect_none_how_to_obtain_walk_past_a_rose_bush_comments_make_great_decorations_shop_prices_npc_sells_0_npc_buys_0_silver_coins_roll_vita_0_mana_0_level_0_path_peasant_max_held_in_1_slot_1_uses_1_crafts_none_other_uses_none_merchant_suggested_price_minimum_0_maximum_0_effect_100_to_999_coins_how_to_obtain_none_comments_none_shop_prices_npc_sells_0_npc_buys_0_smelting_agreement_vita_0_mana_0_level_0_path_peasant_max_held_in_1_slot_1_uses_1_crafts_none_other_uses_needed_to_smelt_ore_merchant_suggested_price_minimum_0_maximum_0_effect_needed_by_smelters_how_to_obtain_messenger_shops_comments_none_shop_prices_npc_sells_100_npc_buys_50_the_wandering_monk_vita_0_mana_0_level_0_path_peasant_max_held_in_1_slot_1_uses_1_crafts_none_other_uses_none_merchant_suggested_price_minimum_0_maximum_0_effect_read_monk_s_scroll_how_to_obtain_library_comments_none_shop_prices_npc_sells_1_000_npc_buys_0_tomes_of_the_earth_vita_0_mana_0_level_0_path_peasant_max_held_in_1_slot_1_uses_1_crafts_none_other_uses_none_merchant_suggested_price_minimum_0_maximum_0_effect_read_druid_s_scroll_how_to_obtain_library_comments_none_shop_prices_npc_sells_1_000_npc_buys_0_yuri_s_love_vita_0_mana_0_level_0_path_peasant_max_held_in_1_slot_1_uses_1_crafts_none_other_uses_make_bouquets_merchant_suggested_price_minimum_0_maximum_0_effect_none_how_to_obtain_created_by_druids_comments_these_were_created_when_king_yuri_fell_in_love_with_malady_druids_can_create_them_shop_prices_npc_sells_0_npc_buys_0",
      "name": "Items | Other Other All the items in Nexus that don't have \"that special category.\" Bombs / Crafts / Drops / Events / Keys / Mana / Potions / Quests Rocks / Scrolls / Shops / Spells / Vita / Woodlands Items / Extinct / Other Prices have been supplied by the Merchants and are suggested only and not to be used as the final authority on value of the item. For the most current prices consult the Merchant Subpath. Daffodil Vita : 0 Mana : 0 Level: 0 Path: Peasant Max. Held in 1 Slot: 1 Uses: 1 Crafts: None Other Uses: Make bouquets Merchant suggested price: Minimum: 0 Maximum: 0 Effect: None How to Obtain: Created by Druids Comments: Make great decorations! Shop prices: NPC Sells: 0 NPC Buys: 0 Dawn tulip Vita : 0 Mana : 0 Level: 0 Path: Peasant Max. Held in 1 Slot: 1 Uses: 1 Crafts: None Other Uses: Make bouquets Merchant suggested price: Minimum: 0 Maximum: 0 Effect: None How to Obtain: Created by Druids Comments: Make great decorations! Shop prices: NPC Sells: 0 NPC Buys: 0 Divine Chronicles Vita : 0 Mana : 0 Level: 0 Path: Peasant Max. Held in 1 Slot: 1 Uses: 1 Crafts: None Other Uses: None Merchant suggested price: Minimum: 0 Maximum: 0 Effect: Read Diviner's Scroll How to Obtain: Library Comments: None Shop prices: NPC Sells: 1,000 NPC Buys: 0 Dragon's tooth Vita : 0 Mana : 0 Level: 0 Path: Peasant Max. Held in 1 Slot: 1 Uses: 1 Crafts: None Other Uses: None Merchant suggested price: Minimum: 0 Maximum: 0 Effect: Allows the character to morph into a Serpentine Dragon How to Obtain: Go to the final room of Nexus Museum and talk to the Caretaker. Click \"Caretaker's gift\" to obtain one. Comments: The color of the morphed dragon depends on the dye the character is using on his armor Shop prices: NPC Sells: 0 NPC Buys: 0 Gold bar Vita : 0 Mana : 0 Level: 0 Path: Peasant Max. Held in 1 Slot: 1 Uses: 1 Crafts: None Other Uses: None Merchant suggested price: Minimum: 0 Maximum: 0 Effect: 1000+ coins in 1 stack How to Obtain: None Comments: None Shop prices: NPC Sells: 0 NPC Buys: 0 Golden sunset Vita : 0 Mana : 0 Level: 0 Path: Peasant Max. Held in 1 Slot: 1 Uses: 1 Crafts: None Other Uses: Make bouquets Merchant suggested price: Minimum: 0 Maximum: 0 Effect: None How to Obtain: Created by Druids Comments: Make great decorations! Shop prices: NPC Sells: 0 NPC Buys: 0 Graced by the Muse Vita : 0 Mana : 0 Level: 0 Path: Peasant Max. Held in 1 Slot: 1 Uses: 1 Crafts: None Other Uses: None Merchant suggested price: Minimum: 0 Maximum: 0 Effect: Read Muse's Scroll How to Obtain: Library Comments: None Shop prices: NPC Sells: 1,000 NPC Buys: 0 Greater tulip Vita : 0 Mana : 0 Level: 0 Path: Peasant Max. Held in 1 Slot: 1 Uses: 1 Crafts: None Other Uses: Make bouquets Merchant suggested price: Minimum: 0 Maximum: 0 Effect: None How to Obtain: Created by Druids Comments: Make great decorations! Shop prices: NPC Sells: 0 NPC Buys: 0 Heaven's bell Vita : 0 Mana : 0 Level: 0 Path: Peasant Max. Held in 1 Slot: 1 Uses: 1 Crafts: None Other Uses: Make bouquets Merchant suggested price: Minimum: 0 Maximum: 0 Effect: None How to Obtain: Created by Druids Comments: Make great decorations! Shop prices: NPC Sells: 0 NPC Buys: 0 Legend Vita : 0 Mana : 0 Level: 0 Path: Peasant Max. Held in 1 Slot: 1 Uses: 1 Crafts: None Other Uses: None Merchant suggested price: Minimum: 0 Maximum: 0 Effect: Tales of history and legendsProvides clues to many quests How to Obtain: Library Comments: None Shop prices: NPC Sells: 1,000 NPC Buys: 0 Midnight's reign Vita : 0 Mana : 0 Level: 0 Path: Peasant Max. Held in 1 Slot: 1 Uses: 1 Crafts: None Other Uses: Make bouquets Merchant suggested price: Minimum: 0 Maximum: 0 Effect: None How to Obtain: Created by Druids Comments: Make great decorations! Shop prices: NPC Sells: 0 NPC Buys: 0 Old poppy Vita : 0 Mana : 0 Level: 0 Path: Peasant Max. Held in 1 Slot: 1 Uses: 1 Crafts: None Other Uses: Make bouquets Merchant suggested price: Minimum: 0 Maximum: 0 Effect: None How to Obtain: Created by Druids Comments: Make great decorations! Shop prices: NPC Sells: 0 NPC Buys: 0 Penny Vita : 0 Mana : 0 Level: 0 Path: Peasant Max. Held in 1 Slot: 1 Uses: 1 Crafts: None Other Uses: None Merchant suggested price: Minimum: 0 Maximum: 0 Effect: 1 coin How to Obtain: None Comments: None Shop prices: NPC Sells: 0 NPC Buys: 0 Pennyroll Vita : 0 Mana : 0 Level: 0 Path: Peasant Max. Held in 1 Slot: 1 Uses: 1 Crafts: None Other Uses: None Merchant suggested price: Minimum: 0 Maximum: 0 Effect: 2 to 99 coins How to Obtain: None Comments: None Shop prices: NPC Sells: 0 NPC Buys: 0 Ranger Code Vita : 0 Mana : 0 Level: 0 Path: Peasant Max. Held in 1 Slot: 1 Uses: 1 Crafts: None Other Uses: None Merchant suggested price: Minimum: 0 Maximum: 0 Effect: Read Ranger's Scroll How to Obtain: Library Comments: None Shop prices: NPC Sells: 1,000 NPC Buys: 0 Rose Vita : 0 Mana : 0 Level: 0 Path: Peasant Max. Held in 1 Slot: 1 Uses: 1 Crafts: None Other Uses: Make bouquets Merchant suggested price: Minimum: 0 Maximum: 0 Effect: None How to Obtain: Walk past a rose bush! Comments: Make great decorations! Shop prices: NPC Sells: 0 NPC Buys: 0 Silver coins roll Vita : 0 Mana : 0 Level: 0 Path: Peasant Max. Held in 1 Slot: 1 Uses: 1 Crafts: None Other Uses: None Merchant suggested price: Minimum: 0 Maximum: 0 Effect: 100 to 999 coins How to Obtain: None Comments: None Shop prices: NPC Sells: 0 NPC Buys: 0 Smelting agreement Vita : 0 Mana : 0 Level: 0 Path: Peasant Max. Held in 1 Slot: 1 Uses: 1 Crafts: None Other Uses: Needed to Smelt ore Merchant suggested price: Minimum: 0 Maximum: 0 Effect: Needed by Smelters How to Obtain: Messenger shops Comments: None Shop prices: NPC Sells: 100 NPC Buys: 50 The Wandering Monk Vita : 0 Mana : 0 Level: 0 Path: Peasant Max. Held in 1 Slot: 1 Uses: 1 Crafts: None Other Uses: None Merchant suggested price: Minimum: 0 Maximum: 0 Effect: Read Monk's Scroll How to Obtain: Library Comments: None Shop prices: NPC Sells: 1,000 NPC Buys: 0 Tomes of the Earth Vita : 0 Mana : 0 Level: 0 Path: Peasant Max. Held in 1 Slot: 1 Uses: 1 Crafts: None Other Uses: None Merchant suggested price: Minimum: 0 Maximum: 0 Effect: Read Druid's Scroll How to Obtain: Library Comments: None Shop prices: NPC Sells: 1,000 NPC Buys: 0 Yuri's love Vita : 0 Mana : 0 Level: 0 Path: Peasant Max. Held in 1 Slot: 1 Uses: 1 Crafts: None Other Uses: Make bouquets Merchant suggested price: Minimum: 0 Maximum: 0 Effect: None How to Obtain: Created by Druids Comments: These were created when King Yuri fell in love with Malady. Druids can create them. Shop prices: NPC Sells: 0 NPC Buys: 0",
      "category": "item",
      "path": [
        "Peasant"
      ],
      "level_tier": "",
      "stats": {
        "Vita": 0,
        "Mana": 0
      },
      "stack_size": 1,
      "other_uses": [
        "Make bouquets"
      ],
      "obtain": [
        "Created by Druids"
      ],
      "comments": "Make great decorations!",
      "npc_buys": 0
    },
    {
      "id": "items_potions_potions_learn_how_to_make_potions_and_scrolls_here_bombs_crafts_drops_events_keys_mana_potions_quests_rocks_scrolls_shops_spells_vita_woodlands_items_extinct_other_prices_have_been_supplied_by_the_merchants_and_are_suggested_only_and_not_to_be_used_as_the_final_authority_on_value_of_the_item_for_the_most_current_prices_consult_the_merchant_subpath_aqua_potion_vita_0_mana_0_level_0_path_peasant_max_held_in_1_slot_1_uses_1_crafts_none_other_uses_none_merchant_suggested_price_minimum_0_maximum_0_effect_sanctuary_185_seconds_how_to_obtain_zombies_comments_none_shop_prices_npc_sells_0_npc_buys_0_red_potion_vita_0_mana_0_level_0_path_peasant_max_held_in_1_slot_2_uses_1_crafts_none_other_uses_need_to_weave_magical_net_merchant_suggested_price_minimum_0_maximum_0_effect_vita_restoration_100_how_to_obtain_potion_shops_comments_restores_all_vitaeach_attempt_to_weave_a_magical_net_needs_1_of_these_shop_prices_npc_sells_15_000_npc_buys_7_500",
      "name": "Items | Potions Potions Learn how to make Potions and Scrolls here. Bombs / Crafts / Drops / Events / Keys / Mana / Potions / Quests Rocks / Scrolls / Shops / Spells / Vita / Woodlands Items / Extinct / Other Prices have been supplied by the Merchants and are suggested only and not to be used as the final authority on value of the item. For the most current prices consult the Merchant Subpath. Aqua potion Vita : 0 Mana : 0 Level: 0 Path: Peasant Max. Held in 1 Slot: 1 Uses: 1 Crafts: None Other Uses: None Merchant suggested price: Minimum: 0 Maximum: 0 Effect: Sanctuary, 185 seconds How to Obtain: Zombies Comments: None Shop prices: NPC Sells: 0 NPC Buys: 0 Red potion Vita : 0 Mana : 0 Level: 0 Path: Peasant Max. Held in 1 Slot: 2 Uses: 1 Crafts: None Other Uses: Need to weave magical net Merchant suggested price: Minimum: 0 Maximum: 0 Effect: Vita restoration - 100% How to Obtain: Potion Shops Comments: Restores all vitaEach attempt to weave a Magical Net needs 1 of these Shop prices: NPC Sells: 15,000 NPC Buys: 7,500",
      "category": "item",
      "path": [
        "Peasant"
      ],
      "level_tier": "",
      "stats": {
        "Vita": 0,
        "Mana": 0
      },
      "stack_size": 1,
      "effect": "Sanctuary, 185 seconds",
      "obtain": [
        "Zombies"
      ],
      "npc_buys": 0
    },
    {
      "id": "items_quests_quests_all_of_the_stuff_you_need_for_or_receive_from_quests_bombs_crafts_drops_events_keys_mana_potions_quests_rocks_scrolls_shops_spells_vita_woodlands_items_extinct_other_prices_have_been_supplied_by_the_merchants_and_are_suggested_only_and_not_to_be_used_as_the_final_authority_on_value_of_the_item_for_the_most_current_prices_consult_the_merchant_subpath_chestnut_vita_8_mana_0_level_0_path_peasant_max_held_in_1_slot_10_uses_1_crafts_none_other_uses_none_merchant_suggested_price_minimum_0_maximum_0_effect_vita_restoration_how_to_obtain_spawns_in_town_gardens_comments_none_shop_prices_npc_sells_0_npc_buys_0_magical_net_vita_0_mana_0_level_0_path_peasant_max_held_in_1_slot_1_uses_1_crafts_none_other_uses_none_merchant_suggested_price_minimum_0_maximum_0_effect_captures_the_winds_how_to_obtain_weave_using_10_fine_cloth_and_1_red_potion_comments_needed_to_capture_the_winds_shop_prices_npc_sells_0_npc_buys_0_sute_key_vita_0_mana_0_level_0_path_peasant_max_held_in_1_slot_1_uses_1_crafts_none_other_uses_none_merchant_suggested_price_minimum_0_maximum_0_effect_none_how_to_obtain_sute_comments_none_shop_prices_npc_sells_0_npc_buys_0_young_ginseng_vita_40_mana_0_level_0_path_peasant_max_held_in_1_slot_1_uses_1_crafts_none_other_uses_none_merchant_suggested_price_minimum_0_maximum_0_effect_vita_restoration_how_to_obtain_chu_rua_comments_none_shop_prices_npc_sells_0_npc_buys_0",
      "name": "Items | Quests Quests All of the stuff you need for or receive from Quests! Bombs / Crafts / Drops / Events / Keys / Mana / Potions / Quests Rocks / Scrolls / Shops / Spells / Vita / Woodlands Items / Extinct / Other Prices have been supplied by the Merchants and are suggested only and not to be used as the final authority on value of the item. For the most current prices consult the Merchant Subpath. Chestnut Vita : 8 Mana : 0 Level: 0 Path: Peasant Max. Held in 1 Slot: 10 Uses: 1 Crafts: None Other Uses: None Merchant suggested price: Minimum: 0 Maximum: 0 Effect: Vita restoration How to Obtain: Spawns in town gardens Comments: None Shop prices: NPC Sells: 0 NPC Buys: 0 Magical net Vita : 0 Mana : 0 Level: 0 Path: Peasant Max. Held in 1 Slot: 1 Uses: 1 Crafts: None Other Uses: None Merchant suggested price: Minimum: 0 Maximum: 0 Effect: Captures the winds How to Obtain: Weave using 10 fine cloth and 1 red potion Comments: Needed to capture the winds Shop prices: NPC Sells: 0 NPC Buys: 0 Sute key Vita : 0 Mana : 0 Level: 0 Path: Peasant Max. Held in 1 Slot: 1 Uses: 1 Crafts: None Other Uses: None Merchant suggested price: Minimum: 0 Maximum: 0 Effect: None How to Obtain: Sute Comments: None Shop prices: NPC Sells: 0 NPC Buys: 0 Young ginseng Vita : 40 Mana : 0 Level: 0 Path: Peasant Max. Held in 1 Slot: 1 Uses: 1 Crafts: None Other Uses: None Merchant suggested price: Minimum: 0 Maximum: 0 Effect: Vita restoration How to Obtain: Chu rua Comments: None Shop prices: NPC Sells: 0 NPC Buys: 0",
      "category": "item",
      "path": [
        "Peasant"
      ],
      "level_tier": "",
      "stats": {
        "Vita": 8,
        "Mana": 0
      },
      "stack_size": 10,
      "effect": "Vita restoration",
      "obtain": [
        "Spawns in town gardens"
      ],
      "npc_buys": 0
    },
    {
      "id": "items_rocks_and_minerals_rocks_and_minerals_rocks_and_minerals_found_throughout_the_kingdom_know_which_stones_are_best_to_chuck_at_your_friends_bombs_crafts_drops_events_keys_mana_potions_quests_rocks_scrolls_shops_spells_vita_woodlands_items_extinct_other_prices_have_been_supplied_by_the_merchants_and_are_suggested_only_and_not_to_be_used_as_the_final_authority_on_value_of_the_item_for_the_most_current_prices_consult_the_merchant_subpath_amber_vita_0_mana_0_level_0_path_peasant_max_held_in_1_slot_100_uses_1_crafts_gemcutting_other_uses_crafts_merchant_suggested_price_minimum_0_maximum_0_effect_none_how_to_obtain_dropped_by_many_creatures_comments_none_shop_prices_npc_sells_0_npc_buys_0_amber_vita_0_mana_0_level_0_path_peasant_max_held_in_1_slot_100_uses_1_crafts_scribe_other_uses_crafts_merchant_suggested_price_minimum_0_maximum_0_effect_none_how_to_obtain_dropped_by_many_creatures_comments_none_shop_prices_npc_sells_0_npc_buys_0_amethyst_vita_0_mana_0_level_0_path_peasant_max_held_in_1_slot_1_uses_1_crafts_none_other_uses_none_merchant_suggested_price_minimum_0_maximum_0_effect_none_how_to_obtain_white_wolf_comments_needed_for_mage_dog_spell_shop_prices_npc_sells_0_npc_buys_600_dark_amber_vita_0_mana_0_level_0_path_peasant_max_held_in_1_slot_100_uses_1_crafts_scribe_other_uses_crafts_merchant_suggested_price_minimum_0_maximum_0_effect_none_how_to_obtain_dropped_by_many_creatures_comments_none_shop_prices_npc_sells_0_npc_buys_0_dark_amber_vita_0_mana_0_level_0_path_peasant_max_held_in_1_slot_100_uses_1_crafts_gemcutting_other_uses_crafts_merchant_suggested_price_minimum_0_maximum_0_effect_none_how_to_obtain_dropped_by_many_creatures_comments_none_shop_prices_npc_sells_0_npc_buys_0_onyx_shard_vita_50_mana_1000_level_0_path_peasant_max_held_in_1_slot_1_uses_5_crafts_none_other_uses_none_merchant_suggested_price_minimum_0_maximum_0_effect_mana_restoration_how_to_obtain_the_shattering_event_comments_none_shop_prices_npc_sells_0_npc_buys_0_prism_amber_vita_0_mana_0_level_0_path_peasant_max_held_in_1_slot_1_uses_1_crafts_none_other_uses_none_merchant_suggested_price_minimum_0_maximum_0_effect_none_how_to_obtain_woodlands_dog_cave_comments_none_shop_prices_npc_sells_0_npc_buys_0_rock_vita_0_mana_0_level_0_path_peasant_max_held_in_1_slot_1_uses_1_crafts_none_other_uses_none_merchant_suggested_price_minimum_0_maximum_0_effect_none_how_to_obtain_woodlands_raheem_desert_cave_comments_none_shop_prices_npc_sells_0_npc_buys_0_white_amber_vita_0_mana_0_level_0_path_peasant_max_held_in_1_slot_20_uses_1_crafts_gemcutting_other_uses_crafts_merchant_suggested_price_minimum_0_maximum_0_effect_none_how_to_obtain_dropped_by_many_creatures_comments_none_shop_prices_npc_sells_0_npc_buys_0_yellow_amber_vita_0_mana_0_level_0_path_peasant_max_held_in_1_slot_20_uses_1_crafts_gemcutting_other_uses_crafts_merchant_suggested_price_minimum_0_maximum_0_effect_none_how_to_obtain_dropped_by_many_creatures_comments_none_shop_prices_npc_sells_0_npc_buys_0",
      "name": "Items | Rocks and Minerals Rocks and Minerals Rocks and Minerals found throughout the Kingdom. Know which stones are best to chuck at your friends! Bombs / Crafts / Drops / Events / Keys / Mana / Potions / Quests Rocks / Scrolls / Shops / Spells / Vita / Woodlands Items / Extinct / Other Prices have been supplied by the Merchants and are suggested only and not to be used as the final authority on value of the item. For the most current prices consult the Merchant Subpath. Amber Vita : 0 Mana : 0 Level: 0 Path: Peasant Max. Held in 1 Slot: 100 Uses: 1 Crafts: Gemcutting Other Uses: Crafts Merchant suggested price: Minimum: 0 Maximum: 0 Effect: None How to Obtain: Dropped by many creatures Comments: None Shop prices: NPC Sells: 0 NPC Buys: 0 Amber Vita : 0 Mana : 0 Level: 0 Path: Peasant Max. Held in 1 Slot: 100 Uses: 1 Crafts: Scribe Other Uses: Crafts Merchant suggested price: Minimum: 0 Maximum: 0 Effect: None How to Obtain: Dropped by many creatures Comments: None Shop prices: NPC Sells: 0 NPC Buys: 0 Amethyst Vita : 0 Mana : 0 Level: 0 Path: Peasant Max. Held in 1 Slot: 1 Uses: 1 Crafts: None Other Uses: None Merchant suggested price: Minimum: 0 Maximum: 0 Effect: None How to Obtain: White wolf Comments: Needed for mage dog spell Shop prices: NPC Sells: 0 NPC Buys: 600 Dark amber Vita : 0 Mana : 0 Level: 0 Path: Peasant Max. Held in 1 Slot: 100 Uses: 1 Crafts: Scribe Other Uses: Crafts Merchant suggested price: Minimum: 0 Maximum: 0 Effect: None How to Obtain: Dropped by many creatures Comments: None Shop prices: NPC Sells: 0 NPC Buys: 0 Dark amber Vita : 0 Mana : 0 Level: 0 Path: Peasant Max. Held in 1 Slot: 100 Uses: 1 Crafts: Gemcutting Other Uses: Crafts Merchant suggested price: Minimum: 0 Maximum: 0 Effect: None How to Obtain: Dropped by many creatures Comments: None Shop prices: NPC Sells: 0 NPC Buys: 0 Onyx shard Vita : -50 Mana : 1000 Level: 0 Path: Peasant Max. Held in 1 Slot: 1 Uses: 5 Crafts: None Other Uses: None Merchant suggested price: Minimum: 0 Maximum: 0 Effect: Mana restoration How to Obtain: The Shattering Event Comments: None Shop prices: NPC Sells: 0 NPC Buys: 0 Prism amber Vita : 0 Mana : 0 Level: 0 Path: Peasant Max. Held in 1 Slot: 1 Uses: 1 Crafts: None Other Uses: None Merchant suggested price: Minimum: 0 Maximum: 0 Effect: None How to Obtain: Woodlands Dog Cave Comments: None Shop prices: NPC Sells: 0 NPC Buys: 0 Rock Vita : 0 Mana : 0 Level: 0 Path: Peasant Max. Held in 1 Slot: 1 Uses: 1 Crafts: None Other Uses: None Merchant suggested price: Minimum: 0 Maximum: 0 Effect: None How to Obtain: Woodlands Raheem Desert Cave Comments: None Shop prices: NPC Sells: 0 NPC Buys: 0 White amber Vita : 0 Mana : 0 Level: 0 Path: Peasant Max. Held in 1 Slot: 20 Uses: 1 Crafts: Gemcutting Other Uses: Crafts Merchant suggested price: Minimum: 0 Maximum: 0 Effect: None How to Obtain: Dropped by many creatures Comments: None Shop prices: NPC Sells: 0 NPC Buys: 0 Yellow amber Vita : 0 Mana : 0 Level: 0 Path: Peasant Max. Held in 1 Slot: 20 Uses: 1 Crafts: Gemcutting Other Uses: Crafts Merchant suggested price: Minimum: 0 Maximum: 0 Effect: None How to Obtain: Dropped by many creatures Comments: None Shop prices: NPC Sells: 0 NPC Buys: 0",
      "category": "item",
      "path": [
        "Peasant"
      ],
      "level_tier": "",
      "stats": {
        "Vita": 0,
        "Mana": 0
      },
      "stack_size": 100,
      "crafts": [
        "Gemcutting"
      ],
      "other_uses": [
        "Crafts"
      ],
      "obtain": [
        "Dropped by many creatures"
      ],
      "npc_buys": 0
    },
    {
      "id": "items_shop_items_shop_items_items_bought_or_sold_in_kingdom_shops_bombs_crafts_drops_events_keys_mana_potions_quests_rocks_scrolls_shops_spells_vita_woodlands_items_extinct_other_prices_have_been_supplied_by_the_merchants_and_are_suggested_only_and_not_to_be_used_as_the_final_authority_on_value_of_the_item_for_the_most_current_prices_consult_the_merchant_subpath_aged_wine_vita_5_mana_100_level_0_path_peasant_max_held_in_1_slot_1_uses_50_crafts_alchemy_other_uses_crafts_merchant_suggested_price_minimum_0_maximum_0_effect_restores_100_mana_takes_5_vita_how_to_obtain_potion_shops_comments_none_shop_prices_npc_sells_150_npc_buys_75_antlers_vita_248_mana_0_level_0_path_peasant_max_held_in_1_slot_52_uses_1_crafts_alchemy_other_uses_crafts_merchant_suggested_price_minimum_0_maximum_0_effect_restores_248_vitaused_by_alchemists_how_to_obtain_arena_shops_dropped_by_deers_comments_none_shop_prices_npc_sells_10_npc_buys_5_apple_vita_8_mana_0_level_0_path_peasant_max_held_in_1_slot_100_uses_1_crafts_none_other_uses_vita_restoration_merchant_suggested_price_minimum_0_maximum_0_effect_fun_to_throw_at_people_how_to_obtain_taverns_comments_none_shop_prices_npc_sells_10_npc_buys_5_axe_vita_0_mana_0_level_0_path_peasant_max_held_in_1_slot_1_uses_1_crafts_woodcutting_other_uses_crafts_merchant_suggested_price_minimum_50_maximum_50_effect_used_for_cutting_wood_how_to_obtain_shops_comments_used_for_cutting_wood_shop_prices_npc_sells_50_npc_buys_25_basic_sickle_vita_0_mana_0_level_0_path_peasant_max_held_in_1_slot_1_uses_1_crafts_farming_other_uses_crafts_merchant_suggested_price_minimum_200_maximum_100_effect_used_for_cutting_wood_how_to_obtain_shops_comments_used_for_cutting_wood_shop_prices_npc_sells_200_npc_buys_100_bear_s_liver_vita_500_mana_0_level_0_path_peasant_max_held_in_1_slot_100_uses_1_crafts_none_other_uses_none_merchant_suggested_price_minimum_0_maximum_0_effect_vita_restoration_how_to_obtain_shops_monsters_poet_call_of_the_wild_spell_comments_none_shop_prices_npc_sells_20_npc_buys_10_book_vita_0_mana_0_level_0_path_peasant_max_held_in_1_slot_1_uses_1_crafts_none_other_uses_spells_merchant_suggested_price_minimum_0_maximum_0_effect_needed_for_spells_how_to_obtain_buy_from_messenger_shops_comments_none_shop_prices_npc_sells_10_npc_buys_5_clear_water_song_vita_0_mana_0_level_0_path_peasant_max_held_in_1_slot_1_uses_1_crafts_none_other_uses_needed_to_make_scroll_of_defense_merchant_suggested_price_minimum_0_maximum_0_effect_casts_purge_how_to_obtain_buy_in_kugnae_baek_s_shop_comments_none_shop_prices_npc_sells_50_npc_buys_25_coconut_stick_vita_0_mana_0_level_0_path_peasant_max_held_in_1_slot_1_uses_1_crafts_farming_other_uses_crafts_merchant_suggested_price_minimum_200_maximum_100_effect_used_for_gathering_coconuts_how_to_obtain_shops_comments_shop_prices_npc_sells_200_npc_buys_100_comb_vita_0_mana_0_level_0_path_peasant_max_held_in_1_slot_1_uses_1_crafts_none_other_uses_none_merchant_suggested_price_minimum_0_maximum_0_effect_keep_your_hair_neat_how_to_obtain_taverns_comments_none_shop_prices_npc_sells_10_npc_buys_5_herb_pipe_vita_15_mana_300_level_0_path_peasant_max_held_in_1_slot_1_uses_100_crafts_none_other_uses_none_merchant_suggested_price_minimum_0_maximum_0_effect_mana_restoration_how_to_obtain_arena_and_alchemist_shops_guild_halls_comments_none_shop_prices_npc_sells_400_npc_buys_200_horse_meat_vita_200_mana_0_level_0_path_peasant_max_held_in_1_slot_100_uses_1_crafts_none_other_uses_none_merchant_suggested_price_minimum_0_maximum_0_effect_vita_restoration_how_to_obtain_mythic_horse_cave_comments_can_be_sold_in_shops_shop_prices_npc_sells_12_npc_buys_12_ink_vita_0_mana_0_level_0_path_peasant_max_held_in_1_slot_1_uses_1_crafts_scribe_other_uses_needed_to_make_most_scrolls_merchant_suggested_price_minimum_0_maximum_0_effect_needed_for_spells_and_the_scribe_craft_how_to_obtain_buy_in_messenger_shops_comments_none_shop_prices_npc_sells_100_npc_buys_50_legend_vita_0_mana_0_level_0_path_peasant_max_held_in_1_slot_1_uses_1_crafts_none_other_uses_none_merchant_suggested_price_minimum_0_maximum_0_effect_tales_of_history_and_legendsprovides_clues_to_many_quests_how_to_obtain_library_comments_none_shop_prices_npc_sells_1_000_npc_buys_0_life_blossom_vita_300_mana_0_level_0_path_peasant_max_held_in_1_slot_1_uses_20_crafts_none_other_uses_none_merchant_suggested_price_minimum_0_maximum_0_effect_vita_restoration_how_to_obtain_none_comments_bought_from_bodhi_s_sanctum_monk_s_subpath_area_shop_prices_npc_sells_600_npc_buys_300_limestone_vita_0_mana_0_level_0_path_peasant_max_held_in_1_slot_52_uses_1_crafts_none_other_uses_used_to_play_g_oh_merchant_suggested_price_minimum_0_maximum_0_effect_none_how_to_obtain_g_oh_shopkeepers_comments_used_to_play_g_oh_shop_prices_npc_sells_20_npc_buys_10_love_vita_0_mana_0_level_15_path_peasant_max_held_in_1_slot_1_uses_1_crafts_none_other_uses_allows_you_to_approach_your_beloved_merchant_suggested_price_minimum_0_maximum_0_effect_brings_you_to_your_mate_s_side_how_to_obtain_received_when_you_are_married_can_be_bought_in_chapels_comments_none_shop_prices_npc_sells_10_000_npc_buys_0_meat_vita_8_mana_0_level_0_path_peasant_max_held_in_1_slot_1_uses_1_crafts_none_other_uses_none_merchant_suggested_price_minimum_0_maximum_0_effect_vita_restoration_how_to_obtain_butcher_shops_comments_none_shop_prices_npc_sells_2_npc_buys_1_meat_scraps_vita_8_mana_0_level_0_path_peasant_max_held_in_1_slot_1_uses_1_crafts_none_other_uses_none_merchant_suggested_price_minimum_0_maximum_0_effect_vita_restoration_how_to_obtain_butcher_shops_comments_none_shop_prices_npc_sells_1_npc_buys_1_memory_blossom_vita_0_mana_30_level_0_path_peasant_max_held_in_1_slot_1_uses_200_crafts_none_other_uses_none_merchant_suggested_price_minimum_0_maximum_0_effect_mana_restoration_how_to_obtain_bohdi_s_sanctum_monk_subpath_area_comments_none_shop_prices_npc_sells_400_npc_buys_200_mining_shovel_vita_0_mana_0_level_0_path_peasant_max_held_in_1_slot_1_uses_1_crafts_mining_other_uses_crafts_merchant_suggested_price_minimum_20_maximum_40_effect_used_for_mining_how_to_obtain_shops_comments_shop_prices_npc_sells_40_npc_buys_20_moon_paper_vita_0_mana_0_level_0_path_peasant_max_held_in_1_slot_1_uses_1_crafts_scribe_other_uses_needed_to_make_scroll_of_defense_merchant_suggested_price_minimum_0_maximum_0_effect_none_how_to_obtain_buy_in_kugnae_baek_s_shop_comments_none_shop_prices_npc_sells_5_000_npc_buys_2_500_moon_wine_vita_5_mana_80_level_0_path_peasant_max_held_in_1_slot_1_uses_50_crafts_alchemy_other_uses_crafts_merchant_suggested_price_minimum_0_maximum_0_effect_none_how_to_obtain_potion_shops_comments_none_shop_prices_npc_sells_100_npc_buys_50_mountain_ginseng_vita_10000_mana_0_level_0_path_peasant_max_held_in_1_slot_10_uses_1_crafts_none_other_uses_spells_merchant_suggested_price_minimum_2_000_maximum_5_000_effect_vita_restoration_how_to_obtain_clan_shops_comments_dropped_by_town_rabbit_cave_bosses_shop_prices_npc_sells_2_000_npc_buys_1_000_obsidian_vita_0_mana_0_level_0_path_peasant_max_held_in_1_slot_52_uses_1_crafts_none_other_uses_used_to_play_g_oh_merchant_suggested_price_minimum_0_maximum_0_effect_none_how_to_obtain_g_oh_shopkeepers_comments_none_shop_prices_npc_sells_20_npc_buys_10_ogre_cider_vita_10_mana_100_level_0_path_peasant_max_held_in_1_slot_1_uses_20_crafts_none_other_uses_none_merchant_suggested_price_minimum_0_maximum_0_effect_mana_restoration_how_to_obtain_home_of_ugh_hamgyong_nam_do_comments_none_shop_prices_npc_sells_100_npc_buys_50_ogre_drought_vita_25_mana_325_level_0_path_peasant_max_held_in_1_slot_1_uses_39_crafts_none_other_uses_none_merchant_suggested_price_minimum_0_maximum_0_effect_mana_restoration_how_to_obtain_home_of_ugh_hamgyong_nam_do_comments_none_shop_prices_npc_sells_100_npc_buys_50_pork_vita_128_mana_0_level_0_path_peasant_max_held_in_1_slot_1_uses_1_crafts_none_other_uses_none_merchant_suggested_price_minimum_0_maximum_0_effect_vita_restoration_how_to_obtain_dropped_in_mythic_pig_cave_and_kugnae_snake_cave_comments_none_shop_prices_npc_sells_10_npc_buys_5_rice_wine_vita_0_mana_30_level_0_path_peasant_max_held_in_1_slot_1_uses_200_crafts_none_other_uses_mana_restoration_merchant_suggested_price_minimum_0_maximum_0_effect_restores_30_mana_how_to_obtain_taverns_comments_none_shop_prices_npc_sells_10_npc_buys_5_rich_wine_vita_10_mana_350_level_0_path_peasant_max_held_in_1_slot_1_uses_80_crafts_none_other_uses_mana_restoration_merchant_suggested_price_minimum_300_maximum_600_effect_restores_350_mana_and_takes_10_vita_how_to_obtain_bagai_shop_comments_restores_350_mana_shop_prices_npc_sells_600_npc_buys_300_root_liquor_vita_1_mana_30_level_0_path_peasant_max_held_in_1_slot_1_uses_200_crafts_none_other_uses_mana_restoration_merchant_suggested_price_minimum_0_maximum_0_effect_restores_30_mana_and_takes_1_vita_how_to_obtain_taverns_comments_none_shop_prices_npc_sells_10_npc_buys_5_sacred_poem_vita_0_mana_0_level_0_path_peasant_max_held_in_1_slot_1_uses_1_crafts_none_other_uses_needed_to_make_scroll_of_defense_merchant_suggested_price_minimum_0_maximum_0_effect_casts_harden_armor_how_to_obtain_buy_in_kugnae_baek_s_shop_comments_none_shop_prices_npc_sells_2_000_npc_buys_1_000_scroll_vita_0_mana_0_level_0_path_peasant_max_held_in_1_slot_1_uses_1_crafts_none_other_uses_spells_merchant_suggested_price_minimum_0_maximum_0_effect_needed_for_spells_how_to_obtain_buy_from_messenger_shops_comments_none_shop_prices_npc_sells_10_npc_buys_5_smelting_agreement_vita_0_mana_0_level_0_path_peasant_max_held_in_1_slot_1_uses_1_crafts_none_other_uses_needed_to_smelt_ore_merchant_suggested_price_minimum_0_maximum_0_effect_needed_by_smelters_how_to_obtain_messenger_shops_comments_none_shop_prices_npc_sells_100_npc_buys_50_sonhi_pipe_vita_50_mana_450_level_0_path_peasant_max_held_in_1_slot_1_uses_50_crafts_none_other_uses_none_merchant_suggested_price_minimum_0_maximum_0_effect_mana_restoration_how_to_obtain_kaming_s_encampment_messenger_comments_none_shop_prices_npc_sells_200_npc_buys_100_soup_bowl_vita_0_mana_0_level_0_path_peasant_max_held_in_1_slot_1_uses_1_crafts_none_other_uses_none_merchant_suggested_price_minimum_0_maximum_0_effect_needed_to_make_nagn_how_to_obtain_taverns_comments_none_shop_prices_npc_sells_10_npc_buys_5_thick_wine_vita_5_mana_40_level_0_path_peasant_max_held_in_1_slot_1_uses_50_crafts_none_other_uses_mana_restoration_merchant_suggested_price_minimum_0_maximum_0_effect_restores_40_mana_and_5_vita_how_to_obtain_taverns_comments_none_shop_prices_npc_sells_10_npc_buys_5_tiger_s_heart_vita_1000_mana_0_level_0_path_peasant_max_held_in_1_slot_20_uses_1_crafts_none_other_uses_none_merchant_suggested_price_minimum_0_maximum_0_effect_vita_restoration_how_to_obtain_shops_monsters_poet_call_of_the_wild_spell_comments_none_shop_prices_npc_sells_60_npc_buys_30_war_poem_vita_0_mana_0_level_0_path_peasant_max_held_in_1_slot_1_uses_1_crafts_none_other_uses_none_merchant_suggested_price_minimum_0_maximum_0_effect_casts_sanctuary_how_to_obtain_buy_in_kugnae_baek_s_shop_comments_none_shop_prices_npc_sells_2_500_npc_buys_1_350_white_paper_vita_0_mana_0_level_0_path_peasant_max_held_in_1_slot_1_uses_1_crafts_scribe_other_uses_needed_to_make_most_scrolls_merchant_suggested_price_minimum_0_maximum_0_effect_none_how_to_obtain_buy_in_messenger_shops_comments_none_shop_prices_npc_sells_100_npc_buys_50_wine_vita_5_mana_25_level_0_path_peasant_max_held_in_1_slot_1_uses_50_crafts_none_other_uses_mana_restoration_merchant_suggested_price_minimum_0_maximum_0_effect_restores_25_mana_and_5_vita_how_to_obtain_taverns_comments_none_shop_prices_npc_sells_10_npc_buys_5_yellow_scroll_vita_0_mana_0_level_0_path_peasant_max_held_in_1_slot_100_uses_1_crafts_none_other_uses_none_merchant_suggested_price_minimum_0_maximum_0_effect_return_to_taverns_how_to_obtain_taverns_comments_buy_in_taverns_shop_prices_npc_sells_1_npc_buys_1",
      "name": "Items | Shop Items Shop Items Items bought or sold in kingdom shops. Bombs / Crafts / Drops / Events / Keys / Mana / Potions / Quests Rocks / Scrolls / Shops / Spells / Vita / Woodlands Items / Extinct / Other Prices have been supplied by the Merchants and are suggested only and not to be used as the final authority on value of the item. For the most current prices consult the Merchant Subpath. Aged wine Vita : -5 Mana : 100 Level: 0 Path: Peasant Max. Held in 1 Slot: 1 Uses: 50 Crafts: Alchemy Other Uses: Crafts Merchant suggested price: Minimum: 0 Maximum: 0 Effect: Restores 100 mana, takes 5 vita How to Obtain: Potion Shops Comments: None Shop prices: NPC Sells: 150 NPC Buys: 75 Antlers Vita : 248 Mana : 0 Level: 0 Path: Peasant Max. Held in 1 Slot: 52 Uses: 1 Crafts: Alchemy Other Uses: Crafts Merchant suggested price: Minimum: 0 Maximum: 0 Effect: Restores 248 vitaUsed by Alchemists How to Obtain: Arena Shops, Dropped by Deers Comments: None Shop prices: NPC Sells: 10 NPC Buys: 5 Apple Vita : 8 Mana : 0 Level: 0 Path: Peasant Max. Held in 1 Slot: 100 Uses: 1 Crafts: None Other Uses: Vita restoration Merchant suggested price: Minimum: 0 Maximum: 0 Effect: Fun to throw at people! How to Obtain: Taverns Comments: None Shop prices: NPC Sells: 10 NPC Buys: 5 Axe Vita : 0 Mana : 0 Level: 0 Path: Peasant Max. Held in 1 Slot: 1 Uses: 1 Crafts: Woodcutting Other Uses: Crafts Merchant suggested price: Minimum: 50 Maximum: 50 Effect: Used for cutting wood How to Obtain: Shops Comments: Used for cutting wood Shop prices: NPC Sells: 50 NPC Buys: 25 Basic sickle Vita : 0 Mana : 0 Level: 0 Path: Peasant Max. Held in 1 Slot: 1 Uses: 1 Crafts: Farming Other Uses: Crafts Merchant suggested price: Minimum: 200 Maximum: 100 Effect: Used for cutting wood How to Obtain: Shops Comments: Used for cutting wood Shop prices: NPC Sells: 200 NPC Buys: 100 Bear's liver Vita : 500 Mana : 0 Level: 0 Path: Peasant Max. Held in 1 Slot: 100 Uses: 1 Crafts: None Other Uses: None Merchant suggested price: Minimum: 0 Maximum: 0 Effect: Vita restoration How to Obtain: Shops, monsters, poet Call of the Wild spell Comments: None Shop prices: NPC Sells: 20 NPC Buys: 10 Book Vita : 0 Mana : 0 Level: 0 Path: Peasant Max. Held in 1 Slot: 1 Uses: 1 Crafts: None Other Uses: Spells Merchant suggested price: Minimum: 0 Maximum: 0 Effect: Needed for spells How to Obtain: Buy from Messenger shops Comments: None Shop prices: NPC Sells: 10 NPC Buys: 5 Clear water song Vita : 0 Mana : 0 Level: 0 Path: Peasant Max. Held in 1 Slot: 1 Uses: 1 Crafts: None Other Uses: Needed to make Scroll of defense Merchant suggested price: Minimum: 0 Maximum: 0 Effect: Casts Purge How to Obtain: Buy in Kugnae, Baek's shop Comments: None Shop prices: NPC Sells: 50 NPC Buys: 25 Coconut stick Vita : 0 Mana : 0 Level: 0 Path: Peasant Max. Held in 1 Slot: 1 Uses: 1 Crafts: Farming Other Uses: Crafts Merchant suggested price: Minimum: 200 Maximum: 100 Effect: Used for gathering coconuts How to Obtain: Shops Comments: Shop prices: NPC Sells: 200 NPC Buys: 100 Comb Vita : 0 Mana : 0 Level: 0 Path: Peasant Max. Held in 1 Slot: 1 Uses: 1 Crafts: None Other Uses: None Merchant suggested price: Minimum: 0 Maximum: 0 Effect: Keep your hair neat! How to Obtain: Taverns Comments: None Shop prices: NPC Sells: 10 NPC Buys: 5 Herb pipe Vita : -15 Mana : 300 Level: 0 Path: Peasant Max. Held in 1 Slot: 1 Uses: 100 Crafts: None Other Uses: None Merchant suggested price: Minimum: 0 Maximum: 0 Effect: Mana restoration How to Obtain: Arena and Alchemist Shops, Guild Halls Comments: None Shop prices: NPC Sells: 400 NPC Buys: 200 Horse meat Vita : 200 Mana : 0 Level: 0 Path: Peasant Max. Held in 1 Slot: 100 Uses: 1 Crafts: None Other Uses: None Merchant suggested price: Minimum: 0 Maximum: 0 Effect: Vita restoration How to Obtain: Mythic horse cave Comments: Can be sold in shops Shop prices: NPC Sells: 12 NPC Buys: 12 Ink Vita : 0 Mana : 0 Level: 0 Path: Peasant Max. Held in 1 Slot: 1 Uses: 1 Crafts: Scribe Other Uses: Needed to make most Scrolls Merchant suggested price: Minimum: 0 Maximum: 0 Effect: Needed for spells and the Scribe craft How to Obtain: Buy in Messenger shops Comments: None Shop prices: NPC Sells: 100 NPC Buys: 50 Legend Vita : 0 Mana : 0 Level: 0 Path: Peasant Max. Held in 1 Slot: 1 Uses: 1 Crafts: None Other Uses: None Merchant suggested price: Minimum: 0 Maximum: 0 Effect: Tales of history and legendsProvides clues to many quests How to Obtain: Library Comments: None Shop prices: NPC Sells: 1,000 NPC Buys: 0 Life Blossom Vita : 300 Mana : 0 Level: 0 Path: Peasant Max. Held in 1 Slot: 1 Uses: 20 Crafts: None Other Uses: None Merchant suggested price: Minimum: 0 Maximum: 0 Effect: Vita restoration How to Obtain: None Comments: Bought from Bodhi's sanctum, Monk's Subpath Area Shop prices: NPC Sells: 600 NPC Buys: 300 Limestone Vita : 0 Mana : 0 Level: 0 Path: Peasant Max. Held in 1 Slot: 52 Uses: 1 Crafts: None Other Uses: Used to play G'oh Merchant suggested price: Minimum: 0 Maximum: 0 Effect: None How to Obtain: G'oh Shopkeepers Comments: Used to play G'oh Shop prices: NPC Sells: 20 NPC Buys: 10 Love Vita : 0 Mana : 0 Level: 15 Path: Peasant Max. Held in 1 Slot: 1 Uses: 1 Crafts: None Other Uses: Allows you to approach your beloved Merchant suggested price: Minimum: 0 Maximum: 0 Effect: Brings you to your mate's side. How to Obtain: Received when you are married. Can be bought in Chapels Comments: None Shop prices: NPC Sells: 10,000 NPC Buys: 0 Meat Vita : 8 Mana : 0 Level: 0 Path: Peasant Max. Held in 1 Slot: 1 Uses: 1 Crafts: None Other Uses: None Merchant suggested price: Minimum: 0 Maximum: 0 Effect: Vita restoration How to Obtain: Butcher shops Comments: None Shop prices: NPC Sells: 2 NPC Buys: 1 Meat scraps Vita : 8 Mana : 0 Level: 0 Path: Peasant Max. Held in 1 Slot: 1 Uses: 1 Crafts: None Other Uses: None Merchant suggested price: Minimum: 0 Maximum: 0 Effect: Vita restoration How to Obtain: Butcher shops Comments: None Shop prices: NPC Sells: 1 NPC Buys: 1 Memory blossom Vita : 0 Mana : 30 Level: 0 Path: Peasant Max. Held in 1 Slot: 1 Uses: 200 Crafts: None Other Uses: None Merchant suggested price: Minimum: 0 Maximum: 0 Effect: Mana restoration How to Obtain: Bohdi's Sanctum - Monk subpath area Comments: None Shop prices: NPC Sells: 400 NPC Buys: 200 Mining shovel Vita : 0 Mana : 0 Level: 0 Path: Peasant Max. Held in 1 Slot: 1 Uses: 1 Crafts: Mining Other Uses: Crafts Merchant suggested price: Minimum: 20 Maximum: 40 Effect: Used for mining How to Obtain: Shops Comments: Shop prices: NPC Sells: 40 NPC Buys: 20 Moon paper Vita : 0 Mana : 0 Level: 0 Path: Peasant Max. Held in 1 Slot: 1 Uses: 1 Crafts: Scribe Other Uses: Needed to make Scroll of defense Merchant suggested price: Minimum: 0 Maximum: 0 Effect: None How to Obtain: Buy in Kugnae, Baek's shop Comments: None Shop prices: NPC Sells: 5,000 NPC Buys: 2,500 Moon wine Vita : -5 Mana : 80 Level: 0 Path: Peasant Max. Held in 1 Slot: 1 Uses: 50 Crafts: Alchemy Other Uses: Crafts Merchant suggested price: Minimum: 0 Maximum: 0 Effect: None How to Obtain: Potion Shops Comments: None Shop prices: NPC Sells: 100 NPC Buys: 50 Mountain ginseng Vita : 10000 Mana : 0 Level: 0 Path: Peasant Max. Held in 1 Slot: 10 Uses: 1 Crafts: None Other Uses: Spells Merchant suggested price: Minimum: 2,000 Maximum: 5,000 Effect: Vita restoration How to Obtain: Clan Shops Comments: Dropped by Town Rabbit Cave bosses Shop prices: NPC Sells: 2,000 NPC Buys: 1,000 Obsidian Vita : 0 Mana : 0 Level: 0 Path: Peasant Max. Held in 1 Slot: 52 Uses: 1 Crafts: None Other Uses: Used to play G'oh Merchant suggested price: Minimum: 0 Maximum: 0 Effect: None How to Obtain: G'oh Shopkeepers Comments: None Shop prices: NPC Sells: 20 NPC Buys: 10 Ogre cider Vita : -10 Mana : 100 Level: 0 Path: Peasant Max. Held in 1 Slot: 1 Uses: 20 Crafts: None Other Uses: None Merchant suggested price: Minimum: 0 Maximum: 0 Effect: Mana restoration How to Obtain: Home of Ugh, Hamgyong nam-do Comments: None Shop prices: NPC Sells: 100 NPC Buys: 50 Ogre drought Vita : -25 Mana : 325 Level: 0 Path: Peasant Max. Held in 1 Slot: 1 Uses: 39 Crafts: None Other Uses: None Merchant suggested price: Minimum: 0 Maximum: 0 Effect: Mana restoration How to Obtain: Home of Ugh, Hamgyong nam-do Comments: None Shop prices: NPC Sells: 100 NPC Buys: 50 Pork Vita : 128 Mana : 0 Level: 0 Path: Peasant Max. Held in 1 Slot: 1 Uses: 1 Crafts: None Other Uses: None Merchant suggested price: Minimum: 0 Maximum: 0 Effect: Vita restoration How to Obtain: Dropped in Mythic Pig Cave and Kugnae Snake Cave Comments: None Shop prices: NPC Sells: 10 NPC Buys: 5 Rice wine Vita : 0 Mana : 30 Level: 0 Path: Peasant Max. Held in 1 Slot: 1 Uses: 200 Crafts: None Other Uses: Mana restoration Merchant suggested price: Minimum: 0 Maximum: 0 Effect: Restores 30 mana How to Obtain: Taverns Comments: None Shop prices: NPC Sells: 10 NPC Buys: 5 Rich wine Vita : -10 Mana : 350 Level: 0 Path: Peasant Max. Held in 1 Slot: 1 Uses: 80 Crafts: None Other Uses: Mana restoration Merchant suggested price: Minimum: 300 Maximum: 600 Effect: Restores 350 mana and takes 10 vita How to Obtain: Bagai Shop Comments: Restores 350 mana Shop prices: NPC Sells: 600 NPC Buys: 300 Root liquor Vita : -1 Mana : 30 Level: 0 Path: Peasant Max. Held in 1 Slot: 1 Uses: 200 Crafts: None Other Uses: Mana restoration Merchant suggested price: Minimum: 0 Maximum: 0 Effect: Restores 30 mana and takes 1 vita How to Obtain: Taverns Comments: None Shop prices: NPC Sells: 10 NPC Buys: 5 Sacred poem Vita : 0 Mana : 0 Level: 0 Path: Peasant Max. Held in 1 Slot: 1 Uses: 1 Crafts: None Other Uses: Needed to make Scroll of defense Merchant suggested price: Minimum: 0 Maximum: 0 Effect: Casts Harden Armor How to Obtain: Buy in Kugnae, Baek's shop Comments: None Shop prices: NPC Sells: 2,000 NPC Buys: 1,000 Scroll Vita : 0 Mana : 0 Level: 0 Path: Peasant Max. Held in 1 Slot: 1 Uses: 1 Crafts: None Other Uses: Spells Merchant suggested price: Minimum: 0 Maximum: 0 Effect: Needed for spells How to Obtain: Buy from Messenger shops Comments: None Shop prices: NPC Sells: 10 NPC Buys: 5 Smelting agreement Vita : 0 Mana : 0 Level: 0 Path: Peasant Max. Held in 1 Slot: 1 Uses: 1 Crafts: None Other Uses: Needed to Smelt ore Merchant suggested price: Minimum: 0 Maximum: 0 Effect: Needed by Smelters How to Obtain: Messenger shops Comments: None Shop prices: NPC Sells: 100 NPC Buys: 50 Sonhi pipe Vita : -50 Mana : 450 Level: 0 Path: Peasant Max. Held in 1 Slot: 1 Uses: 50 Crafts: None Other Uses: None Merchant suggested price: Minimum: 0 Maximum: 0 Effect: Mana restoration How to Obtain: KaMing's Encampment Messenger Comments: None Shop prices: NPC Sells: 200 NPC Buys: 100 Soup bowl Vita : 0 Mana : 0 Level: 0 Path: Peasant Max. Held in 1 Slot: 1 Uses: 1 Crafts: None Other Uses: None Merchant suggested price: Minimum: 0 Maximum: 0 Effect: Needed to make Nagn How to Obtain: Taverns Comments: None Shop prices: NPC Sells: 10 NPC Buys: 5 Thick wine Vita : 5 Mana : 40 Level: 0 Path: Peasant Max. Held in 1 Slot: 1 Uses: 50 Crafts: None Other Uses: Mana restoration Merchant suggested price: Minimum: 0 Maximum: 0 Effect: Restores 40 mana and 5 vita How to Obtain: Taverns Comments: None Shop prices: NPC Sells: 10 NPC Buys: 5 Tiger's heart Vita : 1000 Mana : 0 Level: 0 Path: Peasant Max. Held in 1 Slot: 20 Uses: 1 Crafts: None Other Uses: None Merchant suggested price: Minimum: 0 Maximum: 0 Effect: Vita restoration How to Obtain: Shops, monsters, poet Call of the Wild spell Comments: None Shop prices: NPC Sells: 60 NPC Buys: 30 War poem Vita : 0 Mana : 0 Level: 0 Path: Peasant Max. Held in 1 Slot: 1 Uses: 1 Crafts: None Other Uses: None Merchant suggested price: Minimum: 0 Maximum: 0 Effect: Casts Sanctuary How to Obtain: Buy in Kugnae, Baek's shop Comments: None Shop prices: NPC Sells: 2,500 NPC Buys: 1,350 White paper Vita : 0 Mana : 0 Level: 0 Path: Peasant Max. Held in 1 Slot: 1 Uses: 1 Crafts: Scribe Other Uses: Needed to make most Scrolls Merchant suggested price: Minimum: 0 Maximum: 0 Effect: None How to Obtain: Buy in Messenger shops Comments: None Shop prices: NPC Sells: 100 NPC Buys: 50 Wine Vita : 5 Mana : 25 Level: 0 Path: Peasant Max. Held in 1 Slot: 1 Uses: 50 Crafts: None Other Uses: Mana restoration Merchant suggested price: Minimum: 0 Maximum: 0 Effect: Restores 25 mana and 5 vita How to Obtain: Taverns Comments: None Shop prices: NPC Sells: 10 NPC Buys: 5 Yellow scroll Vita : 0 Mana : 0 Level: 0 Path: Peasant Max. Held in 1 Slot: 100 Uses: 1 Crafts: None Other Uses: None Merchant suggested price: Minimum: 0 Maximum: 0 Effect: Return to Taverns How to Obtain: Taverns Comments: Buy in Taverns Shop prices: NPC Sells: 1 NPC Buys: 1",
      "category": "item",
      "path": [
        "Peasant"
      ],
      "level_tier": "",
      "stats": {
        "Vita": -5,
        "Mana": 100
      },
      "stack_size": 1,
      "crafts": [
        "Alchemy"
      ],
      "other_uses": [
        "Crafts"
      ],
      "effect": "Restores 100 mana, takes 5 vita",
      "obtain": [
        "Potion Shops"
      ],
      "npc_buys": 75
    },
    {
      "id": "items_vita_restoration_vita_restoration_there_are_countless_items_that_you_can_eat_which_will_provide_you_with_small_amounts_vita_the_items_here_are_those_which_are_worth_carrying_around_to_restore_your_vita_bombs_crafts_drops_events_keys_mana_potions_quests_rocks_scrolls_shops_spells_vita_woodlands_items_extinct_other_prices_have_been_supplied_by_the_merchants_and_are_suggested_only_and_not_to_be_used_as_the_final_authority_on_value_of_the_item_for_the_most_current_prices_consult_the_merchant_subpath_antlers_vita_248_mana_0_level_0_path_peasant_max_held_in_1_slot_52_uses_1_crafts_alchemy_other_uses_crafts_merchant_suggested_price_minimum_0_maximum_0_effect_restores_248_vitaused_by_alchemists_how_to_obtain_arena_shops_dropped_by_deers_comments_none_shop_prices_npc_sells_10_npc_buys_5_bear_fur_vita_48_mana_0_level_0_path_peasant_max_held_in_1_slot_1_uses_1_crafts_none_other_uses_keep_your_feet_warm_stand_on_it_merchant_suggested_price_minimum_0_maximum_0_effect_none_how_to_obtain_dropped_by_bears_in_vale_north_of_the_buya_entrance_near_the_great_gate_comments_none_shop_prices_npc_sells_0_npc_buys_0_bear_s_liver_vita_500_mana_0_level_0_path_peasant_max_held_in_1_slot_100_uses_1_crafts_none_other_uses_none_merchant_suggested_price_minimum_0_maximum_0_effect_vita_restoration_how_to_obtain_shops_monsters_poet_call_of_the_wild_spell_comments_none_shop_prices_npc_sells_20_npc_buys_10_beautiful_fish_vita_0_mana_0_level_0_path_peasant_max_held_in_1_slot_1_uses_1_crafts_fishing_other_uses_merchant_suggested_price_minimum_0_maximum_0_effect_vita_restoration_how_to_obtain_fishing_comments_none_shop_prices_npc_sells_0_npc_buys_0_bird_meat_vita_100_mana_0_level_0_path_peasant_max_held_in_1_slot_30_uses_1_crafts_food_preparation_other_uses_needed_for_food_preparation_skill_merchant_suggested_price_minimum_0_maximum_0_effect_vita_how_to_obtain_dropped_by_pheasants_in_the_woodlands_comments_none_shop_prices_npc_sells_0_npc_buys_0_blue_potion_vita_100_mana_0_level_0_path_peasant_max_held_in_1_slot_1_uses_1_crafts_none_other_uses_none_merchant_suggested_price_minimum_0_maximum_0_effect_restores_100_vita_how_to_obtain_potion_shops_comments_restores_100_vita_shop_prices_npc_sells_10_npc_buys_5_boiled_beef_vita_100_mana_0_level_0_path_peasant_max_held_in_1_slot_25_uses_1_crafts_chef_other_uses_none_merchant_suggested_price_minimum_0_maximum_0_effect_vita_restoration_how_to_obtain_made_by_chefs_comments_none_shop_prices_npc_sells_0_npc_buys_0_boiled_fish_vita_1000_mana_0_level_0_path_peasant_max_held_in_1_slot_25_uses_1_crafts_food_preparation_other_uses_none_merchant_suggested_price_minimum_0_maximum_0_effect_vita_restoration_how_to_obtain_made_by_food_preparers_comments_none_shop_prices_npc_sells_0_npc_buys_0_boiled_pork_vita_900_mana_0_level_0_path_peasant_max_held_in_1_slot_0_uses_1_crafts_chef_other_uses_none_merchant_suggested_price_minimum_0_maximum_0_effect_mana_restoration_how_to_obtain_chefs_comments_none_shop_prices_npc_sells_0_npc_buys_0_broiled_meat_vita_1500_mana_0_level_0_path_peasant_max_held_in_1_slot_10_uses_1_crafts_food_preparation_other_uses_none_merchant_suggested_price_minimum_0_maximum_0_effect_vita_restoration_how_to_obtain_cooking_tiger_meat_comments_made_from_tiger_meat_but_barbarians_may_be_forced_to_hurt_you_if_you_cook_this_shop_prices_npc_sells_0_npc_buys_0_chicken_meat_vita_40_mana_0_level_0_path_peasant_max_held_in_1_slot_30_uses_1_crafts_food_preparation_other_uses_food_preparation_skill_merchant_suggested_price_minimum_0_maximum_0_effect_vita_restoration_how_to_obtain_none_comments_dropped_by_various_chicken_creatures_shop_prices_npc_sells_0_npc_buys_0_cooked_fish_vita_900_mana_0_level_0_path_peasant_max_held_in_1_slot_50_uses_1_crafts_none_other_uses_for_wives_to_use_next_to_their_husbands_merchant_suggested_price_minimum_0_maximum_0_effect_causes_husband_and_wife_to_wink_how_to_obtain_chapels_comments_if_a_husband_eats_this_while_standing_next_to_his_wife_he_gets_960_vita_all_other_uses_give_20_vita_shop_prices_npc_sells_20_npc_buys_0_delicious_fish_vita_960_mana_0_level_0_path_peasant_max_held_in_1_slot_1_uses_1_crafts_fishing_other_uses_needed_for_food_preparation_skill_merchant_suggested_price_minimum_0_maximum_0_effect_vita_restoration_how_to_obtain_none_comments_none_shop_prices_npc_sells_0_npc_buys_0_egg_vita_8_mana_0_level_0_path_peasant_max_held_in_1_slot_12_uses_1_crafts_food_preparation_other_uses_needed_for_food_preparation_skill_merchant_suggested_price_minimum_0_maximum_0_effect_vita_restoration_how_to_obtain_dropped_by_various_chickens_comments_none_shop_prices_npc_sells_0_npc_buys_0_fine_rabbit_meat_vita_200_mana_0_level_0_path_peasant_max_held_in_1_slot_100_uses_1_crafts_none_other_uses_none_merchant_suggested_price_minimum_0_maximum_0_effect_vita_restoration_how_to_obtain_mythic_rabbits_comments_none_shop_prices_npc_sells_0_npc_buys_0_fine_snake_meat_vita_320_mana_0_level_0_path_peasant_max_held_in_1_slot_40_uses_1_crafts_alchemy_other_uses_alchemy_lime_potions_merchant_suggested_price_minimum_0_maximum_0_effect_vita_restoration_how_to_obtain_mythic_snakes_comments_none_shop_prices_npc_sells_0_npc_buys_0_fried_egg_vita_100_mana_0_level_0_path_peasant_max_held_in_1_slot_12_uses_1_crafts_food_preparation_other_uses_made_by_food_preparation_merchant_suggested_price_minimum_0_maximum_0_effect_vita_restoration_how_to_obtain_none_comments_none_shop_prices_npc_sells_0_npc_buys_0_ginseng_vita_2000_mana_0_level_0_path_peasant_max_held_in_1_slot_1_uses_1_crafts_none_other_uses_none_merchant_suggested_price_minimum_0_maximum_0_effect_vita_restoration_how_to_obtain_various_rats_comments_none_shop_prices_npc_sells_0_npc_buys_0_ginseng_piece_vita_60_mana_0_level_0_path_peasant_max_held_in_1_slot_1_uses_1_crafts_none_other_uses_none_merchant_suggested_price_minimum_0_maximum_0_effect_vita_restoration_how_to_obtain_various_rats_comments_none_shop_prices_npc_sells_0_npc_buys_0_grilled_beef_vita_800_mana_0_level_0_path_peasant_max_held_in_1_slot_25_uses_1_crafts_none_other_uses_none_merchant_suggested_price_minimum_0_maximum_0_effect_vita_restoration_how_to_obtain_created_by_food_preparation_comments_none_shop_prices_npc_sells_0_npc_buys_0_horse_meat_vita_200_mana_0_level_0_path_peasant_max_held_in_1_slot_100_uses_1_crafts_none_other_uses_none_merchant_suggested_price_minimum_0_maximum_0_effect_vita_restoration_how_to_obtain_mythic_horse_cave_comments_can_be_sold_in_shops_shop_prices_npc_sells_12_npc_buys_12_large_fish_vita_440_mana_0_level_0_path_peasant_max_held_in_1_slot_10_uses_1_crafts_fishing_other_uses_needed_for_food_preparation_skill_merchant_suggested_price_minimum_0_maximum_0_effect_vita_restoration_how_to_obtain_fishing_comments_none_shop_prices_npc_sells_0_npc_buys_0_lean_beef_vita_500_mana_0_level_0_path_peasant_max_held_in_1_slot_50_uses_1_crafts_food_preparation_other_uses_needed_for_food_preparation_skill_merchant_suggested_price_minimum_0_maximum_0_effect_vita_restoration_how_to_obtain_mythic_oxen_kugnae_mud_snake_comments_none_shop_prices_npc_sells_0_npc_buys_0_leech_juice_vita_0_mana_0_level_0_path_peasant_max_held_in_1_slot_4_uses_1_crafts_none_other_uses_gives_up_to_33_vita_restoration_when_used_merchant_suggested_price_minimum_0_maximum_0_effect_vita_restoration_33_how_to_obtain_lost_mines_comments_dropped_by_leeches_in_lost_mine_events_shop_prices_npc_sells_0_npc_buys_0_life_blossom_vita_300_mana_0_level_0_path_peasant_max_held_in_1_slot_1_uses_20_crafts_none_other_uses_none_merchant_suggested_price_minimum_0_maximum_0_effect_vita_restoration_how_to_obtain_none_comments_bought_from_bodhi_s_sanctum_monk_s_subpath_area_shop_prices_npc_sells_600_npc_buys_300_malodorous_fish_vita_80_mana_0_level_0_path_peasant_max_held_in_1_slot_100_uses_1_crafts_none_other_uses_trade_for_items_in_chum_s_fish_hut_hamgyong_nam_do_merchant_suggested_price_minimum_0_maximum_0_effect_vita_restoration_how_to_obtain_river_ogres_comments_none_shop_prices_npc_sells_0_npc_buys_0_medium_fish_vita_360_mana_0_level_0_path_peasant_max_held_in_1_slot_10_uses_1_crafts_fishing_other_uses_needed_for_food_preparation_skill_merchant_suggested_price_minimum_0_maximum_0_effect_vita_restoration_how_to_obtain_fishing_comments_none_shop_prices_npc_sells_0_npc_buys_0_mountain_ginseng_vita_10000_mana_0_level_0_path_peasant_max_held_in_1_slot_10_uses_1_crafts_none_other_uses_spells_merchant_suggested_price_minimum_2_000_maximum_5_000_effect_vita_restoration_how_to_obtain_clan_shops_comments_dropped_by_town_rabbit_cave_bosses_shop_prices_npc_sells_2_000_npc_buys_1_000_noodles_vita_300_mana_0_level_0_path_peasant_max_held_in_1_slot_1_uses_1_crafts_chef_other_uses_none_merchant_suggested_price_minimum_0_maximum_0_effect_vita_restoration_how_to_obtain_none_comments_prepared_from_salt_block_water_jug_and_flour_by_players_with_food_preparation_skill_shop_prices_npc_sells_0_npc_buys_0_peas_vita_100_mana_0_level_0_path_peasant_max_held_in_1_slot_5_uses_1_crafts_gardening_other_uses_none_merchant_suggested_price_minimum_0_maximum_0_effect_vita_restoration_how_to_obtain_none_comments_dug_from_kugnae_and_wilderness_gardens_shop_prices_npc_sells_0_npc_buys_0_pork_vita_128_mana_0_level_0_path_peasant_max_held_in_1_slot_1_uses_1_crafts_none_other_uses_none_merchant_suggested_price_minimum_0_maximum_0_effect_vita_restoration_how_to_obtain_dropped_in_mythic_pig_cave_and_kugnae_snake_cave_comments_none_shop_prices_npc_sells_10_npc_buys_5_putrid_fish_vita_120_mana_0_level_0_path_peasant_max_held_in_1_slot_100_uses_1_crafts_none_other_uses_trade_for_items_in_chum_s_fish_hut_hamgyong_nam_do_merchant_suggested_price_minimum_0_maximum_0_effect_vita_restoration_how_to_obtain_river_ogres_comments_none_shop_prices_npc_sells_0_npc_buys_0_rabbit_meat_vita_48_mana_0_level_0_path_peasant_max_held_in_1_slot_200_uses_1_crafts_none_other_uses_spell_item_merchant_suggested_price_minimum_0_maximum_0_effect_needs_for_spells_how_to_obtain_dropped_by_various_rabbits_comments_none_shop_prices_npc_sells_2_npc_buys_2_red_potion_vita_0_mana_0_level_0_path_peasant_max_held_in_1_slot_2_uses_1_crafts_none_other_uses_need_to_weave_magical_net_merchant_suggested_price_minimum_0_maximum_0_effect_vita_restoration_100_how_to_obtain_potion_shops_comments_restores_all_vitaeach_attempt_to_weave_a_magical_net_needs_1_of_these_shop_prices_npc_sells_15_000_npc_buys_7_500_repugnant_fish_vita_80_mana_0_level_0_path_peasant_max_held_in_1_slot_100_uses_1_crafts_none_other_uses_trade_for_items_in_chum_s_fish_hut_hamgyong_nam_do_merchant_suggested_price_minimum_0_maximum_0_effect_vita_restoration_how_to_obtain_river_ogres_comments_none_shop_prices_npc_sells_0_npc_buys_0_roast_chicken_vita_1000_mana_0_level_0_path_peasant_max_held_in_1_slot_25_uses_1_crafts_food_preparation_other_uses_none_merchant_suggested_price_minimum_0_maximum_0_effect_vita_restoration_how_to_obtain_food_preparers_comments_prepared_from_bird_or_chicken_meat_by_players_with_food_preparation_skill_shop_prices_npc_sells_0_npc_buys_0_rose_petals_vita_900_mana_0_level_0_path_peasant_max_held_in_1_slot_50_uses_1_crafts_none_other_uses_for_husbands_to_use_next_to_their_wives_merchant_suggested_price_minimum_0_maximum_0_effect_causes_husband_and_wife_to_wink_how_to_obtain_chapels_comments_if_a_wife_eats_this_while_standing_next_to_her_husband_she_gets_960_vita_all_other_uses_give_20_vita_shop_prices_npc_sells_20_npc_buys_0_scrawny_fish_vita_180_mana_0_level_0_path_peasant_max_held_in_1_slot_10_uses_1_crafts_fishing_other_uses_needed_for_food_preparation_skill_merchant_suggested_price_minimum_0_maximum_0_effect_vita_restoration_how_to_obtain_fishing_comments_none_shop_prices_npc_sells_0_npc_buys_0_seaweed_vita_400_mana_0_level_0_path_peasant_max_held_in_1_slot_25_uses_1_crafts_none_other_uses_none_merchant_suggested_price_minimum_0_maximum_0_effect_vita_restoration_how_to_obtain_dropped_by_island_lobsters_in_hausson_dropped_by_most_snakes_in_woodlands_snake_cave_comments_none_shop_prices_npc_sells_0_npc_buys_0_small_fish_vita_400_mana_0_level_0_path_peasant_max_held_in_1_slot_10_uses_1_crafts_fishing_other_uses_needed_for_food_preparation_skill_merchant_suggested_price_minimum_0_maximum_0_effect_vita_restoration_how_to_obtain_fishing_comments_none_shop_prices_npc_sells_0_npc_buys_0_snake_meat_vita_100_mana_0_level_0_path_peasant_max_held_in_1_slot_100_uses_1_crafts_none_other_uses_crafts_merchant_suggested_price_minimum_0_maximum_0_effect_vita_restoration_how_to_obtain_various_snakes_comments_none_shop_prices_npc_sells_0_npc_buys_0_tasty_fish_vita_540_mana_0_level_0_path_peasant_max_held_in_1_slot_10_uses_1_crafts_fishing_other_uses_needed_for_food_preparation_skill_merchant_suggested_price_minimum_0_maximum_0_effect_vita_restoration_how_to_obtain_fishing_comments_none_shop_prices_npc_sells_0_npc_buys_0_tiger_meat_vita_100_mana_0_level_0_path_peasant_max_held_in_1_slot_10_uses_1_crafts_food_preparation_other_uses_subpath_quest_item_merchant_suggested_price_minimum_0_maximum_0_effect_vita_restoration_how_to_obtain_dropped_by_iron_lab_tigers_comments_none_shop_prices_npc_sells_100_npc_buys_50_tiger_s_heart_vita_1000_mana_0_level_0_path_peasant_max_held_in_1_slot_20_uses_1_crafts_none_other_uses_none_merchant_suggested_price_minimum_0_maximum_0_effect_vita_restoration_how_to_obtain_shops_monsters_poet_call_of_the_wild_spell_comments_none_shop_prices_npc_sells_60_npc_buys_30_tiny_fish_vita_100_mana_0_level_0_path_peasant_max_held_in_1_slot_10_uses_1_crafts_fishing_other_uses_needed_for_food_preparation_skill_merchant_suggested_price_minimum_0_maximum_0_effect_vita_restoration_how_to_obtain_fishing_comments_none_shop_prices_npc_sells_0_npc_buys_0_violet_potion_vita_200_mana_0_level_0_path_peasant_max_held_in_1_slot_50_uses_1_crafts_none_other_uses_none_merchant_suggested_price_minimum_0_maximum_0_effect_restores_200_vita_how_to_obtain_potion_shops_comments_restores_200_vita_shop_prices_npc_sells_30_npc_buys_15_watermelon_vita_800_mana_0_level_0_path_peasant_max_held_in_1_slot_1_uses_1_crafts_none_other_uses_none_merchant_suggested_price_minimum_0_maximum_0_effect_vita_restoration_how_to_obtain_halloween_events_comments_none_shop_prices_npc_sells_0_npc_buys_0_wolf_meat_vita_48_mana_0_level_0_path_peasant_max_held_in_1_slot_1_uses_1_crafts_none_other_uses_needed_for_chung_ryong_helm_et_merchant_suggested_price_minimum_0_maximum_0_effect_vita_restoration_how_to_obtain_dropped_by_various_wolves_comments_none_shop_prices_npc_sells_4_npc_buys_2_yellow_potion_vita_50_mana_0_level_0_path_peasant_max_held_in_1_slot_1_uses_1_crafts_none_other_uses_none_merchant_suggested_price_minimum_0_maximum_0_effect_restores_50_vita_how_to_obtain_potion_shops_comments_restores_50_vita_shop_prices_npc_sells_10_npc_buys_5_young_ginseng_vita_40_mana_0_level_0_path_peasant_max_held_in_1_slot_1_uses_1_crafts_none_other_uses_none_merchant_suggested_price_minimum_0_maximum_0_effect_vita_restoration_how_to_obtain_chu_rua_comments_none_shop_prices_npc_sells_0_npc_buys_0",
      "name": "Items | Vita Restoration Vita Restoration There are countless items that you can eat which will provide you with small amounts vita. The items here are those which are worth carrying around to restore your vita. Bombs / Crafts / Drops / Events / Keys / Mana / Potions / Quests Rocks / Scrolls / Shops / Spells / Vita / Woodlands Items / Extinct / Other Prices have been supplied by the Merchants and are suggested only and not to be used as the final authority on value of the item. For the most current prices consult the Merchant Subpath. Antlers Vita : 248 Mana : 0 Level: 0 Path: Peasant Max. Held in 1 Slot: 52 Uses: 1 Crafts: Alchemy Other Uses: Crafts Merchant suggested price: Minimum: 0 Maximum: 0 Effect: Restores 248 vitaUsed by Alchemists How to Obtain: Arena Shops, Dropped by Deers Comments: None Shop prices: NPC Sells: 10 NPC Buys: 5 Bear fur Vita : 48 Mana : 0 Level: 0 Path: Peasant Max. Held in 1 Slot: 1 Uses: 1 Crafts: None Other Uses: Keep your feet warm; stand on it! Merchant suggested price: Minimum: 0 Maximum: 0 Effect: None How to Obtain: Dropped by Bears in Vale north of the Buya entrance near the Great Gate. Comments: None Shop prices: NPC Sells: 0 NPC Buys: 0 Bear's liver Vita : 500 Mana : 0 Level: 0 Path: Peasant Max. Held in 1 Slot: 100 Uses: 1 Crafts: None Other Uses: None Merchant suggested price: Minimum: 0 Maximum: 0 Effect: Vita restoration How to Obtain: Shops, monsters, poet Call of the Wild spell Comments: None Shop prices: NPC Sells: 20 NPC Buys: 10 Beautiful fish Vita : 0 Mana : 0 Level: 0 Path: Peasant Max. Held in 1 Slot: 1 Uses: 1 Crafts: Fishing Other Uses: Merchant suggested price: Minimum: 0 Maximum: 0 Effect: Vita restoration How to Obtain: Fishing Comments: None Shop prices: NPC Sells: 0 NPC Buys: 0 Bird meat Vita : 100 Mana : 0 Level: 0 Path: Peasant Max. Held in 1 Slot: 30 Uses: 1 Crafts: Food preparation Other Uses: Needed for food preparation skill Merchant suggested price: Minimum: 0 Maximum: 0 Effect: Vita How to Obtain: Dropped by Pheasants in the Woodlands Comments: None Shop prices: NPC Sells: 0 NPC Buys: 0 Blue potion Vita : 100 Mana : 0 Level: 0 Path: Peasant Max. Held in 1 Slot: 1 Uses: 1 Crafts: None Other Uses: None Merchant suggested price: Minimum: 0 Maximum: 0 Effect: Restores 100 vita How to Obtain: Potion Shops Comments: Restores 100 vita Shop prices: NPC Sells: 10 NPC Buys: 5 Boiled beef Vita : 100 Mana : 0 Level: 0 Path: Peasant Max. Held in 1 Slot: 25 Uses: 1 Crafts: Chef Other Uses: None Merchant suggested price: Minimum: 0 Maximum: 0 Effect: Vita restoration How to Obtain: Made by chefs Comments: None Shop prices: NPC Sells: 0 NPC Buys: 0 Boiled fish Vita : 1000 Mana : 0 Level: 0 Path: Peasant Max. Held in 1 Slot: 25 Uses: 1 Crafts: Food preparation Other Uses: None Merchant suggested price: Minimum: 0 Maximum: 0 Effect: Vita restoration How to Obtain: Made by food preparers Comments: None Shop prices: NPC Sells: 0 NPC Buys: 0 Boiled pork Vita : 900 Mana : 0 Level: 0 Path: Peasant Max. Held in 1 Slot: 0 Uses: 1 Crafts: Chef Other Uses: None Merchant suggested price: Minimum: 0 Maximum: 0 Effect: Mana restoration How to Obtain: Chefs Comments: None Shop prices: NPC Sells: 0 NPC Buys: 0 Broiled meat Vita : 1500 Mana : 0 Level: 0 Path: Peasant Max. Held in 1 Slot: 10 Uses: 1 Crafts: Food preparation Other Uses: None Merchant suggested price: Minimum: 0 Maximum: 0 Effect: Vita restoration How to Obtain: Cooking Tiger meat. Comments: Made from Tiger meat but Barbarians may be forced to hurt you if you cook this! Shop prices: NPC Sells: 0 NPC Buys: 0 Chicken meat Vita : 40 Mana : 0 Level: 0 Path: Peasant Max. Held in 1 Slot: 30 Uses: 1 Crafts: Food preparation Other Uses: Food preparation skill Merchant suggested price: Minimum: 0 Maximum: 0 Effect: Vita restoration How to Obtain: None Comments: Dropped by various chicken creatures Shop prices: NPC Sells: 0 NPC Buys: 0 Cooked fish Vita : 900 Mana : 0 Level: 0 Path: Peasant Max. Held in 1 Slot: 50 Uses: 1 Crafts: None Other Uses: For wives to use next to their husbands Merchant suggested price: Minimum: 0 Maximum: 0 Effect: Causes husband and wife to wink. How to Obtain: Chapels Comments: If a husband eats this while standing next to his wife, he gets 960 vita. All other uses give 20 vita. Shop prices: NPC Sells: 20 NPC Buys: 0 Delicious fish Vita : 960 Mana : 0 Level: 0 Path: Peasant Max. Held in 1 Slot: 1 Uses: 1 Crafts: Fishing Other Uses: Needed for food preparation skill Merchant suggested price: Minimum: 0 Maximum: 0 Effect: Vita restoration How to Obtain: None Comments: None Shop prices: NPC Sells: 0 NPC Buys: 0 Egg Vita : 8 Mana : 0 Level: 0 Path: Peasant Max. Held in 1 Slot: 12 Uses: 1 Crafts: Food preparation Other Uses: Needed for food preparation skill Merchant suggested price: Minimum: 0 Maximum: 0 Effect: Vita restoration How to Obtain: Dropped by various chickens Comments: None Shop prices: NPC Sells: 0 NPC Buys: 0 Fine rabbit meat Vita : 200 Mana : 0 Level: 0 Path: Peasant Max. Held in 1 Slot: 100 Uses: 1 Crafts: None Other Uses: None Merchant suggested price: Minimum: 0 Maximum: 0 Effect: Vita restoration How to Obtain: Mythic rabbits Comments: None Shop prices: NPC Sells: 0 NPC Buys: 0 Fine snake meat Vita : 320 Mana : 0 Level: 0 Path: Peasant Max. Held in 1 Slot: 40 Uses: 1 Crafts: Alchemy Other Uses: Alchemy - lime potions Merchant suggested price: Minimum: 0 Maximum: 0 Effect: Vita restoration How to Obtain: Mythic Snakes Comments: None Shop prices: NPC Sells: 0 NPC Buys: 0 Fried egg Vita : 100 Mana : 0 Level: 0 Path: Peasant Max. Held in 1 Slot: 12 Uses: 1 Crafts: Food preparation Other Uses: Made by food preparation Merchant suggested price: Minimum: 0 Maximum: 0 Effect: Vita restoration How to Obtain: None Comments: None Shop prices: NPC Sells: 0 NPC Buys: 0 Ginseng Vita : 2000 Mana : 0 Level: 0 Path: Peasant Max. Held in 1 Slot: 1 Uses: 1 Crafts: None Other Uses: None Merchant suggested price: Minimum: 0 Maximum: 0 Effect: Vita restoration How to Obtain: Various rats Comments: None Shop prices: NPC Sells: 0 NPC Buys: 0 Ginseng piece Vita : 60 Mana : 0 Level: 0 Path: Peasant Max. Held in 1 Slot: 1 Uses: 1 Crafts: None Other Uses: None Merchant suggested price: Minimum: 0 Maximum: 0 Effect: Vita restoration How to Obtain: Various rats Comments: None Shop prices: NPC Sells: 0 NPC Buys: 0 Grilled beef Vita : 800 Mana : 0 Level: 0 Path: Peasant Max. Held in 1 Slot: 25 Uses: 1 Crafts: None Other Uses: None Merchant suggested price: Minimum: 0 Maximum: 0 Effect: Vita restoration How to Obtain: Created by food preparation Comments: None Shop prices: NPC Sells: 0 NPC Buys: 0 Horse meat Vita : 200 Mana : 0 Level: 0 Path: Peasant Max. Held in 1 Slot: 100 Uses: 1 Crafts: None Other Uses: None Merchant suggested price: Minimum: 0 Maximum: 0 Effect: Vita restoration How to Obtain: Mythic horse cave Comments: Can be sold in shops Shop prices: NPC Sells: 12 NPC Buys: 12 Large fish Vita : 440 Mana : 0 Level: 0 Path: Peasant Max. Held in 1 Slot: 10 Uses: 1 Crafts: Fishing Other Uses: Needed for food preparation skill Merchant suggested price: Minimum: 0 Maximum: 0 Effect: Vita restoration How to Obtain: Fishing Comments: None Shop prices: NPC Sells: 0 NPC Buys: 0 Lean beef Vita : 500 Mana : 0 Level: 0 Path: Peasant Max. Held in 1 Slot: 50 Uses: 1 Crafts: Food preparation Other Uses: Needed for food preparation skill Merchant suggested price: Minimum: 0 Maximum: 0 Effect: Vita restoration How to Obtain: Mythic Oxen, Kugnae Mud Snake Comments: None Shop prices: NPC Sells: 0 NPC Buys: 0 Leech juice Vita : 0 Mana : 0 Level: 0 Path: Peasant Max. Held in 1 Slot: 4 Uses: 1 Crafts: None Other Uses: Gives up to 33% vita restoration when used Merchant suggested price: Minimum: 0 Maximum: 0 Effect: Vita restoration - 33% How to Obtain: Lost Mines Comments: Dropped by Leeches in Lost Mine events Shop prices: NPC Sells: 0 NPC Buys: 0 Life Blossom Vita : 300 Mana : 0 Level: 0 Path: Peasant Max. Held in 1 Slot: 1 Uses: 20 Crafts: None Other Uses: None Merchant suggested price: Minimum: 0 Maximum: 0 Effect: Vita restoration How to Obtain: None Comments: Bought from Bodhi's sanctum, Monk's Subpath Area Shop prices: NPC Sells: 600 NPC Buys: 300 Malodorous fish Vita : 80 Mana : 0 Level: 0 Path: Peasant Max. Held in 1 Slot: 100 Uses: 1 Crafts: None Other Uses: Trade for items in Chum's Fish Hut, Hamgyong nam-do Merchant suggested price: Minimum: 0 Maximum: 0 Effect: Vita restoration How to Obtain: River Ogres Comments: None Shop prices: NPC Sells: 0 NPC Buys: 0 Medium fish Vita : 360 Mana : 0 Level: 0 Path: Peasant Max. Held in 1 Slot: 10 Uses: 1 Crafts: Fishing Other Uses: Needed for food preparation skill Merchant suggested price: Minimum: 0 Maximum: 0 Effect: Vita restoration How to Obtain: Fishing Comments: None Shop prices: NPC Sells: 0 NPC Buys: 0 Mountain ginseng Vita : 10000 Mana : 0 Level: 0 Path: Peasant Max. Held in 1 Slot: 10 Uses: 1 Crafts: None Other Uses: Spells Merchant suggested price: Minimum: 2,000 Maximum: 5,000 Effect: Vita restoration How to Obtain: Clan Shops Comments: Dropped by Town Rabbit Cave bosses Shop prices: NPC Sells: 2,000 NPC Buys: 1,000 Noodles Vita : 300 Mana : 0 Level: 0 Path: Peasant Max. Held in 1 Slot: 1 Uses: 1 Crafts: Chef Other Uses: None Merchant suggested price: Minimum: 0 Maximum: 0 Effect: Vita restoration How to Obtain: None Comments: Prepared from Salt Block, Water Jug, and Flour by players with Food preparation skill. Shop prices: NPC Sells: 0 NPC Buys: 0 Peas Vita : 100 Mana : 0 Level: 0 Path: Peasant Max. Held in 1 Slot: 5 Uses: 1 Crafts: Gardening Other Uses: None Merchant suggested price: Minimum: 0 Maximum: 0 Effect: Vita restoration How to Obtain: None Comments: Dug from Kugnae and Wilderness Gardens Shop prices: NPC Sells: 0 NPC Buys: 0 Pork Vita : 128 Mana : 0 Level: 0 Path: Peasant Max. Held in 1 Slot: 1 Uses: 1 Crafts: None Other Uses: None Merchant suggested price: Minimum: 0 Maximum: 0 Effect: Vita restoration How to Obtain: Dropped in Mythic Pig Cave and Kugnae Snake Cave Comments: None Shop prices: NPC Sells: 10 NPC Buys: 5 Putrid fish Vita : 120 Mana : 0 Level: 0 Path: Peasant Max. Held in 1 Slot: 100 Uses: 1 Crafts: None Other Uses: Trade for items in Chum's Fish Hut, Hamgyong nam-do Merchant suggested price: Minimum: 0 Maximum: 0 Effect: Vita restoration How to Obtain: River Ogres Comments: None Shop prices: NPC Sells: 0 NPC Buys: 0 Rabbit meat Vita : 48 Mana : 0 Level: 0 Path: Peasant Max. Held in 1 Slot: 200 Uses: 1 Crafts: None Other Uses: Spell item Merchant suggested price: Minimum: 0 Maximum: 0 Effect: Needs for spells How to Obtain: Dropped by various rabbits Comments: None Shop prices: NPC Sells: 2 NPC Buys: 2 Red potion Vita : 0 Mana : 0 Level: 0 Path: Peasant Max. Held in 1 Slot: 2 Uses: 1 Crafts: None Other Uses: Need to weave magical net Merchant suggested price: Minimum: 0 Maximum: 0 Effect: Vita restoration - 100% How to Obtain: Potion Shops Comments: Restores all vitaEach attempt to weave a Magical Net needs 1 of these Shop prices: NPC Sells: 15,000 NPC Buys: 7,500 Repugnant fish Vita : 80 Mana : 0 Level: 0 Path: Peasant Max. Held in 1 Slot: 100 Uses: 1 Crafts: None Other Uses: Trade for items in Chum's Fish Hut, Hamgyong nam-do Merchant suggested price: Minimum: 0 Maximum: 0 Effect: Vita restoration How to Obtain: River Ogres Comments: None Shop prices: NPC Sells: 0 NPC Buys: 0 Roast chicken Vita : 1000 Mana : 0 Level: 0 Path: Peasant Max. Held in 1 Slot: 25 Uses: 1 Crafts: Food preparation Other Uses: None Merchant suggested price: Minimum: 0 Maximum: 0 Effect: Vita restoration How to Obtain: Food preparers Comments: Prepared from Bird or Chicken meat by players with Food preparation skill. Shop prices: NPC Sells: 0 NPC Buys: 0 Rose petals Vita : 900 Mana : 0 Level: 0 Path: Peasant Max. Held in 1 Slot: 50 Uses: 1 Crafts: None Other Uses: For husbands to use next to their wives Merchant suggested price: Minimum: 0 Maximum: 0 Effect: Causes husband and wife to wink. How to Obtain: Chapels Comments: If a wife eats this while standing next to her husband, she gets 960 vita. All other uses give 20 vita. Shop prices: NPC Sells: 20 NPC Buys: 0 Scrawny fish Vita : 180 Mana : 0 Level: 0 Path: Peasant Max. Held in 1 Slot: 10 Uses: 1 Crafts: Fishing Other Uses: Needed for food preparation skill Merchant suggested price: Minimum: 0 Maximum: 0 Effect: Vita restoration How to Obtain: Fishing Comments: None Shop prices: NPC Sells: 0 NPC Buys: 0 Seaweed Vita : 400 Mana : 0 Level: 0 Path: Peasant Max. Held in 1 Slot: 25 Uses: 1 Crafts: None Other Uses: None Merchant suggested price: Minimum: 0 Maximum: 0 Effect: Vita restoration How to Obtain: Dropped by Island Lobsters in Hausson. Dropped by most snakes in Woodlands Snake Cave. Comments: None Shop prices: NPC Sells: 0 NPC Buys: 0 Small fish Vita : 400 Mana : 0 Level: 0 Path: Peasant Max. Held in 1 Slot: 10 Uses: 1 Crafts: Fishing Other Uses: Needed for food preparation skill Merchant suggested price: Minimum: 0 Maximum: 0 Effect: Vita restoration How to Obtain: Fishing Comments: None Shop prices: NPC Sells: 0 NPC Buys: 0 Snake meat Vita : 100 Mana : 0 Level: 0 Path: Peasant Max. Held in 1 Slot: 100 Uses: 1 Crafts: None Other Uses: Crafts Merchant suggested price: Minimum: 0 Maximum: 0 Effect: Vita restoration How to Obtain: Various snakes Comments: None Shop prices: NPC Sells: 0 NPC Buys: 0 Tasty fish Vita : 540 Mana : 0 Level: 0 Path: Peasant Max. Held in 1 Slot: 10 Uses: 1 Crafts: Fishing Other Uses: Needed for food preparation skill Merchant suggested price: Minimum: 0 Maximum: 0 Effect: Vita restoration How to Obtain: Fishing Comments: None Shop prices: NPC Sells: 0 NPC Buys: 0 Tiger meat Vita : 100 Mana : 0 Level: 0 Path: Peasant Max. Held in 1 Slot: 10 Uses: 1 Crafts: Food preparation Other Uses: Subpath quest item Merchant suggested price: Minimum: 0 Maximum: 0 Effect: Vita restoration How to Obtain: Dropped by Iron lab tigers Comments: None Shop prices: NPC Sells: 100 NPC Buys: 50 Tiger's heart Vita : 1000 Mana : 0 Level: 0 Path: Peasant Max. Held in 1 Slot: 20 Uses: 1 Crafts: None Other Uses: None Merchant suggested price: Minimum: 0 Maximum: 0 Effect: Vita restoration How to Obtain: Shops, monsters, poet Call of the Wild spell Comments: None Shop prices: NPC Sells: 60 NPC Buys: 30 Tiny fish Vita : 100 Mana : 0 Level: 0 Path: Peasant Max. Held in 1 Slot: 10 Uses: 1 Crafts: Fishing Other Uses: Needed for food preparation skill Merchant suggested price: Minimum: 0 Maximum: 0 Effect: Vita restoration How to Obtain: Fishing Comments: None Shop prices: NPC Sells: 0 NPC Buys: 0 Violet potion Vita : 200 Mana : 0 Level: 0 Path: Peasant Max. Held in 1 Slot: 50 Uses: 1 Crafts: None Other Uses: None Merchant suggested price: Minimum: 0 Maximum: 0 Effect: Restores 200 vita How to Obtain: Potion Shops Comments: Restores 200 vita Shop prices: NPC Sells: 30 NPC Buys: 15 Watermelon Vita : 800 Mana : 0 Level: 0 Path: Peasant Max. Held in 1 Slot: 1 Uses: 1 Crafts: None Other Uses: None Merchant suggested price: Minimum: 0 Maximum: 0 Effect: Vita restoration How to Obtain: Halloween events Comments: None Shop prices: NPC Sells: 0 NPC Buys: 0 Wolf meat Vita : 48 Mana : 0 Level: 0 Path: Peasant Max. Held in 1 Slot: 1 Uses: 1 Crafts: None Other Uses: Needed for chung ryong helm(et) Merchant suggested price: Minimum: 0 Maximum: 0 Effect: Vita restoration How to Obtain: Dropped by various wolves Comments: None Shop prices: NPC Sells: 4 NPC Buys: 2 Yellow potion Vita : 50 Mana : 0 Level: 0 Path: Peasant Max. Held in 1 Slot: 1 Uses: 1 Crafts: None Other Uses: None Merchant suggested price: Minimum: 0 Maximum: 0 Effect: Restores 50 vita How to Obtain: Potion Shops Comments: Restores 50 vita Shop prices: NPC Sells: 10 NPC Buys: 5 Young ginseng Vita : 40 Mana : 0 Level: 0 Path: Peasant Max. Held in 1 Slot: 1 Uses: 1 Crafts: None Other Uses: None Merchant suggested price: Minimum: 0 Maximum: 0 Effect: Vita restoration How to Obtain: Chu rua Comments: None Shop prices: NPC Sells: 0 NPC Buys: 0",
      "category": "item",
      "path": [
        "Peasant"
      ],
      "level_tier": "",
      "stats": {
        "Vita": 248,
        "Mana": 0
      },
      "stack_size": 52,
      "crafts": [
        "Alchemy"
      ],
      "other_uses": [
        "Crafts"
      ],
      "effect": "Restores 248 vitaUsed by Alchemists",
      "obtain": [
        "Arena Shops, Dropped by Deers"
      ],
      "npc_buys": 5
    },
    {
      "id": "vita_1_mana_30_level_0_path_peasant_max_held_in_1_slot_1_uses_200_crafts_none_other_uses_mana_restoration_merchant_suggested_price_minimum_0_maximum_0_effect_restores_30_mana_and_takes_1_vita_how_to_obtain_taverns_comments_none_shop_prices_npc_sells_10_npc_buys_5",
      "name": "Vita : -1 Mana : 30 Level: 0 Path: Peasant Max. Held in 1 Slot: 1 Uses: 200 Crafts: None Other Uses: Mana restoration Merchant suggested price: Minimum: 0 Maximum: 0 Effect: Restores 30 mana and takes 1 vita How to Obtain: Taverns Comments: None Shop prices: NPC Sells: 10 NPC Buys: 5",
      "category": "item",
      "level_tier": "",
      "stats": {
        "Vita": -1,
        "Mana": 30
      },
      "stack_size": 1,
      "crafts": [],
      "other_uses": [
        "Mana restoration"
      ],
      "effect": "Restores 30 mana and takes 1 vita",
      "obtain": [
        "Taverns"
      ],
      "comments": null,
      "npc_buys": 5,
      "path": [
        "Peasant"
      ]
    },
    {
      "id": "vita_1_mana_500_level_0_path_peasant_max_held_in_1_slot_1_uses_64_crafts_none_other_uses_subpath_spell_item_merchant_suggested_price_minimum_0_maximum_0_effect_mana_restoration_how_to_obtain_random_merchant_comments_none_shop_prices_npc_sells_5_000_npc_buys_0",
      "name": "Vita : -1 Mana : 500 Level: 0 Path: Peasant Max. Held in 1 Slot: 1 Uses: 64 Crafts: None Other Uses: Subpath spell item Merchant suggested price: Minimum: 0 Maximum: 0 Effect: Mana restoration How to Obtain: Random Merchant Comments: None Shop prices: NPC Sells: 5,000 NPC Buys: 0",
      "category": "item",
      "path": [
        "Peasant"
      ],
      "level_tier": "",
      "stats": {
        "Vita": -1,
        "Mana": 500
      },
      "stack_size": 1,
      "other_uses": [
        "Subpath spell item"
      ],
      "effect": "Mana restoration",
      "obtain": [
        "Random Merchant"
      ],
      "npc_buys": 0
    },
    {
      "id": "vita_10_mana_100_level_0_path_peasant_max_held_in_1_slot_1_uses_20_crafts_none_other_uses_none_merchant_suggested_price_minimum_0_maximum_0_effect_mana_restoration_how_to_obtain_home_of_ugh_hamgyong_nam_do_comments_none_shop_prices_npc_sells_100_npc_buys_50",
      "name": "Vita : -10 Mana : 100 Level: 0 Path: Peasant Max. Held in 1 Slot: 1 Uses: 20 Crafts: None Other Uses: None Merchant suggested price: Minimum: 0 Maximum: 0 Effect: Mana restoration How to Obtain: Home of Ugh, Hamgyong nam-do Comments: None Shop prices: NPC Sells: 100 NPC Buys: 50",
      "category": "item",
      "level_tier": "",
      "stats": {
        "Vita": -10,
        "Mana": 100
      },
      "stack_size": 1,
      "crafts": [],
      "other_uses": [],
      "effect": "Mana restoration",
      "obtain": [
        "Home of Ugh, Hamgyong nam-do"
      ],
      "comments": null,
      "npc_buys": 50,
      "path": [
        "Peasant"
      ]
    },
    {
      "id": "vita_10_mana_350_level_0_path_peasant_max_held_in_1_slot_1_uses_80_crafts_none_other_uses_mana_restoration_merchant_suggested_price_minimum_300_maximum_600_effect_restores_350_mana_and_takes_10_vita_how_to_obtain_bagai_shop_comments_restores_350_mana_shop_prices_npc_sells_600_npc_buys_300",
      "name": "Vita : -10 Mana : 350 Level: 0 Path: Peasant Max. Held in 1 Slot: 1 Uses: 80 Crafts: None Other Uses: Mana restoration Merchant suggested price: Minimum: 300 Maximum: 600 Effect: Restores 350 mana and takes 10 vita How to Obtain: Bagai Shop Comments: Restores 350 mana Shop prices: NPC Sells: 600 NPC Buys: 300",
      "category": "item",
      "level_tier": "",
      "stats": {
        "Vita": -10,
        "Mana": 350
      },
      "stack_size": 1,
      "crafts": [],
      "other_uses": [
        "Mana restoration"
      ],
      "effect": "Restores 350 mana and takes 10 vita",
      "obtain": [
        "Bagai Shop"
      ],
      "comments": "Restores 350 mana",
      "npc_buys": 300,
      "path": [
        "Peasant"
      ]
    },
    {
      "id": "vita_15_mana_300_level_0_path_peasant_max_held_in_1_slot_1_uses_100_crafts_none_other_uses_none_merchant_suggested_price_minimum_0_maximum_0_effect_mana_restoration_how_to_obtain_arena_and_alchemist_shops_guild_halls_comments_none_shop_prices_npc_sells_400_npc_buys_200",
      "name": "Vita : -15 Mana : 300 Level: 0 Path: Peasant Max. Held in 1 Slot: 1 Uses: 100 Crafts: None Other Uses: None Merchant suggested price: Minimum: 0 Maximum: 0 Effect: Mana restoration How to Obtain: Arena and Alchemist Shops, Guild Halls Comments: None Shop prices: NPC Sells: 400 NPC Buys: 200",
      "category": "item",
      "level_tier": "",
      "stats": {
        "Vita": -15,
        "Mana": 300
      },
      "stack_size": 1,
      "crafts": [],
      "other_uses": [],
      "effect": "Mana restoration",
      "obtain": [
        "Arena and Alchemist Shops, Guild Halls"
      ],
      "comments": null,
      "npc_buys": 200,
      "path": [
        "Peasant"
      ]
    },
    {
      "id": "vita_25_mana_325_level_0_path_peasant_max_held_in_1_slot_1_uses_39_crafts_none_other_uses_none_merchant_suggested_price_minimum_0_maximum_0_effect_mana_restoration_how_to_obtain_home_of_ugh_hamgyong_nam_do_comments_none_shop_prices_npc_sells_100_npc_buys_50",
      "name": "Vita : -25 Mana : 325 Level: 0 Path: Peasant Max. Held in 1 Slot: 1 Uses: 39 Crafts: None Other Uses: None Merchant suggested price: Minimum: 0 Maximum: 0 Effect: Mana restoration How to Obtain: Home of Ugh, Hamgyong nam-do Comments: None Shop prices: NPC Sells: 100 NPC Buys: 50",
      "category": "item",
      "level_tier": "",
      "stats": {
        "Vita": -25,
        "Mana": 325
      },
      "stack_size": 1,
      "crafts": [],
      "other_uses": [],
      "effect": "Mana restoration",
      "obtain": [
        "Home of Ugh, Hamgyong nam-do"
      ],
      "comments": null,
      "npc_buys": 50,
      "path": [
        "Peasant"
      ]
    },
    {
      "id": "vita_5_mana_100_level_0_path_peasant_max_held_in_1_slot_1_uses_50_crafts_alchemy_other_uses_crafts_merchant_suggested_price_minimum_0_maximum_0_effect_restores_100_mana_takes_5_vita_how_to_obtain_potion_shops_comments_none_shop_prices_npc_sells_150_npc_buys_75",
      "name": "Vita : -5 Mana : 100 Level: 0 Path: Peasant Max. Held in 1 Slot: 1 Uses: 50 Crafts: Alchemy Other Uses: Crafts Merchant suggested price: Minimum: 0 Maximum: 0 Effect: Restores 100 mana, takes 5 vita How to Obtain: Potion Shops Comments: None Shop prices: NPC Sells: 150 NPC Buys: 75",
      "category": "item",
      "level_tier": "",
      "stats": {
        "Vita": -5,
        "Mana": 100
      },
      "stack_size": 1,
      "crafts": [
        "Alchemy"
      ],
      "other_uses": [
        "Crafts"
      ],
      "effect": "Restores 100 mana, takes 5 vita",
      "obtain": [
        "Potion Shops"
      ],
      "comments": null,
      "npc_buys": 75,
      "path": [
        "Peasant"
      ]
    },
    {
      "id": "vita_5_mana_80_level_0_path_peasant_max_held_in_1_slot_1_uses_50_crafts_alchemy_other_uses_crafts_merchant_suggested_price_minimum_0_maximum_0_effect_none_how_to_obtain_potion_shops_comments_none_shop_prices_npc_sells_100_npc_buys_50",
      "name": "Vita : -5 Mana : 80 Level: 0 Path: Peasant Max. Held in 1 Slot: 1 Uses: 50 Crafts: Alchemy Other Uses: Crafts Merchant suggested price: Minimum: 0 Maximum: 0 Effect: None How to Obtain: Potion Shops Comments: None Shop prices: NPC Sells: 100 NPC Buys: 50",
      "category": "item",
      "level_tier": "",
      "stats": {
        "Vita": -5,
        "Mana": 80
      },
      "stack_size": 1,
      "crafts": [
        "Alchemy"
      ],
      "other_uses": [
        "Crafts"
      ],
      "effect": null,
      "obtain": [
        "Potion Shops"
      ],
      "comments": null,
      "npc_buys": 50,
      "path": [
        "Peasant"
      ]
    },
    {
      "id": "vita_50_mana_1000_level_0_path_peasant_max_held_in_1_slot_1_uses_5_crafts_none_other_uses_none_merchant_suggested_price_minimum_0_maximum_0_effect_mana_restoration_how_to_obtain_the_shattering_event_comments_none_shop_prices_npc_sells_0_npc_buys_0",
      "name": "Vita : -50 Mana : 1000 Level: 0 Path: Peasant Max. Held in 1 Slot: 1 Uses: 5 Crafts: None Other Uses: None Merchant suggested price: Minimum: 0 Maximum: 0 Effect: Mana restoration How to Obtain: The Shattering Event Comments: None Shop prices: NPC Sells: 0 NPC Buys: 0",
      "category": "item",
      "level_tier": "",
      "stats": {
        "Vita": -50,
        "Mana": 1000
      },
      "stack_size": 1,
      "crafts": [],
      "other_uses": [],
      "effect": "Mana restoration",
      "obtain": [
        "The Shattering Event"
      ],
      "comments": null,
      "npc_buys": 0,
      "path": [
        "Peasant"
      ]
    },
    {
      "id": "vita_50_mana_450_level_0_path_peasant_max_held_in_1_slot_1_uses_50_crafts_none_other_uses_none_merchant_suggested_price_minimum_0_maximum_0_effect_mana_restoration_how_to_obtain_kaming_s_encampment_messenger_comments_none_shop_prices_npc_sells_200_npc_buys_100",
      "name": "Vita : -50 Mana : 450 Level: 0 Path: Peasant Max. Held in 1 Slot: 1 Uses: 50 Crafts: None Other Uses: None Merchant suggested price: Minimum: 0 Maximum: 0 Effect: Mana restoration How to Obtain: KaMing's Encampment Messenger Comments: None Shop prices: NPC Sells: 200 NPC Buys: 100",
      "category": "item",
      "level_tier": "",
      "stats": {
        "Vita": -50,
        "Mana": 450
      },
      "stack_size": 1,
      "crafts": [],
      "other_uses": [],
      "effect": "Mana restoration",
      "obtain": [
        "KaMing's Encampment Messenger"
      ],
      "comments": null,
      "npc_buys": 100,
      "path": [
        "Peasant"
      ]
    },
    {
      "id": "vita_0_mana_0_level_0_path_peasant_max_held_in_1_slot_1_uses_1_crafts_farming_other_uses_crafts_merchant_suggested_price_minimum_200_maximum_100_effect_used_for_cutting_wood_how_to_obtain_shops_comments_used_for_cutting_wood_shop_prices_npc_sells_200_npc_buys_100",
      "name": "Vita : 0 Mana : 0 Level: 0 Path: Peasant Max. Held in 1 Slot: 1 Uses: 1 Crafts: Farming Other Uses: Crafts Merchant suggested price: Minimum: 200 Maximum: 100 Effect: Used for cutting wood How to Obtain: Shops Comments: Used for cutting wood Shop prices: NPC Sells: 200 NPC Buys: 100",
      "category": "item",
      "path": [
        "Peasant"
      ],
      "level_tier": "",
      "stats": {
        "Vita": 0,
        "Mana": 0
      },
      "stack_size": 1,
      "crafts": [
        "Farming"
      ],
      "other_uses": [
        "Crafts"
      ],
      "effect": "Used for cutting wood",
      "obtain": [
        "Shops"
      ],
      "comments": "Used for cutting wood",
      "npc_buys": 100
    },
    {
      "id": "vita_0_mana_0_level_0_path_peasant_max_held_in_1_slot_1_uses_1_crafts_farming_other_uses_crafts_merchant_suggested_price_minimum_200_maximum_100_effect_used_for_gathering_coconuts_how_to_obtain_shops_comments_shop_prices_npc_sells_200_npc_buys_100",
      "name": "Vita : 0 Mana : 0 Level: 0 Path: Peasant Max. Held in 1 Slot: 1 Uses: 1 Crafts: Farming Other Uses: Crafts Merchant suggested price: Minimum: 200 Maximum: 100 Effect: Used for gathering coconuts How to Obtain: Shops Comments: Shop prices: NPC Sells: 200 NPC Buys: 100",
      "category": "item",
      "path": [
        "Peasant"
      ],
      "level_tier": "",
      "stats": {
        "Vita": 0,
        "Mana": 0
      },
      "stack_size": 1,
      "crafts": [
        "Farming"
      ],
      "other_uses": [
        "Crafts"
      ],
      "effect": "Used for gathering coconuts",
      "obtain": [
        "Shops"
      ],
      "comments": "Shop prices:",
      "npc_buys": 100
    },
    {
      "id": "vita_0_mana_0_level_0_path_peasant_max_held_in_1_slot_1_uses_1_crafts_fishing_other_uses_merchant_suggested_price_minimum_0_maximum_0_effect_vita_restoration_how_to_obtain_fishing_comments_none_shop_prices_npc_sells_0_npc_buys_0",
      "name": "Vita : 0 Mana : 0 Level: 0 Path: Peasant Max. Held in 1 Slot: 1 Uses: 1 Crafts: Fishing Other Uses: Merchant suggested price: Minimum: 0 Maximum: 0 Effect: Vita restoration How to Obtain: Fishing Comments: None Shop prices: NPC Sells: 0 NPC Buys: 0",
      "category": "item",
      "path": [
        "Peasant"
      ],
      "level_tier": "",
      "stats": {
        "Vita": 0,
        "Mana": 0
      },
      "stack_size": 1,
      "crafts": [
        "Fishing"
      ],
      "other_uses": [
        "Merchant suggested price:"
      ],
      "effect": "Vita restoration",
      "obtain": [
        "Fishing"
      ],
      "npc_buys": 0
    },
    {
      "id": "vita_0_mana_0_level_0_path_peasant_max_held_in_1_slot_1_uses_1_crafts_mining_other_uses_crafts_merchant_suggested_price_minimum_20_maximum_40_effect_used_for_mining_how_to_obtain_shops_comments_shop_prices_npc_sells_40_npc_buys_20",
      "name": "Vita : 0 Mana : 0 Level: 0 Path: Peasant Max. Held in 1 Slot: 1 Uses: 1 Crafts: Mining Other Uses: Crafts Merchant suggested price: Minimum: 20 Maximum: 40 Effect: Used for mining How to Obtain: Shops Comments: Shop prices: NPC Sells: 40 NPC Buys: 20",
      "category": "item",
      "path": [
        "Peasant"
      ],
      "level_tier": "",
      "stats": {
        "Vita": 0,
        "Mana": 0
      },
      "stack_size": 1,
      "crafts": [
        "Mining"
      ],
      "other_uses": [
        "Crafts"
      ],
      "effect": "Used for mining",
      "obtain": [
        "Shops"
      ],
      "comments": "Shop prices:",
      "npc_buys": 20
    },
    {
      "id": "vita_0_mana_0_level_0_path_peasant_max_held_in_1_slot_1_uses_1_crafts_none_other_uses_change_totem_at_shrinesjoin_npc_subpath_at_kugnae_scroll_shop_merchant_suggested_price_minimum_0_maximum_0_effect_none_how_to_obtain_mythic_dragon_key_bosses_comments_needed_for_lesser_alliance_with_mythic_dog_shop_prices_npc_sells_0_npc_buys_0",
      "name": "Vita : 0 Mana : 0 Level: 0 Path: Peasant Max. Held in 1 Slot: 1 Uses: 1 Crafts: None Other Uses: Change totem at shrinesJoin NPC subpath at Kugnae Scroll shop Merchant suggested price: Minimum: 0 Maximum: 0 Effect: None How to Obtain: Mythic Dragon Key Bosses Comments: Needed for Lesser Alliance with Mythic Dog Shop prices: NPC Sells: 0 NPC Buys: 0",
      "category": "item",
      "path": [
        "Peasant"
      ],
      "level_tier": "",
      "stats": {
        "Vita": 0,
        "Mana": 0
      },
      "stack_size": 1,
      "other_uses": [
        "Change totem at shrinesJoin NPC subpath at Kugnae Scroll shop"
      ],
      "obtain": [
        "Mythic Dragon Key Bosses"
      ],
      "comments": "Needed for Lesser Alliance with Mythic Dog",
      "npc_buys": 0
    },
    {
      "id": "vita_0_mana_0_level_0_path_peasant_max_held_in_1_slot_1_uses_1_crafts_none_other_uses_change_totem_at_shrinesjoin_npc_subpath_at_kugnae_scroll_shop_merchant_suggested_price_minimum_0_maximum_0_effect_none_how_to_obtain_mythic_sheep_key_bosses_comments_needed_for_lesser_alliance_with_mythic_ox_shop_prices_npc_sells_0_npc_buys_0",
      "name": "Vita : 0 Mana : 0 Level: 0 Path: Peasant Max. Held in 1 Slot: 1 Uses: 1 Crafts: None Other Uses: Change totem at shrinesJoin NPC subpath at Kugnae Scroll shop Merchant suggested price: Minimum: 0 Maximum: 0 Effect: None How to Obtain: Mythic Sheep Key Bosses Comments: Needed for Lesser Alliance with Mythic Ox Shop prices: NPC Sells: 0 NPC Buys: 0",
      "category": "item",
      "path": [
        "Peasant"
      ],
      "level_tier": "",
      "stats": {
        "Vita": 0,
        "Mana": 0
      },
      "stack_size": 1,
      "other_uses": [
        "Change totem at shrinesJoin NPC subpath at Kugnae Scroll shop"
      ],
      "obtain": [
        "Mythic Sheep Key Bosses"
      ],
      "comments": "Needed for Lesser Alliance with Mythic Ox",
      "npc_buys": 0
    },
    {
      "id": "vita_0_mana_0_level_0_path_peasant_max_held_in_1_slot_1_uses_1_crafts_none_other_uses_change_totem_at_shrinesjoin_npc_subpath_at_kugnae_scroll_shop_merchant_suggested_price_minimum_0_maximum_0_effect_none_how_to_obtain_mythic_snake_key_bosses_comments_needed_for_lesser_alliance_with_mythic_pig_shop_prices_npc_sells_0_npc_buys_0",
      "name": "Vita : 0 Mana : 0 Level: 0 Path: Peasant Max. Held in 1 Slot: 1 Uses: 1 Crafts: None Other Uses: Change totem at shrinesJoin NPC subpath at Kugnae Scroll shop Merchant suggested price: Minimum: 0 Maximum: 0 Effect: None How to Obtain: Mythic Snake Key Bosses Comments: Needed for Lesser Alliance with Mythic Pig Shop prices: NPC Sells: 0 NPC Buys: 0",
      "category": "item",
      "path": [
        "Peasant"
      ],
      "level_tier": "",
      "stats": {
        "Vita": 0,
        "Mana": 0
      },
      "stack_size": 1,
      "other_uses": [
        "Change totem at shrinesJoin NPC subpath at Kugnae Scroll shop"
      ],
      "obtain": [
        "Mythic Snake Key Bosses"
      ],
      "comments": "Needed for Lesser Alliance with Mythic Pig",
      "npc_buys": 0
    },
    {
      "id": "vita_0_mana_0_level_0_path_peasant_max_held_in_1_slot_1_uses_1_crafts_none_other_uses_change_totem_at_shrinesjoin_npc_subpath_at_kugnae_scroll_shop_merchant_suggested_price_minimum_0_maximum_0_effect_none_how_to_obtain_mythic_tiger_key_bosses_comments_needed_for_lesser_alliance_with_mythic_monkey_shop_prices_npc_sells_0_npc_buys_0",
      "name": "Vita : 0 Mana : 0 Level: 0 Path: Peasant Max. Held in 1 Slot: 1 Uses: 1 Crafts: None Other Uses: Change totem at shrinesJoin NPC subpath at Kugnae Scroll shop Merchant suggested price: Minimum: 0 Maximum: 0 Effect: None How to Obtain: Mythic Tiger Key Bosses Comments: Needed for Lesser Alliance with Mythic Monkey Shop prices: NPC Sells: 0 NPC Buys: 0",
      "category": "item",
      "path": [
        "Peasant"
      ],
      "level_tier": "",
      "stats": {
        "Vita": 0,
        "Mana": 0
      },
      "stack_size": 1,
      "other_uses": [
        "Change totem at shrinesJoin NPC subpath at Kugnae Scroll shop"
      ],
      "obtain": [
        "Mythic Tiger Key Bosses"
      ],
      "comments": "Needed for Lesser Alliance with Mythic Monkey",
      "npc_buys": 0
    },
    {
      "id": "vita_0_mana_0_level_0_path_peasant_max_held_in_1_slot_1_uses_1_crafts_none_other_uses_make_bouquets_merchant_suggested_price_minimum_0_maximum_0_effect_none_how_to_obtain_created_by_druids_comments_make_great_decorations_shop_prices_npc_sells_0_npc_buys_0",
      "name": "Vita : 0 Mana : 0 Level: 0 Path: Peasant Max. Held in 1 Slot: 1 Uses: 1 Crafts: None Other Uses: Make bouquets Merchant suggested price: Minimum: 0 Maximum: 0 Effect: None How to Obtain: Created by Druids Comments: Make great decorations! Shop prices: NPC Sells: 0 NPC Buys: 0",
      "category": "item",
      "level_tier": "",
      "stats": {
        "Vita": 0,
        "Mana": 0
      },
      "stack_size": 1,
      "crafts": [],
      "other_uses": [
        "Make bouquets"
      ],
      "effect": null,
      "obtain": [
        "Created by Druids"
      ],
      "comments": "Make great decorations!",
      "npc_buys": 0,
      "path": [
        "Peasant"
      ]
    },
    {
      "id": "vita_0_mana_0_level_0_path_peasant_max_held_in_1_slot_1_uses_1_crafts_none_other_uses_make_bouquets_merchant_suggested_price_minimum_0_maximum_0_effect_none_how_to_obtain_created_by_druids_comments_these_were_created_when_king_yuri_fell_in_love_with_malady_druids_can_create_them_shop_prices_npc_sells_0_npc_buys_0",
      "name": "Vita : 0 Mana : 0 Level: 0 Path: Peasant Max. Held in 1 Slot: 1 Uses: 1 Crafts: None Other Uses: Make bouquets Merchant suggested price: Minimum: 0 Maximum: 0 Effect: None How to Obtain: Created by Druids Comments: These were created when King Yuri fell in love with Malady. Druids can create them. Shop prices: NPC Sells: 0 NPC Buys: 0",
      "category": "item",
      "path": [
        "Peasant"
      ],
      "level_tier": "",
      "stats": {
        "Vita": 0,
        "Mana": 0
      },
      "stack_size": 1,
      "other_uses": [
        "Make bouquets"
      ],
      "obtain": [
        "Created by Druids"
      ],
      "comments": "These were created when King Yuri fell in love with Malady. Druids can create them.",
      "npc_buys": 0
    },
    {
      "id": "vita_0_mana_0_level_0_path_peasant_max_held_in_1_slot_1_uses_1_crafts_none_other_uses_make_bouquets_merchant_suggested_price_minimum_0_maximum_0_effect_none_how_to_obtain_walk_past_a_rose_bush_comments_make_great_decorations_shop_prices_npc_sells_0_npc_buys_0",
      "name": "Vita : 0 Mana : 0 Level: 0 Path: Peasant Max. Held in 1 Slot: 1 Uses: 1 Crafts: None Other Uses: Make bouquets Merchant suggested price: Minimum: 0 Maximum: 0 Effect: None How to Obtain: Walk past a rose bush! Comments: Make great decorations! Shop prices: NPC Sells: 0 NPC Buys: 0",
      "category": "item",
      "path": [
        "Peasant"
      ],
      "level_tier": "",
      "stats": {
        "Vita": 0,
        "Mana": 0
      },
      "stack_size": 1,
      "other_uses": [
        "Make bouquets"
      ],
      "obtain": [
        "Walk past a rose bush!"
      ],
      "comments": "Make great decorations!",
      "npc_buys": 0
    },
    {
      "id": "vita_0_mana_0_level_0_path_peasant_max_held_in_1_slot_1_uses_1_crafts_none_other_uses_needed_to_make_scroll_of_defense_merchant_suggested_price_minimum_0_maximum_0_effect_casts_harden_armor_how_to_obtain_buy_in_kugnae_baek_s_shop_comments_none_shop_prices_npc_sells_2_000_npc_buys_1_000",
      "name": "Vita : 0 Mana : 0 Level: 0 Path: Peasant Max. Held in 1 Slot: 1 Uses: 1 Crafts: None Other Uses: Needed to make Scroll of defense Merchant suggested price: Minimum: 0 Maximum: 0 Effect: Casts Harden Armor How to Obtain: Buy in Kugnae, Baek's shop Comments: None Shop prices: NPC Sells: 2,000 NPC Buys: 1,000",
      "category": "item",
      "path": [
        "Peasant"
      ],
      "level_tier": "",
      "stats": {
        "Vita": 0,
        "Mana": 0
      },
      "stack_size": 1,
      "other_uses": [
        "Needed to make Scroll of defense"
      ],
      "effect": "Casts Harden Armor",
      "obtain": [
        "Buy in Kugnae, Baek's shop"
      ],
      "npc_buys": 1
    },
    {
      "id": "vita_0_mana_0_level_0_path_peasant_max_held_in_1_slot_1_uses_1_crafts_none_other_uses_needed_to_make_scroll_of_defense_merchant_suggested_price_minimum_0_maximum_0_effect_casts_purge_how_to_obtain_buy_in_kugnae_baek_s_shop_comments_none_shop_prices_npc_sells_50_npc_buys_25",
      "name": "Vita : 0 Mana : 0 Level: 0 Path: Peasant Max. Held in 1 Slot: 1 Uses: 1 Crafts: None Other Uses: Needed to make Scroll of defense Merchant suggested price: Minimum: 0 Maximum: 0 Effect: Casts Purge How to Obtain: Buy in Kugnae, Baek's shop Comments: None Shop prices: NPC Sells: 50 NPC Buys: 25",
      "category": "item",
      "path": [
        "Peasant"
      ],
      "level_tier": "",
      "stats": {
        "Vita": 0,
        "Mana": 0
      },
      "stack_size": 1,
      "other_uses": [
        "Needed to make Scroll of defense"
      ],
      "effect": "Casts Purge",
      "obtain": [
        "Buy in Kugnae, Baek's shop"
      ],
      "npc_buys": 25
    },
    {
      "id": "vita_0_mana_0_level_0_path_peasant_max_held_in_1_slot_1_uses_1_crafts_none_other_uses_needed_to_smelt_ore_merchant_suggested_price_minimum_0_maximum_0_effect_needed_by_smelters_how_to_obtain_messenger_shops_comments_none_shop_prices_npc_sells_100_npc_buys_50",
      "name": "Vita : 0 Mana : 0 Level: 0 Path: Peasant Max. Held in 1 Slot: 1 Uses: 1 Crafts: None Other Uses: Needed to Smelt ore Merchant suggested price: Minimum: 0 Maximum: 0 Effect: Needed by Smelters How to Obtain: Messenger shops Comments: None Shop prices: NPC Sells: 100 NPC Buys: 50",
      "category": "item",
      "level_tier": "",
      "stats": {
        "Vita": 0,
        "Mana": 0
      },
      "stack_size": 1,
      "crafts": [],
      "other_uses": [
        "Needed to Smelt ore"
      ],
      "effect": "Needed by Smelters",
      "obtain": [
        "Messenger shops"
      ],
      "comments": null,
      "npc_buys": 50,
      "path": [
        "Peasant"
      ]
    },
    {
      "id": "vita_0_mana_0_level_0_path_peasant_max_held_in_1_slot_1_uses_1_crafts_none_other_uses_none_merchant_suggested_price_minimum_0_maximum_0_effect_1_coin_how_to_obtain_none_comments_none_shop_prices_npc_sells_0_npc_buys_0",
      "name": "Vita : 0 Mana : 0 Level: 0 Path: Peasant Max. Held in 1 Slot: 1 Uses: 1 Crafts: None Other Uses: None Merchant suggested price: Minimum: 0 Maximum: 0 Effect: 1 coin How to Obtain: None Comments: None Shop prices: NPC Sells: 0 NPC Buys: 0",
      "category": "item",
      "path": [
        "Peasant"
      ],
      "level_tier": "",
      "stats": {
        "Vita": 0,
        "Mana": 0
      },
      "stack_size": 1,
      "effect": "1 coin",
      "obtain": [
        "None"
      ],
      "npc_buys": 0
    }
  ]
}